Workbook

Sheet cross_sector_insights_tp
A1: ID | B1: Name | C1: Scope | D1: Perspective | E1: s001:Construction | F1: s002:Manufacturing | G1: s003:Health Services | H1: field
A2: TP01 | B2: Model-based Knowledge Representation and Simulation | C2: Uses BIM, 3D/4D models, engineering simulations, virtual models, and computational scenarios to represent assets, environments, construction processes, system behavior, and performance relationships. | D2: Digital Codification | E2: {=IFERROR(INDEX(s001_insights!F:F,MATCH("s001M01"&A2,s001_insights!A:A,0)),"")} -> TK06 Trained Sensory and Perceptual Recognition | F2: {=IFERROR(INDEX(s002_insights!F:F,MATCH("s002M01"&A2,s002_insights!A:A,0)),"")} | G2: {=IFERROR(INDEX(s003_insights!F:F,MATCH("s003M01"&A2,s003_insights!A:A,0)),"")} -> TK05 Practised Motor and Tool-Operation Skill TK06 Trained Sensory and Perceptual Recognition TK10 Shared Professional Norms and Standards of Judgment | H2: =3-COUNTIF(E2:G2,"") -> 2 | J2: <TP01, TK06> | K2: <TP01, TK05> <TP01, TK10>
A3: TP02 | B3: Spatial Knowledge Capture and Geospatial Reconstruction | C3: Uses UAVs, photogrammetry, laser scanning, GIS, and surveying technologies to convert physical and spatial conditions into measurable digital representations. | D3: Digital Codification | E3: {=IFERROR(INDEX(s001_insights!F:F,MATCH("s001M01"&A3,s001_insights!A:A,0)),"")} | F3: {=IFERROR(INDEX(s002_insights!F:F,MATCH("s002M01"&A3,s002_insights!A:A,0)),"")} | G3: {=IFERROR(INDEX(s003_insights!F:F,MATCH("s003M01"&A3,s003_insights!A:A,0)),"")} | H3: =3-COUNTIF(E3:G3,"") -> 0
A4: TP03 | B4: Situated Experiential Learning through Extended Reality | C4: Uses VR, AR, MR, CAVE, or hybrid XR environments to support embodied rehearsal, contextual guidance, historical interpretation, hazard recognition, and situated knowledge transfer. | D4: Experiential Amplification | E4: {=IFERROR(INDEX(s001_insights!F:F,MATCH("s001M01"&A4,s001_insights!A:A,0)),"")} -> TK05 Practised Motor and Tool-Operation Skill TK06 Trained Sensory and Perceptual Recognition TK07 Embodied Posture, Balance, and Spatial Control TK08 Immediate Embodied Response to Changing Conditions TK10 Shared Professional Norms and Standards of Judgment | F4: {=IFERROR(INDEX(s002_insights!F:F,MATCH("s002M01"&A4,s002_insights!A:A,0)),"")} -> TK04 Unrecognized or Unarticulated Personal Know-how TK05 Practised Motor and Tool-Operation Skill TK06 Trained Sensory and Perceptual Recognition TK07 Embodied Posture, Balance, and Spatial Control | G4: {=IFERROR(INDEX(s003_insights!F:F,MATCH("s003M01"&A4,s003_insights!A:A,0)),"")} -> TK05 Practised Motor and Tool-Operation Skill TK06 Trained Sensory and Perceptual Recognition TK08 Immediate Embodied Response to Changing Conditions TK11 Informal Coordination, Communication, and Escalation Know-how TK10 Shared Professional Norms and Standards of Judgment | H4: =3-COUNTIF(E4:G4,"") -> 3 | I4: <TP03, TK05> <TP03, TK06> | J4: <TP03, TK07> <TP03, TK08> <TP03, TK10> | K4: <TP03, TK04> <TP03, TK11>
A5: TP04 | B5: Interactive Consequence Learning and Digital Feedback | C5: Uses responsive simulations, animations, indicators, interfaces, or multisensory feedback to make relationships between actions, system states, and consequences experientially perceptible. | D5: Experiential Amplification | E5: {=IFERROR(INDEX(s001_insights!F:F,MATCH("s001M01"&A5,s001_insights!A:A,0)),"")} | F5: {=IFERROR(INDEX(s002_insights!F:F,MATCH("s002M01"&A5,s002_insights!A:A,0)),"")} -> TK05 Practised Motor and Tool-Operation Skill | G5: {=IFERROR(INDEX(s003_insights!F:F,MATCH("s003M01"&A5,s003_insights!A:A,0)),"")} -> TK10 Shared Professional Norms and Standards of Judgment | H5: =3-COUNTIF(E5:G5,"") -> 2
A6: TP05 | B6: Real-time Condition Intelligence through IoT Monitoring | C6: Uses connected sensors and real-time data streams to capture building performance, occupancy, environmental conditions, and operational states. | D6: Digital Codification | E6: {=IFERROR(INDEX(s001_insights!F:F,MATCH("s001M01"&A6,s001_insights!A:A,0)),"")} | F6: {=IFERROR(INDEX(s002_insights!F:F,MATCH("s002M01"&A6,s002_insights!A:A,0)),"")} | G6: {=IFERROR(INDEX(s003_insights!F:F,MATCH("s003M01"&A6,s003_insights!A:A,0)),"")} | H6: =3-COUNTIF(E6:G6,"") -> 0
A7: TP06 | B7: Worker Activity and State Capture through Wearable Sensors and Cameras | C7: Uses IMUs, wearable sensors, eye trackers, cameras, and video analysis to record workers’ movement, posture, gaze, workload, task sequences, and situated work activities. | D7: Digital Codification | E7: {=IFERROR(INDEX(s001_insights!F:F,MATCH("s001M01"&A7,s001_insights!A:A,0)),"")} -> TK06 Trained Sensory and Perceptual Recognition TK07 Embodied Posture, Balance, and Spatial Control | F7: {=IFERROR(INDEX(s002_insights!F:F,MATCH("s002M01"&A7,s002_insights!A:A,0)),"")} -> TK04 Unrecognized or Unarticulated Personal Know-how TK05 Practised Motor and Tool-Operation Skill TK06 Trained Sensory and Perceptual Recognition TK07 Embodied Posture, Balance, and Spatial Control | G7: {=IFERROR(INDEX(s003_insights!F:F,MATCH("s003M01"&A7,s003_insights!A:A,0)),"")} | H7: =3-COUNTIF(E7:G7,"") -> 2 | I7: <TP06, TK06> <TP06, TK07>
A8: TP07 | B8: Algorithmic Pattern Discovery and Prediction | C8: Uses AI, machine learning, NLP, statistical learning, or rule-based algorithms to derive classifications, forecasts, detected patterns, and predicted conditions from data. | D8: Digital Codification | E8: {=IFERROR(INDEX(s001_insights!F:F,MATCH("s001M01"&A8,s001_insights!A:A,0)),"")} -> TK06 Trained Sensory and Perceptual Recognition TK10 Shared Professional Norms and Standards of Judgment | F8: {=IFERROR(INDEX(s002_insights!F:F,MATCH("s002M01"&A8,s002_insights!A:A,0)),"")} -> TK02 Knowledge Conveyed Through Examples or Demonstration TK04 Unrecognized or Unarticulated Personal Know-how TK05 Practised Motor and Tool-Operation Skill TK06 Trained Sensory and Perceptual Recognition | G8: {=IFERROR(INDEX(s003_insights!F:F,MATCH("s003M01"&A8,s003_insights!A:A,0)),"")} -> TK06 Trained Sensory and Perceptual Recognition TK10 Shared Professional Norms and Standards of Judgment | H8: =3-COUNTIF(E8:G8,"") -> 3 | I8: <TP07, TK06> | J8: <TP07, TK10>
A9: TP08 | B9: Generative Knowledge Synthesis and Content Production | C9: Uses generative AI to combine requirements, contextual data, and retrieved knowledge into new drafts, reports, explanations, summaries, or recommendations. | D9: Digital Codification | E9: {=IFERROR(INDEX(s001_insights!F:F,MATCH("s001M01"&A9,s001_insights!A:A,0)),"")} -> TK12 Organizational Culture and Unwritten Working Practices | F9: {=IFERROR(INDEX(s002_insights!F:F,MATCH("s002M01"&A9,s002_insights!A:A,0)),"")} -> TK06 Trained Sensory and Perceptual Recognition TK07 Embodied Posture, Balance, and Spatial Control TK12 Organizational Culture and Unwritten Working Practices | G9: {=IFERROR(INDEX(s003_insights!F:F,MATCH("s003M01"&A9,s003_insights!A:A,0)),"")} | H9: =3-COUNTIF(E9:G9,"") -> 2 | J9: <TP08, TK12>
A10: TP09 | B10: Semantic Knowledge Structuring and Retrieval | C10: Uses knowledge graphs, semantic metadata, embeddings, vector databases, and meaning-based search to represent knowledge relationships and retrieve contextually relevant information. | D10: Digital Codification | E10: {=IFERROR(INDEX(s001_insights!F:F,MATCH("s001M01"&A10,s001_insights!A:A,0)),"")} -> TK05 Practised Motor and Tool-Operation Skill | F10: {=IFERROR(INDEX(s002_insights!F:F,MATCH("s002M01"&A10,s002_insights!A:A,0)),"")} -> TK12 Organizational Culture and Unwritten Working Practices | G10: {=IFERROR(INDEX(s003_insights!F:F,MATCH("s003M01"&A10,s003_insights!A:A,0)),"")} -> TK02 Knowledge Conveyed Through Examples or Demonstration TK05 Practised Motor and Tool-Operation Skill TK10 Shared Professional Norms and Standards of Judgment TK09 Shared Professional Language and Contextual Meaning | H10: =3-COUNTIF(E10:G10,"") -> 3 | J10: <TP09, TK05>
A11: TP10 | B11: Database-supported Project Knowledge Archiving | C11: Preserves and retrieves codified project records, narratives, lessons learned, safety information, and operational knowledge through databases, data warehouses, or conventional KMS repositories. | D11: Digital Codification | E11: {=IFERROR(INDEX(s001_insights!F:F,MATCH("s001M01"&A11,s001_insights!A:A,0)),"")} -> TK02 Knowledge Conveyed Through Examples or Demonstration TK04 Unrecognized or Unarticulated Personal Know-how TK05 Practised Motor and Tool-Operation Skill TK10 Shared Professional Norms and Standards of Judgment TK11 Informal Coordination, Communication, and Escalation Know-how TK12 Organizational Culture and Unwritten Working Practices | F11: {=IFERROR(INDEX(s002_insights!F:F,MATCH("s002M01"&A11,s002_insights!A:A,0)),"")} -> TK04 Unrecognized or Unarticulated Personal Know-how TK05 Practised Motor and Tool-Operation Skill | G11: {=IFERROR(INDEX(s003_insights!F:F,MATCH("s003M01"&A11,s003_insights!A:A,0)),"")} -> TK09 Shared Professional Language and Contextual Meaning | H11: =3-COUNTIF(E11:G11,"") -> 3 | J11: <TP10, TK04> <TP10, TK05>
A12: TP11 | B12: Collaborative Knowledge Co-creation through Digital Platforms | C12: Uses portals, messaging systems, shared virtual environments, and online collaboration platforms to support peer exchange, collective interpretation, user contribution, and shared knowledge construction. | D12: Experiential Amplification | E12: {=IFERROR(INDEX(s001_insights!F:F,MATCH("s001M01"&A12,s001_insights!A:A,0)),"")} | F12: {=IFERROR(INDEX(s002_insights!F:F,MATCH("s002M01"&A12,s002_insights!A:A,0)),"")} -> TK04 Unrecognized or Unarticulated Personal Know-how TK09 Shared Professional Language and Contextual Meaning TK12 Organizational Culture and Unwritten Working Practices | G12: {=IFERROR(INDEX(s003_insights!F:F,MATCH("s003M01"&A12,s003_insights!A:A,0)),"")} -> TK02 Knowledge Conveyed Through Examples or Demonstration TK04 Unrecognized or Unarticulated Personal Know-how TK10 Shared Professional Norms and Standards of Judgment | H12: =3-COUNTIF(E12:G12,"") -> 2 | J12: <TP11, TK04>
A13: TP12 | B13: Multimedia and Blended Knowledge Internalization | C13: Combines digital content, interactive media, online resources, and face-to-face or workplace activities to strengthen demonstration, participation, and knowledge internalization. | D13: Experiential Amplification | E13: {=IFERROR(INDEX(s001_insights!F:F,MATCH("s001M01"&A13,s001_insights!A:A,0)),"")} -> TK05 Practised Motor and Tool-Operation Skill TK11 Informal Coordination, Communication, and Escalation Know-how | F13: {=IFERROR(INDEX(s002_insights!F:F,MATCH("s002M01"&A13,s002_insights!A:A,0)),"")} -> TK05 Practised Motor and Tool-Operation Skill TK10 Shared Professional Norms and Standards of Judgment | G13: {=IFERROR(INDEX(s003_insights!F:F,MATCH("s003M01"&A13,s003_insights!A:A,0)),"")} -> TK05 Practised Motor and Tool-Operation Skill | H13: =3-COUNTIF(E13:G13,"") -> 3 | J13: <TP12, TK05>
A14: TP13 | B14: Criteria-based Performance Evaluation and Ranking | C14: Measures, compares, scores, or ranks learners, models, interventions, and alternatives using predefined criteria, indicators, benchmarks, or performance metrics. | D14: Digital Codification | E14: {=IFERROR(INDEX(s001_insights!F:F,MATCH("s001M01"&A14,s001_insights!A:A,0)),"")} -> TK10 Shared Professional Norms and Standards of Judgment | F14: {=IFERROR(INDEX(s002_insights!F:F,MATCH("s002M01"&A14,s002_insights!A:A,0)),"")} -> TK05 Practised Motor and Tool-Operation Skill TK10 Shared Professional Norms and Standards of Judgment | G14: {=IFERROR(INDEX(s003_insights!F:F,MATCH("s003M01"&A14,s003_insights!A:A,0)),"")} -> TK12 Organizational Culture and Unwritten Working Practices | H14: =3-COUNTIF(E14:G14,"") -> 3 | J14: <TP13, TK10>
A15: TP15 | B15: Distributed-Ledger-enabled Transaction Assurance and Traceability | C15: Uses blockchain or distributed-ledger technologies to create verifiable transaction records, strengthen provenance and supply-chain traceability, validate products, and automate trusted exchanges through smart contracts or related mechanisms. | D15: Digital Codification | E15: {=IFERROR(INDEX(s001_insights!F:F,MATCH("s001M01"&A15,s001_insights!A:A,0)),"")} | F15: {=IFERROR(INDEX(s002_insights!F:F,MATCH("s002M01"&A15,s002_insights!A:A,0)),"")} | G15: {=IFERROR(INDEX(s003_insights!F:F,MATCH("s003M01"&A15,s003_insights!A:A,0)),"")} -> TK04 Unrecognized or Unarticulated Personal Know-how | H15: =3-COUNTIF(E15:G15,"") -> 1
A16: TP16 | B16: Gamified Procedural and Scenario-based Learning | C16: Uses structured games, quizzes, cards, role-playing scenarios, and realistic problem cases to help learners reconstruct procedural sequences, apply operational criteria, recognize errors, and select appropriate responses. | D16: Experiential Amplification | E16: {=IFERROR(INDEX(s001_insights!F:F,MATCH("s001M01"&A16,s001_insights!A:A,0)),"")} | F16: {=IFERROR(INDEX(s002_insights!F:F,MATCH("s002M01"&A16,s002_insights!A:A,0)),"")} -> TK05 Practised Motor and Tool-Operation Skill TK06 Trained Sensory and Perceptual Recognition | G16: {=IFERROR(INDEX(s003_insights!F:F,MATCH("s003M01"&A16,s003_insights!A:A,0)),"")} | H16: =3-COUNTIF(E16:G16,"") -> 1

Sheet TP Perspectives
A1: ID | B1: Practice | C1: Retention Mechanism | D1: Sector coverage | E1: Relevant sectors | F1: Potential Pattern | G1: Potential Patterns
A2: TP01 | B2: Model-based Knowledge Representation and Simulation | C2: Digital Codification | D2: 2/3 | E2: Construction; Health Services | F2: TK Convergence: TK06 TK Divergence: TK05; TK10 | G2: Perceptual convergence with health-specific extension to motor skill and professional judgment
A3: TP03 | B3: Situated Experiential Learning through Extended Reality | C3: Experiential Amplification | D3: 3/3 | E3: Construction; Manufacturing; Health Services | F3: TK Convergence: TK05; TK06; TK07; TK08; TK10 TK Divergence: TK04; TK11 | G3: Strong embodied–perceptual convergence with sector-specific extensions of situated know-how
A4: TP04 | B4: Interactive Consequence Learning and Digital Feedback | C4: Experiential Amplification | D4: 2/3 | E4: Manufacturing; Health Services | F4: TK Convergence: None identified TK Divergence: TK05; TK10 | G4: Sector-divergent experiential feedback targeting motor skill and professional judgment
A5: TP06 | B5: Worker Activity and State Capture through Wearable Sensors and Cameras | C5: Digital Codification | D5: 2/3 | E5: Construction; Manufacturing | F5: TK Convergence: TK06; TK07 TK Divergence: TK04; TK05 | G5: Embodied–perceptual convergence with broader know-how capture in manufacturing
A6: TP07 | B6: Algorithmic Pattern Discovery and Prediction | C6: Digital Codification | D6: 3/3 | E6: Construction; Manufacturing; Health Services | F6: TK Convergence: TK06; TK10 TK Divergence: TK02; TK04; TK05 | G6: Perceptual convergence with sector-specific extensions to judgment, demonstration, motor skill, and unarticulated know-how
A7: TP08 | B7: Generative Knowledge Synthesis and Content Production | C7: Digital Codification | D7: 2/3 | E7: Construction; Manufacturing | F7: TK Convergence: TK12 TK Divergence: TK06; TK07 | G7: Organizational-practice convergence with manufacturing extension to embodied–perceptual knowledge
A8: TP09 | B8: Semantic Knowledge Structuring and Retrieval | C8: Digital Codification | D8: 3/3 | E8: Construction; Manufacturing; Health Services | F8: TK Convergence: TK05 TK Divergence: TK02; TK09; TK10; TK12 | G8: cross-industry recurrence with divergent knowledge targets
A9: TP10 | B9: Database-supported Project Knowledge Archiving | C9: Digital Codification | D9: 3/3 | E9: Construction; Manufacturing; Health Services | F9: TK Convergence: TK04; TK05 TK Divergence: TK02; TK09; TK10; TK11; TK12 | G9: cross-industry recurrence with strongly sector-divergent archival knowledge targets
A10: TP11 | B10: Collaborative Knowledge Co-creation through Digital Platforms | C10: Experiential Amplification | D10: 2/3 | E10: Manufacturing; Health Services | F10: TK Convergence: TK04 TK Divergence: TK02; TK09; TK10; TK12 | G10: Interpersonal and socially embedded know-how convergence with sector-specific professional and organizational extensions
A11: TP12 | B11: Multimedia and Blended Knowledge Internalization | C11: Experiential Amplification | D11: 3/3 | E11: Construction; Manufacturing; Health Services | F11: TK Convergence: TK05 TK Divergence: TK10; TK11 | G11: Strong motor-skill convergence with sector-specific social and professional extensions
A12: TP13 | B12: Criteria-based Performance Evaluation and Ranking | C12: Digital Codification | D12: 3/3 | E12: Construction; Manufacturing; Health Services | F12: TK Convergence: TK10 TK Divergence: TK05; TK12 | G12: Professional-judgment convergence with sector-specific motor and organizational extensions
... A14: TP16 | B14: Gamified Procedural and Scenario-based Learning | C14: Experiential Amplification | D14: 1/3 | E14: Manufacturing | F14: TK Convergence: None identified TK Divergence: TK05; TK06 | G14: Embodied–perceptual learning pattern

Sheet cross_sector_insights_tk
A1: ID | B1: Name | C1: Scope | D1: Collins TK Taxonomy | E1: s001:Construction | F1: s002:Manufacturing | G1: s003:Health Services | H1: filed | I1: Sectors
A2: TK02 | B2: Knowledge Conveyed Through Examples or Demonstration | C2: Knowledge transferred through cases, stories, simulations, examples, pointing, or practical demonstration because a sufficient verbal account has not been provided. | D2: Relational Tacit Knowledge | F2: TP07 Algorithmic Pattern Discovery and Prediction TP10 Database-supported Project Knowledge Archiving | G2: TP09 Semantic Knowledge Structuring and Retrieval TP11 Collaborative Knowledge Co-creation through Digital Platforms | H2: =3-COUNTIF(E2:G2,"") -> 2 | I2: Manufacturing; Health Services
A3: TK04 | B3: Unrecognized or Unarticulated Personal Know-how | C3: A person performs or decides effectively but has not consciously identified, reflected upon, or expressed the knowledge being used. | D3: Relational Tacit Knowledge | E3: TP10 Database-supported Project Knowledge Archiving | F3: TP03 Situated Experiential Learning through Extended Reality TP06 Worker Activity and State Capture through Wearable Sensors and Cameras TP07 Algorithmic Pattern Discovery and Prediction TP10 Database-supported Project Knowledge Archiving TP11 Collaborative Knowledge Co-creation through Digital Platforms | G3: TP11 Collaborative Knowledge Co-creation through Digital Platforms TP15 Distributed-Ledger-enabled Transaction Assurance and Traceability | H3: =3-COUNTIF(E3:G3,"") -> 3 | I3: Construction; Manufacturing; Health Services
A4: TK05 | B4: Practised Motor and Tool-Operation Skill | C4: Competence requiring learned bodily control and coordination during physical work or tool-mediated activity. | D4: Somatic Tacit Knowledge | E4: TP03 Situated Experiential Learning through Extended Reality TP09 Semantic Knowledge Structuring and Retrieval TP10 Database-supported Project Knowledge Archiving TP12 Multimedia and Blended Knowledge Internalization | F4: TP03 Situated Experiential Learning through Extended Reality TP04 Interactive Consequence Learning and Digital Feedback TP06 Worker Activity and State Capture through Wearable Sensors and Cameras TP07 Algorithmic Pattern Discovery and Prediction TP10 Database-supported Project Knowledge Archiving TP12 Multimedia and Blended Knowledge Internalization TP13 Criteria-based Performance Evaluation and Ranking TP16 Gamified Procedural and Scenario-based Learning | G4: TP01 Model-based Knowledge Representation and Simulation TP03 Situated Experiential Learning through Extended Reality TP09 Semantic Knowledge Structuring and Retrieval TP12 Multimedia and Blended Knowledge Internalization | H4: =3-COUNTIF(E4:G4,"") -> 3 | I4: Construction; Manufacturing; Health Services
A5: TK06 | B5: Trained Sensory and Perceptual Recognition | C5: A learned capacity to detect meaningful visual, auditory, tactile, spatial, or other sensory differences. | D5: Somatic Tacit Knowledge | E5: TP01 Model-based Knowledge Representation and Simulation TP03 Situated Experiential Learning through Extended Reality TP06 Worker Activity and State Capture through Wearable Sensors and Cameras TP07 Algorithmic Pattern Discovery and Prediction | F5: TP03 Situated Experiential Learning through Extended Reality TP06 Worker Activity and State Capture through Wearable Sensors and Cameras TP07 Algorithmic Pattern Discovery and Prediction TP08 Generative Knowledge Synthesis and Content Production TP16 Gamified Procedural and Scenario-based Learning | G5: TP01 Model-based Knowledge Representation and Simulation TP03 Situated Experiential Learning through Extended Reality TP07 Algorithmic Pattern Discovery and Prediction | H5: =3-COUNTIF(E5:G5,"") -> 3 | I5: Construction; Manufacturing; Health Services
A6: TK07 | B6: Embodied Posture, Balance, and Spatial Control | C6: Bodily competence involving posture, balance, orientation, movement, distance, positioning, or spatial awareness. | D6: Somatic Tacit Knowledge | E6: TP03 Situated Experiential Learning through Extended Reality TP06 Worker Activity and State Capture through Wearable Sensors and Cameras | F6: TP03 Situated Experiential Learning through Extended Reality TP06 Worker Activity and State Capture through Wearable Sensors and Cameras TP08 Generative Knowledge Synthesis and Content Production | H6: =3-COUNTIF(E6:G6,"") -> 2 | I6: Construction; Manufacturing
A7: TK08 | B7: Immediate Embodied Response to Changing Conditions | C7: Rapid bodily or neurophysiological response to hazards or changing conditions, often preceding complete conscious reasoning. | D7: Somatic Tacit Knowledge | E7: TP03 Situated Experiential Learning through Extended Reality | G7: TP03 Situated Experiential Learning through Extended Reality | H7: =3-COUNTIF(E7:G7,"") -> 2 | I7: Construction; Health Services
A8: TK09 | B8: Shared Professional Language and Contextual Meaning | C8: Understanding that depends on participation in a community sharing specialized terms, categories, expressions, narratives, and contextual meanings. | D8: Collective Tacit Knowledge | F8: TP11 Collaborative Knowledge Co-creation through Digital Platforms | G8: TP09 Semantic Knowledge Structuring and Retrieval TP10 Database-supported Project Knowledge Archiving | H8: =3-COUNTIF(E8:G8,"") -> 2 | I8: Manufacturing; Health Services
A9: TK10 | B9: Shared Professional Norms and Standards of Judgment | C9: Judgment grounded in collectively learned expectations about what is appropriate, acceptable, credible, safe, or legitimate. | D9: Collective Tacit Knowledge | E9: TP03 Situated Experiential Learning through Extended Reality TP07 Algorithmic Pattern Discovery and Prediction TP10 Database-supported Project Knowledge Archiving TP13 Criteria-based Performance Evaluation and Ranking | F9: TP12 Multimedia and Blended Knowledge Internalization TP13 Criteria-based Performance Evaluation and Ranking | G9: TP01 Model-based Knowledge Representation and Simulation TP03 Situated Experiential Learning through Extended Reality TP04 Interactive Consequence Learning and Digital Feedback TP07 Algorithmic Pattern Discovery and Prediction TP09 Semantic Knowledge Structuring and Retrieval TP11 Collaborative Knowledge Co-creation through Digital Platforms | H9: =3-COUNTIF(E9:G9,"") -> 3 | I9: Construction; Manufacturing; Health Services
A10: TK11 | B10: Informal Coordination, Communication, and Escalation Know-how | C10: Unwritten conventions governing coordination, communication, negotiation, signalling, collaboration, contact, and escalation within a group. | D10: Collective Tacit Knowledge | E10: TP10 Database-supported Project Knowledge Archiving TP12 Multimedia and Blended Knowledge Internalization | G10: TP03 Situated Experiential Learning through Extended Reality | H10: =3-COUNTIF(E10:G10,"") -> 2 | I10: Construction; Health Services
A11: TK12 | B11: Organizational Culture and Unwritten Working Practices | C11: Knowledge embedded in organizational identity, traditions, routines, authority relations, and historically developed ways of working. | D11: Collective Tacit Knowledge | E11: TP08 Generative Knowledge Synthesis and Content Production TP10 Database-supported Project Knowledge Archiving | F11: TP08 Generative Knowledge Synthesis and Content Production TP09 Semantic Knowledge Structuring and Retrieval TP11 Collaborative Knowledge Co-creation through Digital Platforms | G11: TP13 Criteria-based Performance Evaluation and Ranking | H11: =3-COUNTIF(E11:G11,"") -> 3 | I11: Construction; Manufacturing; Health Services

Sheet TK Perspectives
A1: ID | B1: Name | C1: Retention Taxonomy | D1: Sector coverage | E1: Relevant sectors | F1: Potential Pattern
A2: =cross_sector_insights_tk!A2 -> TK02 | B2: =cross_sector_insights_tk!B2 -> Knowledge Conveyed Through Examples or Demonstration | C2: =cross_sector_insights_tk!D2 -> Relational Tacit Knowledge | D2: =cross_sector_insights_tk!H2&"/3" -> 2/3 | E2: =cross_sector_insights_tk!I2 -> Manufacturing; Health Services | F2: TP Convergence: None identified TP Divergence: TP07; TP09; TP10; TP11
A3: =cross_sector_insights_tk!A3 -> TK04 | B3: =cross_sector_insights_tk!B3 -> Unrecognized or Unarticulated Personal Know-how | C3: =cross_sector_insights_tk!D3 -> Relational Tacit Knowledge | D3: =cross_sector_insights_tk!H3&"/3" -> 3/3 | E3: =cross_sector_insights_tk!I3 -> Construction; Manufacturing; Health Services | F3: TP Convergence: TP10; TP11 TP Divergence: TP03; TP06; TP07; TP15
A4: =cross_sector_insights_tk!A4 -> TK05 | B4: =cross_sector_insights_tk!B4 -> Practised Motor and Tool-Operation Skill | C4: =cross_sector_insights_tk!D4 -> Somatic Tacit Knowledge | D4: =cross_sector_insights_tk!H4&"/3" -> 3/3 | E4: =cross_sector_insights_tk!I4 -> Construction; Manufacturing; Health Services | F4: TP Convergence: TP03; TP09; TP10; TP12 TP Divergence: TP01; TP04; TP06; TP07; TP13; TP16
A5: =cross_sector_insights_tk!A5 -> TK06 | B5: =cross_sector_insights_tk!B5 -> Trained Sensory and Perceptual Recognition | C5: =cross_sector_insights_tk!D5 -> Somatic Tacit Knowledge | D5: =cross_sector_insights_tk!H5&"/3" -> 3/3 | E5: =cross_sector_insights_tk!I5 -> Construction; Manufacturing; Health Services | F5: TP Convergence: TP01; TP03; TP06; TP07 TP Divergence: TP08; TP16
A6: =cross_sector_insights_tk!A6 -> TK07 | B6: =cross_sector_insights_tk!B6 -> Embodied Posture, Balance, and Spatial Control | C6: =cross_sector_insights_tk!D6 -> Somatic Tacit Knowledge | D6: =cross_sector_insights_tk!H6&"/3" -> 2/3 | E6: =cross_sector_insights_tk!I6 -> Construction; Manufacturing | F6: TP Convergence: TP03; TP06 TP Divergence: TP08
A7: =cross_sector_insights_tk!A7 -> TK08 | B7: =cross_sector_insights_tk!B7 -> Immediate Embodied Response to Changing Conditions | C7: =cross_sector_insights_tk!D7 -> Somatic Tacit Knowledge | D7: =cross_sector_insights_tk!H7&"/3" -> 2/3 | E7: =cross_sector_insights_tk!I7 -> Construction; Health Services | F7: TP Convergence: TP03 TP Divergence: None identified
A8: =cross_sector_insights_tk!A8 -> TK09 | B8: =cross_sector_insights_tk!B8 -> Shared Professional Language and Contextual Meaning | C8: =cross_sector_insights_tk!D8 -> Collective Tacit Knowledge | D8: =cross_sector_insights_tk!H8&"/3" -> 2/3 | E8: =cross_sector_insights_tk!I8 -> Manufacturing; Health Services | F8: TP Convergence: None identified TP Divergence: TP09; TP10; TP11
A9: =cross_sector_insights_tk!A9 -> TK10 | B9: =cross_sector_insights_tk!B9 -> Shared Professional Norms and Standards of Judgment | C9: =cross_sector_insights_tk!D9 -> Collective Tacit Knowledge | D9: =cross_sector_insights_tk!H9&"/3" -> 3/3 | E9: =cross_sector_insights_tk!I9 -> Construction; Manufacturing; Health Services | F9: TP Convergence: TP03; TP07; TP13 TP Divergence: TP01; TP04; TP09; TP10; TP11; TP12
A10: =cross_sector_insights_tk!A10 -> TK11 | B10: =cross_sector_insights_tk!B10 -> Informal Coordination, Communication, and Escalation Know-how | C10: =cross_sector_insights_tk!D10 -> Collective Tacit Knowledge | D10: =cross_sector_insights_tk!H10&"/3" -> 2/3 | E10: =cross_sector_insights_tk!I10 -> Construction; Health Services | F10: TP Convergence: None identified TP Divergence: TP03; TP10; TP12
A11: =cross_sector_insights_tk!A11 -> TK12 | B11: =cross_sector_insights_tk!B11 -> Organizational Culture and Unwritten Working Practices | C11: =cross_sector_insights_tk!D11 -> Collective Tacit Knowledge | D11: =cross_sector_insights_tk!H11&"/3" -> 3/3 | E11: =cross_sector_insights_tk!I11 -> Construction; Manufacturing; Health Services | F11: TP Convergence: TP08 TP Divergence: TP09; TP10; TP11; TP13

Sheet s001_insights
A1: node_id | B1: category | C1: insight | D1: primary_retention_category | E1: retention_mechanism | F1: tacit_knowledge_retained | G1: evidence_chain
A2: s001M01TP03 | B2: Technology-enable Retention Mechanism | C2: Focal technology-enabled tacit knowledge retention approach. Situated Experiential Learning through Extended Reality is classified as Experience Amplification. The aggregated practice uses VR, AR, MR, CAVE, and hybrid environments to reconstruct consequential cues, let learners navigate or act, and return immediate sensory or instructional feedback (node_id:s001M01TP03). Its dominant function is rehearsal and situated perception 3D assets and logs are supporting representations rather than the principal retained object. Evidence chain (directional and bounded). The practice adopts Artificial Intelligence and Intelligent Computation (node_id:s001M01TE01) Human–Computer Interaction and Immersive Technologies such as Unity, HoloLens, Oculus, HTC VIVE, and CAVE (node_id:s001M01TE02) cyber-physical, modelling, sensing, mobile, and supporting tools (node_id:s001M01TE03 node_id:s001M01TE04 node_id:s001M01TE05 node_id:s001M01TE07 node_id:s001M01TE09). It transfers Trained Sensory and Perceptual Recognition (node_id:s001M01TK06) through clearer and interactive hazard visualization and transfers Shared Professional Norms and Standards of Judgment (node_id:s001M01TK10) through risk assessment, equipment choice, and consequence feedback. It also captures Practised Motor and Tool-Operation Skill, Embodied Posture and Spatial Control, and Immediate Embodied Response (node_id:s001M01TK05 node_id:s001M01TK07 node_id:s001M01TK08) through recorded craft sequences, VR behaviour, and practical performance assessment. Retention mechanism. Experience Amplification follows the mechanism reconstructed cues → learner action → feedback or consequence → stabilized experiential pattern. Cross-case evidence supports this pattern: AR and VR made hazards perceptible and improved identification virtual excavation enabled practical performance before and after training problem-first VR required selection under uncertainty and then displayed accident consequences. Long-term evidence is mixed. One VR cohort showed no significant knowledge decline after four weeks and problem-first VR outperformed direct instruction, yet another comparison found significant forgetting after four to five weeks, and long-term practical performance was not tested. Thus the graph supports stronger experiential learning and some retention, not uniform causal persistence. Tacit knowledge retained. The core retained knowledge is embodied hazard recognition and judgment: perceiving hazards, assessing severity and likelihood, choosing protective equipment, navigating space, and responding rapidly. Such knowledge is difficult to retain because passive instruction lacks interaction, learners forget, expertise levels differ, and context-dependent judgment resists full articulation (node_id:s001M01LI01 node_id:s001M01LI03 node_id:s001M01LI04 node_id:s001M01LI10). XR mitigates these limits by permitting safe failure, reproducing otherwise inaccessible or unethical disaster conditions, making consequences visible, and linking knowing to doing. It does not eliminate motivation or expertise-reversal effects. Conditions and constraints. The practice depends on regulatory and ethics controls, external connectivity, physical site conditions, retention-test timing, governance, technical resources, protected training time, participant availability, and task-aligned interface design (node_id:s001M01ED01 node_id:s001M01ED05 node_id:s001M01ED08 node_id:s001M01ED10 node_id:s001M01OD01 node_id:s001M01OD03 node_id:s001M01OD04 node_id:s001M01OD05 node_id:s001M01OD08). Constraints include cybersickness and withdrawal, age and working-memory differences, limited content coverage, interoperability and loading delays, scarce haptics and physical space, development workload, commercialization pressure, and narrow retention measures (node_id:s001M01LI02 node_id:s001M01LI03 node_id:s001M01LI04 node_id:s001M01LI05 node_id:s001M01LI06 node_id:s001M01LI08 node_id:s001M01LI12 node_id:s001M01LI13). Cross-case synthesis and theoretical statement. Heritage interpretation, construction hazard training, energy-use learning, and confined-space exercises are not separate focal practices here together they reveal a common experiential mechanism. Their complementarity also explains the limits: fidelity without accessible hardware excludes users, immersion without sound instructional design can overload them, and short-term performance without delayed workplace assessment leaves retention uncertain. Emerging XR retains tacit knowledge by amplifying situated experience and allowing safe, consequential practice, but only when governance, design, access, adaptation time, and repeated use convert immersive exposure into durable workplace judgment. | D2: Experience Amplification | E2: Extended-reality technologies retain tacit knowledge by reconstructing consequential workplace cues, enabling learners to act within simulated situations, and returning immediate sensory or instructional feedback. VR, AR, MR, and CAVE environments make hazards perceptible, support equipment selection and spatial navigation, permit safe failure, and reveal consequences that cannot be ethically recreated onsite. Repeated action stabilizes perceptual, motor, postural, response, and professional-judgment patterns. Across cases, hazard identification and practical performance improved, and some four-week persistence appeared, although forgetting was also observed. Durable retention therefore depends on sound instructional design, accessible hardware, adaptation time, governance, and repeated, task-aligned practice with delayed workplace assessment. | F2: TK05 Practised Motor and Tool-Operation Skill TK06 Trained Sensory and Perceptual Recognition TK07 Embodied Posture, Balance, and Spatial Control TK08 Immediate Embodied Response to Changing Conditions TK10 Shared Professional Norms and Standards of Judgment | G2: TE01 TE02 TE03 TE04 TE05 TE07 TE09 -> TP03 -> TK05 TK06 TK07 TK08 TK10
A3: s001M01TP12 | B3: Technology-enable Retention Mechanism | C3: Focal technology-enabled tacit knowledge retention approach. Multimedia and Blended Knowledge Internalization is classified as Experience Amplification. It combines digital content, interactive media, online resources, and face-to-face or workplace activity so learners observe demonstrations, contribute, discuss, and apply knowledge (node_id:s001M01TP12). Its dominant function is strengthened experience and social participation, not merely the storage of content. Evidence chain (directional and bounded). Interactive classroom technologies such as Vevox and Mentimeter (node_id:s001M01TE02), Moodle (node_id:s001M01TE04), Padlet and YouTube (node_id:s001M01TE07), and eBooks within the ambiguous technology class (node_id:s001M01TE09) are adopted by Multimedia and Blended Internalization (node_id:s001M01TP12). The practice transfers Practised Motor and Tool-Operation Skill (node_id:s001M01TK05) through technology-supported practical learning and demonstration, and transfers Informal Coordination, Communication, and Escalation Know-how (node_id:s001M01TK11) through group learning. The latter relationship is directly expressed as learning from groupmates. Retention mechanism. Experience Amplification follows digital demonstration and content → active discussion or problem solving → application and peer feedback → internalization. YouTube scaffolding visualization and interactive platforms supply examples face-to-face participation and small-group exchange allow learners to interpret and rehearse them. The graph reports that 82 percent of respondents felt more involved and that flipped and block structures can reduce cognitive overload. These are plausible enabling outcomes, but no delayed retention test is linked to this practice, so long-term persistence remains unproven. Tacit knowledge retained. The target knowledge is practical digital and construction skill plus the unwritten coordination habits learned through peer collaboration. These are hard to retain where craft inheritance is interrupted, formats fragment, and formal documentation misses interpersonal nuance (node_id:s001M01LI05 node_id:s001M01LI10). Blended learning mitigates passive listening and the theory–practice gap (node_id:s001M01LI04) by making learners active contributors, but it does not automatically resolve absenteeism, unequal participation, or differences in prior education. Conditions and constraints. The practice depends on institutional sponsorship (node_id:s001M01OD02), protected schedules and manageable class sizes (node_id:s001M01OD04), student engagement and co-creation (node_id:s001M01OD05), industry-aligned curriculum design (node_id:s001M01OD08), and the sociocultural diversity of learners (node_id:s001M01ED03). Student absence is an incompletely specified external dependency (node_id:s001M01ED10). Diverse backgrounds, scheduling pressure, and group dynamics constrain results (node_id:s001M01LI03 node_id:s001M01LI08 node_id:s001M01LI09). Cross-case synthesis. Heritage craft display and higher-education blended learning contribute different components to the aggregate. The former suggests that lightweight digital presentation can extend access to craft processes, while the latter shows how interactive platforms, peer collaboration, and block teaching support internalization. The strongest tacit link is not the medium itself but participation around the medium: students interpret demonstrations, compare perspectives, and learn coordination from groupmates. Content availability without these interactions would be codified access rather than experiential retention. Integrative theoretical statement. Blended technologies retain tacit knowledge primarily by amplifying socially situated practice. Digital content becomes durable know-how only when learners participate, receive contextual guidance, obtain feedback, and repeatedly translate representations into coordinated action. Evidence of later performance across different projects would strengthen the retention claim beyond reported engagement and immediate understanding. Institutional support and curriculum alignment are therefore not background variables but constitutive parts of the mechanism they determine whether multimedia is consumed passively or becomes a scaffold for practice. | D3: Experience Amplification | E3: Blended technologies retain tacit knowledge by combining demonstrations with active discussion, problem solving, workplace application, and peer feedback. Videos, eBooks, Moodle, Padlet, and interactive classroom tools supply examples and reference points face-to-face and small-group activity lets learners interpret, rehearse, and adapt them. The mechanism amplifies socially situated experience, supporting practical skill and informal coordination rather than merely distributing content. Reported involvement and reduced cognitive overload indicate enabling conditions, but delayed retention remains untested. Persistence therefore depends on institutional sponsorship, protected schedules, manageable groups, inclusive participation, industry-aligned curriculum, and repeated application across projects passive consumption would amount only to codified access. | F3: TK05 Practised Motor and Tool-Operation Skill TK11 Informal Coordination, Communication, and Escalation Know-how | G3: TE02 TE04 TE07 TE09 -> TP12 -> TK05 TK11
A4: s001M01TP01 | B4: Technology-enable Retention Mechanism | C4: Focal technology-enabled tacit knowledge retention approach. Model-based Knowledge Representation and Simulation is classified as Digital Codification. Across the aggregated cases, BIM, 3D/4D models, computational scenarios, and virtual models translate spatial arrangements, construction sequences, hazards, and performance relationships into inspectable representations (node_id:s001M01TP01). The dominant retention function is therefore the preservation and reuse of a model, not repeated embodied rehearsal. Immersive presentation is a secondary delivery capability. Evidence chain (directional and bounded). Human–Computer Interaction and Immersive Technologies, including Unity, CAVE, Navisworks, and SketchUp (node_id:s001M01TE02), together with Data, Information, and Knowledge Systems such as BIM, AutoCAD, Rhinoceros, Revit, and a centralized database (node_id:s001M01TE04), and the specifically evidenced EnergyPlus tool within the ambiguous technology class (node_id:s001M01TE09), are adopted by Model-based Knowledge Representation and Simulation (node_id:s001M01TP01). The only non-ambiguous retention edge is Technology-enabled Practice → captures → Trained Sensory and Perceptual Recognition (node_id:s001M01TK06): 4D BIM simulation made activity-based hazards identifiable at design stage. The linked tacit knowledge is difficult to retain where passive instruction fails to stimulate skill transfer (node_id:s001M01LI04) and where manual rules or sparse data omit complex safety cues (node_id:s001M01LI05). The secondary chain is Technology-enabled Practice → depends on → Culture, Trust and Relational Climate (node_id:s001M01OD06), evidenced by the need for a consciously maintained safety and continuous-improvement culture. Retention mechanism. Digital Codification is justified because the practice externalizes expert hazard recognition into persistent geometry, schedules, risk records, and simulated sequences that can be inspected before work and revisited across projects. The graph distinguishes adoption from retention: the presence of modelling software establishes technical availability the capture edge to hazard-recognition knowledge establishes codification effective retention is strongest only where the centralized OHS database preserves and shares information for later projects. Tacit knowledge retained. The retained capability is trained perceptual recognition: noticing activity-based hazards in spatial and temporal context (node_id:s001M01TK06). This know-how is hard to verbalize exhaustively and conventional instruction leaves a knowledge-to-practice gap. The model mitigates that gap by making otherwise latent relationships among design, sequence, and hazard visible, while the database component counters loss of OHS information as personnel change (node_id:s001M01LI10). BIM also reduced stakeholder document-approval time in one case, mitigating part of the workload constraint (node_id:s001M01LI08), but that efficiency is not itself evidence of knowledge retention. Conditions and constraints. Implementation is constrained by capital and maintenance cost (node_id:s001M01LI07), limited BIM and OHS-model expertise (node_id:s001M01LI08), and the quality limits attached to formal rules and data (node_id:s001M01LI05). The dependence on safety and learning culture means that a technically available model may remain unused or fail to become organizational memory. Cross-case synthesis and theoretical statement. The cases contribute different components rather than different practices: heritage and apartment models establish representation, BIM cases establish design communication and sequence simulation, and the OHS cases connect modelling to hazard recognition and future-project reuse. The strongest retention evidence comes from the OHS chain because it joins simulation to a named tacit capability and then to centralized continuity. The energy and presentation examples demonstrate adoption and representation but do not independently prove retention. Emerging modelling technologies therefore retain tacit know-how when organizations convert situated expert recognition into a governed, revisitable representation, preserve the related decisions and lessons, and embed the artefact in continuous-improvement routines adoption without capture, database continuity, and cultural use remains only technological deployment. | D4: Digital Codification | E4: Modeling technologies retain tacit hazard-recognition knowledge by translating experts’ spatial, sequencing, and performance judgments into BIM, 3D/4D models, simulations, and linked risk records. These representations make latent relationships visible before construction, allow teams to inspect activity-based hazards, and preserve decisions for later projects. Centralized OHS databases strengthen continuity by storing and sharing the modeled information beyond individual staff tenure. Retention depends on expert validation, adequate modeling competence, governed data, and a safety-oriented continuous-improvement culture. Software adoption alone is insufficient: the mechanism becomes retention only when captured cues remain revisitable, interpretable, and routinely reused in design reviews, training, and project learning. | F4: TK06 Trained Sensory and Perceptual Recognition | G4: TE02 TE04 TE09 -> TP01 -> TK06
A5: s001M01TP06 | B5: Technology-enable Retention Mechanism | C5: Focal technology-enabled tacit knowledge retention approach. Worker Activity and State Capture through Wearable Sensors and Cameras is classified as Digital Codification. IMUs, wearable cameras, eye tracking, and video analysis intercept embodied work and convert posture, movement, gaze, external load, and task context into measurable records (node_id:s001M01TP06). The durable data representation is the dominant function feedback or rehearsal is not the primary mechanism. Evidence chain (directional and bounded). Human–Computer Interaction and Immersive Technologies, specifically HoloLens eye and head gaze capture (node_id:s001M01TE02), and Imaging, Sensing, and Perception Technologies, including multiple IMUs and wearable cameras (node_id:s001M01TE05), are adopted by Worker Activity and State Capture (node_id:s001M01TP06). The practice captures Trained Sensory and Perceptual Recognition (node_id:s001M01TK06) by detecting abnormal or hazardous postures, and it captures and evaluates Embodied Posture, Balance, and Spatial Control (node_id:s001M01TK07) by combining sensor posture with video-observed hand weight to estimate lumbar load. The associated knowledge is hard to capture uniformly because individual bodies differ and motivation affects workplace transfer (node_id:s001M01LI03 node_id:s001M01LI04). Retention mechanism. Digital Codification operates as activity → sensor/video trace → calculated posture or workload representation → comparison and later assessment. This preserves aspects of embodied know-how that workers may not verbalize, including how they position themselves and handle loads. It remains a partial codification: the data represent observable posture and state, not the full situated reasons behind a worker's action. The graph supports capture and evaluation more strongly than transfer or long-term reuse. Tacit knowledge retained. The focal content is perceptual hazard recognition and embodied posture control. Video and IMU measurements make otherwise fleeting bodily performance inspectable, enabling organizations to identify risky patterns and potentially design assistive technology. The practice mitigates a measurement weakness only conditionally: collecting more observations may improve workload estimates, but one study found no clear correlation between workload and assistive technologies and an unclear target population (node_id:s001M01LI13). Thus the graph does not demonstrate that recorded data became retained operational know-how. Conditions and constraints. Regulatory evaluation frameworks such as OWAS, RULA, REBA, and HOHSRAM provide an external interpretation standard (node_id:s001M01ED01) access to actual job sites supplies the physical context needed to relate sensors to work (node_id:s001M01ED08) and individual–technology compatibility shapes implementation (node_id:s001M01OD08). Mixed learner characteristics, narrow samples, and uncertain construct validity constrain generalization (node_id:s001M01LI03 node_id:s001M01LI13 node_id:s001M01LI14). Cross-case synthesis and theoretical statement. The workload and mixed-reality cases identify complementary forms of capture: body-worn devices record the worker, while eye and head tracking record attention inside an instructional environment. Both depend on interpretation standards and representative populations. A measured posture may indicate risk without explaining the practical trade-off that produced it, and gaze may indicate attention without establishing comprehension. Retention therefore requires expert annotation, comparison over time, and feedback into redesigned tasks or training. Longitudinal evidence showing safer later performance would be needed to close the chain from measurement to retained capability. Wearables support tacit-knowledge retention when ephemeral embodied action is converted into interpretable, governed records and then fed back into practice sensing alone records performance without proving organizational learning. | D5: Digital Codification | E5: Wearable sensors and cameras retain tacit knowledge by converting fleeting embodied activity into durable, interpretable records. IMUs, wearable video, eye tracking, and workload analysis capture posture, movement, gaze, load handling, and task context that workers may struggle to verbalize. Analysts can compare traces over time, identify hazardous patterns, and use the findings to redesign work, assistive technology, or training. The codification remains partial because measurements represent observable action, not every situated reason behind it. Retention therefore requires expert annotation, regulatory interpretation, representative samples, privacy safeguards, and feedback into practice sensing alone documents performance without demonstrating transfer or safer long-term behavior. | F5: TK06 Trained Sensory and Perceptual Recognition TK07 Embodied Posture, Balance, and Spatial Control | G5: TE02 TE05 -> TP06 -> TK06 TK07
A6: s001M01TP07 | B6: Technology-enable Retention Mechanism | C6: Focal technology-enabled tacit knowledge retention approach. Algorithmic Pattern Discovery and Prediction is classified as Digital Codification. AI, machine learning, NLP, statistical learning, and rules transform unstructured reports, gaze data, and operating measurements into features, classifications, forecasts, and detected patterns (node_id:s001M01TP07). The dominant function is the extraction and durable representation of latent regularities, not situated rehearsal. Evidence chain (directional and bounded). Artificial Intelligence and Intelligent Computation—NLP, deep learning, CNNs, Word2Vec, GPT-4o extraction, ensemble classifiers, and predictive analytics—is the principal adopted technology (node_id:s001M01TE01), with Python grouped as a supporting ambiguous technology (node_id:s001M01TE09). The practice captures and transfers Trained Sensory and Perceptual Recognition (node_id:s001M01TK06) by extracting accident precursors and non-explicit semantic associations, and captures Shared Professional Norms and Standards of Judgment (node_id:s001M01TK10) by identifying the importance of risk factors, scenario-specific hazards, temporary support, soil stability, and material fatigue. These knowledge types are difficult to retain because manual rules omit complex texts, classification is subjective, and contextual judgment resists full automation (node_id:s001M01LI05 node_id:s001M01LI08 node_id:s001M01LI10). Retention mechanism. Digital Codification proceeds from historical data → preprocessing and representation → learned pattern or prediction → retrievable classification and decision cue. Cross-case evidence supports automatic feature extraction from accident narratives, requirement extraction from bids, learner-pattern classification, and predictive monitoring. Algorithms reduce dependence on manually designed features and large-scale human classification, mitigating software/data barriers and workload (node_id:s001M01LI05 node_id:s001M01LI08). They also surface information for archiving and immediate sharing. Yet discovery is not automatically retention: the graph provides limited evidence that predictions were repeatedly used, validated, or embedded in routines. Tacit knowledge retained. The strongest retained content is latent safety recognition and professional risk judgment. Narrative phrases and CNN representations make antecedents that experts perceive implicitly available for comparison across reports. This can broaden organizational memory beyond individual recall. However, overlapping vocabulary produced misclassification, language specificity reduced portability, object-strike performance remained weak, and the theoretical framework had not become a practical tool. The data therefore support codification of candidate tacit patterns, not a complete replacement for expert interpretation. Conditions and constraints. The practice depends on representative corpora and integrated infrastructure (node_id:s001M01OD03), leadership sponsorship and safety-management commitment (node_id:s001M01OD02), a knowledge-sharing and safety culture (node_id:s001M01OD06), and, for heating prediction, climatic context (node_id:s001M01ED04). Constraints include data imbalance, OCR and format limits, infrastructure gaps, underutilization under authoritarian leadership, privacy risks, operational variability, and limited validation (node_id:s001M01LI05 node_id:s001M01LI06 node_id:s001M01LI09 node_id:s001M01LI10 node_id:s001M01LI11 node_id:s001M01LI13 node_id:s001M01LI14). Cross-case synthesis and theoretical statement. Accident classification offers the clearest codification chain because latent phrases are linked to named safety knowledge bid extraction, learner classification, project monitoring, and heating prediction show the broader analytical capability but not the same strength of retention evidence. The cases also expose a recurrent trade-off between scale and meaning: algorithms can process more traces than experts, yet their categories inherit corpus imbalance, language boundaries, labels, and infrastructure conditions. Algorithmic technologies retain tacit knowledge by converting dispersed experiential traces into reusable pattern representations, but those representations become actionable organizational memory only through expert validation, adequate data, leadership support, contestable classifications, and incorporation into real decisions. | D6: Digital Codification | E6: Algorithmic technologies retain tacit knowledge by transforming experience traces into reusable classifications, patterns, forecasts, and decision cues. AI, machine learning, and NLP preprocess accident narratives, gaze data, bid material, and operating measurements, then surface hidden precursors, semantic associations, and risk factors that manual rules may miss. These codified patterns can support search, monitoring, and professional judgment while reducing classification workload. However, discovery becomes organizational memory only when outputs are validated by experts, supported by representative data and infrastructure, and embedded in real decisions. Bias, privacy, context loss, weak leadership, or limited validation can otherwise preserve misleading patterns rather than knowledge. | F6: TK06 Trained Sensory and Perceptual Recognition TK10 Shared Professional Norms and Standards of Judgment | G6: TE01 TE09 -> TP07 -> TK06 TK10
A7: s001M01TP08 | B7: Technology-enable Retention Mechanism | C7: Focal technology-enabled tacit knowledge retention approach. Generative Knowledge Synthesis and Content Production is classified as Digital Codification. The practice combines requirements, embeddings, retrieved organizational examples, and generative models to produce new drafts and reports (node_id:s001M01TP08). Its dominant retention function is to reactivate preserved organizational material through a durable semantic representation and generated artefact conversational interaction is secondary. Evidence chain (directional and bounded). Artificial Intelligence and Intelligent Computation—GPT-4o, embeddings, cosine similarity, few-shot prompting, NLP, and LangChain orchestration (node_id:s001M01TE01)—is combined with a Streamlit interface (node_id:s001M01TE02), Pinecone vector storage (node_id:s001M01TE04), and API access (node_id:s001M01TE09). These technologies are adopted by Generative Knowledge Synthesis (node_id:s001M01TP08), which transfers Organizational Culture and Unwritten Working Practices (node_id:s001M01TK12) through an AI system drawing on historical bids. This tacit knowledge is difficult to capture where incentives and trust are weak (node_id:s001M01LI09) and is vulnerable to staff turnover, fragmented records, and context loss (node_id:s001M01LI10). Retention mechanism. Digital Codification operates through historical documents → chunking and embeddings → semantic retrieval → contextual prompting → generated methodology → expert review. Retrieval grounds the output in firm-specific history, allowing prior ways of working to be surfaced when a new request arrives. This is stronger than simple model availability because the graph documents an integrated proof of concept and transfer relation. Effective retention nevertheless remains conditional: the system generates only methodology text, and organizational judgment is not fully contained in the corpus or model. Tacit knowledge retained. The focal content is historically developed organizational practice embodied in earlier bids—how the firm frames methods, responds to requirements, and structures persuasive technical content. Semantic retrieval and generation mitigate fragmented storage, inconsistent documentation, manual drafting effort, limited knowledge transfer, and turnover-related loss. They do not eliminate expert contextual judgment: each bid requires customization, nuanced risks make full automation impractical, and hallucination or confidentiality risk may weaken trust in the resulting memory. Conditions and constraints. The practice depends on client and procurement rules (node_id:s001M01ED06), document standards and stewardship (node_id:s001M01OD01), leadership sponsorship (node_id:s001M01OD02), high-quality centralized data and information-system readiness (node_id:s001M01OD03), openness to digital transformation (node_id:s001M01OD06), and organizational maturity and workflow fit (node_id:s001M01OD08). PDF-only processing, absent OCR, small historical corpora, third-party APIs, fragmented data, limited training, and underuse constrain scaling (node_id:s001M01LI05 node_id:s001M01LI08 node_id:s001M01LI09 node_id:s001M01LI10 node_id:s001M01LI14). Cross-case synthesis and theoretical statement. The bid system supplies the most direct mechanism evidence: retrieved examples shape a new methodology draft and human reviewers remain responsible for project-specific meaning. Net Zero Cloud broadens the category to automated reporting, but the graph does not connect that reporting to the same tacit-knowledge node it should therefore be treated as adoption evidence, not an additional retention practice. Retention quality should be assessed through provenance, reviewer correction, later reuse, and whether outputs improve decisions without flattening exceptions. Generative AI retains tacit organizational knowledge when it is coupled to a governed retrieval layer, standardized historical corpus, auditable provenance, and expert review. Without data readiness, trust, confidentiality controls, and contextual validation, generation recombines text but does not secure actionable memory. | D7: Digital Codification | E7: Generative technologies retain tacit organizational knowledge by reactivating prior work practices when new tasks arise. Historical bids are segmented, embedded, stored, and semantically retrieved relevant examples then ground prompts that generate a methodology draft for expert review. This chain converts fragmented experience into a reusable artifact while preserving links to firm-specific precedent. Retention quality depends on governed documents, adequate corpus breadth, provenance, reviewer correction, infrastructure, and workflow fit. The model cannot contain every contextual judgment, and generated text is not automatically valid knowledge. Its value lies in helping experts recover, adapt, and transmit unwritten practices despite turnover and documentation gaps. | F7: TK12 Organizational Culture and Unwritten Working Practices | G7: TE01 TE02 TE04 TE09 -> TP08 -> TK12
A8: s001M01TP09 | B8: Technology-enable Retention Mechanism | C8: Focal technology-enabled tacit knowledge retention approach. Semantic Knowledge Structuring and Retrieval is classified as Digital Codification. Knowledge graphs, metadata, embeddings, vector databases, and meaning-based search organize relationships and create durable retrieval paths (node_id:s001M01TP09). The dominant function is representational persistence and recall rather than rehearsal. Evidence chain (directional and bounded). Artificial Intelligence and Intelligent Computation, including text embeddings and cosine similarity (node_id:s001M01TE01), and Data, Information, and Knowledge Systems, specifically Pinecone vector storage (node_id:s001M01TE04), are adopted by Semantic Knowledge Structuring and Retrieval (node_id:s001M01TP09). The non-ambiguous retention chain is Technology-enabled Practice → transfers → Practised Motor and Tool-Operation Skill (node_id:s001M01TK05): an interactive knowledge graph digitizes the sequence of wooden construction, rammed-earth work, and associated intangible-cultural-heritage skills. The skill is difficult to retain because inheritance is interrupted (node_id:s001M01LI10), while fragmented formats restrict cross-platform reuse (node_id:s001M01LI05). No organizational or environmental dependency and no mitigation or resolve edge is returned for the focal practice. Retention mechanism. Digital Codification converts a craft sequence or historical document into structured entities, semantic metadata, embeddings, and indexed relationships, then retrieves a contextually relevant representation. For craftsmanship, the knowledge graph makes process order available beyond the original practitioner for bids, vector search ranks similar proposals. Only the craftsmanship relation is explicitly tied to tacit knowledge, so bid retrieval should not be counted as a second retention practice. Tacit knowledge retained. The retained content is practised motor and tool-operation skill represented through ordered craft processes. The representation can preserve sequence and access, but the graph does not show that users can reproduce the embodied quality of the skill from the digital structure alone. Accordingly, the evidence supports partial externalization and transfer, not complete substitution for demonstration, practice, or expert correction. Conditions and constraints. More than 70 percent of referenced projects encounter data-format or interoperability problems, and the bid knowledge base contains only 13 documents from two firms. These limitations narrow retrieval coverage and portability. Cross-case synthesis. The heritage graph and bid-retrieval cases demonstrate the same technical logic but different evidentiary strength. Both structure dispersed material and make it searchable by relation or meaning. Only the heritage case links that function to a named tacit skill, while the bid case establishes retrieval of similar documents without a corresponding tacit-knowledge edge in this focal subgraph. This distinction prevents corpus size, search quality, or semantic similarity from being mistaken for retention. Theoretical implication. Semantic structure can preserve the order, provenance, and relationships surrounding practice, which are often lost in isolated files. It can also support boundary crossing by letting later users approach knowledge through task meaning rather than exact keywords. Yet retrieval remains representational: a returned craft sequence must still be interpreted, demonstrated, and embodied by a learner. Evaluation should therefore test whether users can find the right episode and perform competently in a changed context. Semantic technologies support tacit-knowledge retention by creating durable relational pathways to examples and procedures, but actionable retention depends on interoperable standards, adequate metadata, sufficient corpus breadth, expert curation, and complementary human enactment. | D8: Digital Codification | E8: Semantic technologies retain tacit knowledge by converting craft sequences into structured entities, metadata, embeddings, relationships, and meaning-based retrieval paths. In the heritage case, a knowledge graph preserves the order and relationships of wooden construction and rammed-earth practices so later users can approach skills beyond the original practitioner. Vector search similarly retrieves related bid examples, although that case lacks an explicit tacit-knowledge link. Codification is therefore partial: structured representations provide durable access but cannot replace demonstration, enactment, or expert correction. Effective retention requires interoperable formats, adequate metadata, sufficient corpus breadth, curation, and opportunities to translate retrieved representations back into competent action. | F8: TK05 Practised Motor and Tool-Operation Skill | G8: TE01 TE04 -> TP09 -> TK05
A9: s001M01TP10 | B9: Technology-enable Retention Mechanism | C9: Focal technology-enabled tacit knowledge retention approach. Database-supported Project Knowledge Archiving is classified as Digital Codification. It preserves project narratives, lessons learned, safety information, and operational records in data warehouses, conventional KMS repositories, SQL databases, and applications (node_id:s001M01TP10). The dominant function is explicitly durable storage and retrieval. Evidence chain (directional and bounded). PowerApps interfaces (node_id:s001M01TE02), data warehouses, databases, digital KMS, Excel, Azure, and SQL (node_id:s001M01TE04), audio/video recording (node_id:s001M01TE05), and rule-based macros (node_id:s001M01TE08) are adopted by the archive practice. It captures or transfers Knowledge Conveyed Through Examples, Unrecognized Personal Know-how, Practised Motor Skill, Shared Professional Judgment, Informal Coordination Know-how, and Organizational Culture and Unwritten Practices (node_id:s001M01TK02 node_id:s001M01TK04 node_id:s001M01TK05 node_id:s001M01TK10 node_id:s001M01TK11 node_id:s001M01TK12). Stories preserve intuitive geotechnical responses, risk judgments, failure lessons, coordination norms, and organizational identity databases preserve craft sequences, OHS lessons, and prior-phase information. Retention mechanism. Digital Codification proceeds from elicited story or project activity → recording and transcription → curation, tagging, and structured asset → database integration → retrieval, monitoring, and reuse. Multiple cases show a common mechanism despite different media: data warehousing stores lessons learned storytelling converts nuanced experience into reusable narrative artefacts centralized OHS databases carry prior-project risk information into later monitoring. The archive therefore externalizes aspects of intuition without claiming that every nuance becomes explicit. Tacit knowledge retained. The practice targets knowledge that is intuitive, example-dependent, socially embedded, or hard to articulate. These forms are threatened by retirement, turnover, temporary teams, formal documents that omit context, knowledge hoarding, and weak trust (node_id:s001M01LI09 node_id:s001M01LI10). Storytelling improves capture of contextual, emotional, and situational detail centralized storage reduces dependence on individual memory and makes information available to future projects. Privacy safeguards, restricted access, and anonymization are necessary because sensitive stories can otherwise make retention unethical or unusable. Conditions and constraints. The practice depends on regulatory standards for OHS records (node_id:s001M01ED01), workforce demographic pressure (node_id:s001M01ED02), stewardship and review cycles (node_id:s001M01OD01), leadership and cultural reinforcement (node_id:s001M01OD02), technical and financial resources (node_id:s001M01OD03), protected time (node_id:s001M01OD04), psychological safety (node_id:s001M01OD06), and incentives (node_id:s001M01OD07). Cost and slow benefits (node_id:s001M01LI07), facilitation and curation workload (node_id:s001M01LI08), and cultural resistance (node_id:s001M01LI09) create weakest-link effects: failure at elicitation, trust, curation, governance, or retrieval can prevent a stored artefact from becoming organizational memory. Cross-case synthesis. The archive combines two different input pathways: direct digital recording of processes and deliberate human elicitation through stories. Their convergence is theoretically important. Process records improve continuity and traceability, while narratives recover motives, emotions, contingencies, and interpersonal knowledge omitted by formal documents. A repository that receives only one pathway risks either context-poor data or unstructured stories that cannot be found. Integrative theoretical statement. Emerging databases enable tacit-knowledge retention when human elicitation and governance convert situated experience into a findable, trusted, and repeatedly used asset. Technology redistributes expert work toward narration, validation, stewardship, and contextual interpretation it does not eliminate that work. The evidence supports continuity and reuse, but effective retention still depends on whether later users can translate codified narratives and records back into competent action and whether reuse metrics reveal that the archive is functioning as organizational memory. | D9: Digital Codification | E9: Database technologies retain tacit knowledge by moving experience through elicitation, recording, transcription, curation, tagging, integration, retrieval, and reuse. Data warehouses preserve lessons learned digital storytelling captures motives, emotions, examples, and interpersonal nuance OHS databases carry risk information across projects. Together, these systems counter turnover, retirement, temporary teams, fragmented records, and formal documents that omit context. Organizational memory still depends on psychological safety, incentives, privacy safeguards, stewardship, leadership, protected time, and search. Technology shifts expert work toward narration, validation, and interpretation: a stored asset contributes to retention only when later users trust it, retrieve it, and translate it into competent action. | F9: TK02 Knowledge Conveyed Through Examples or Demonstration TK04 Unrecognized or Unarticulated Personal Know-how TK05 Practised Motor and Tool-Operation Skill TK10 Shared Professional Norms and Standards of Judgment TK11 Informal Coordination, Communication, and Escalation Know-how TK12 Organizational Culture and Unwritten Working Practices | G9: TE02 TE04 TE05 TE08 -> TP10 -> TK02 TK04 TK05 TK10 TK11 TK12
A10: s001M01TP13 | B10: Technology-enable Retention Mechanism | C10: Focal technology-enabled tacit knowledge retention approach. Criteria-based Performance Evaluation and Ranking is classified as Digital Codification because questionnaires, tests, indicators, and benchmarked scores convert otherwise situated performance and judgment into comparable records (node_id:s001M01TP13). This is an assessment-centred codification, not a training or capture mechanism in itself. Evidence chain (directional and bounded). Human–Computer Interaction technologies such as Google Forms, a web application, and Qualtrics (node_id:s001M01TE02), together with Microsoft Excel as a data system (node_id:s001M01TE04), are adopted by Criteria-based Evaluation (node_id:s001M01TP13). The practice evaluates Shared Professional Norms and Standards of Judgment (node_id:s001M01TK10): retained safety knowledge is connected to safe work practices, and VR practical assessment asks participants to identify, evaluate, and respond to excavation hazards. The query provides no direct capture or transfer edge, no tacit-knowledge limitation edge specific to this evaluated node, and no mitigation or resolve relationship. Retention mechanism. Digital Codification is justified because the practice makes performance legible through pre/post/retention questionnaires, practical hazard assessments, model metrics, rankings, and OHS indicators. These records can diagnose change and support comparison. Yet evaluation is evidence about retention only when measurement timing and construct validity match the tacit capability. A questionnaire score cannot be assumed to represent embodied workplace action. Tacit knowledge retained. The evaluated content is professional safety judgment—recognizing hazards, appraising severity, and selecting an appropriate response. The graph supports evaluation of this judgment but not the mechanism by which it was retained. The practice should therefore be treated as a verification layer around other learning practices, rather than as proof that the assessment technology preserved knowledge. Conditions and constraints. OHS indicators depend on external regulatory standards (node_id:s001M01ED01). Learner preferences are heterogeneous and not fixed (node_id:s001M01LI03), while questioned learning-style validity and null physical-performance differences expose construct and validation problems (node_id:s001M01LI13). Cross-case synthesis. The aggregate combines fuzzy multi-criteria comparison of training media, practical VR hazard assessment, repeated knowledge tests, workload questionnaires, classifier benchmarks, and OHS monitoring. These are measurement components, not separate retention practices. Together they show that evaluation can examine both declarative recall and situated response, but the measures are not interchangeable. Delayed tests assess persistence, practical scenarios assess enactment, and algorithmic metrics assess model performance rather than human knowledge. Analytical boundary and theoretical statement. A valid retention claim requires temporal evidence and a measure close to the tacit capability of interest. Pre/post gains show acquisition a four-week score shows persistence safe action in a changed setting provides stronger transfer evidence. Regulatory benchmarks add legitimacy but may not capture local judgment. Scores also require interpretation by instructors, safety professionals, or managers otherwise the record remains detached from intervention. Digital evaluation can stabilize evidence of tacit performance as organizational data, reveal decay or mismatch, and direct refresher learning, but it contributes to retention only when valid measures are linked to repeated learning, corrective feedback, later competent action, and organizational decisions about how practice should change. | D10: Digital Codification | E10: Assessments assist retention by converting situated judgment and performance into comparable evidence. Forms, web applications, spreadsheets, tests, hazard scenarios, rankings, and OHS indicators record what learners identify, evaluate, remember, and enact. Repeated or delayed measures can reveal knowledge decay, diagnose mismatches, trigger refresher learning, and guide organizational decisions. Yet assessment is a verification layer, not the learning mechanism, and scores cannot represent embodied workplace competence. Its contribution depends on valid constructs, appropriate timing, regulatory alignment, corrective feedback, and later performance in changed settings. When these conditions hold, evaluation stabilizes evidence of professional judgment and helps organizations maintain it over time. | F10: TK10 Shared Professional Norms and Standards of Judgment | G10: TE02 TE04 -> TP13 -> TK10

Sheet s002_insights
A1: node_id | B1: category | C1: insight | D1: primary_retention_category | E1: retention_mechanism | F1: tacit_knowledge_retained | G1: evidence_chain
A2: s002M01TP03 | B2: Technology-enable Retention Mechanism | C2: Focal technology-enabled tacit knowledge retention approach. Situated Experiential Learning through Extended Reality (node_id:s002M01TP03) is the single focal practice. It is defined in the graph as Uses VR, AR, MR, CAVE, or hybrid XR environments to support embodied rehearsal, contextual guidance, historical interpretation, hazard recognition, and situated knowledge transfer. The node aggregates evidence across cases, so it represents a conceptual family rather than one event. The adopted technologies are Human–Computer Interaction and Immersive Technologies (node_id:s002M01TE02); Imaging, Sensing, and Perception Technologies (node_id:s002M01TE05). Adoption establishes technical availability and use, but it does not by itself establish retention. Evidence chain (directional and bounded). The supported main chain is Human–Computer Interaction and Immersive Technologies (node_id:s002M01TE02); Imaging, Sensing, and Perception Technologies (node_id:s002M01TE05) → Situated Experiential Learning through Extended Reality (node_id:s002M01TP03) → Practised Motor and Tool-Operation Skill (node_id:s002M01TK05); Trained Sensory and Perceptual Recognition (node_id:s002M01TK06); Unrecognized or Unarticulated Personal Know-how (node_id:s002M01TK04); Embodied Posture, Balance, and Spatial Control (node_id:s002M01TK07). Retrieved constraints are Individual Ergonomic, Usability and Immediate Safety Risks (node_id:s002M01LI02); Instructional Design, Delivery, Assessment and Transfer Shortcomings (node_id:s002M01LI04); Software, Algorithmic, Data Quality and Interoperability Barriers (node_id:s002M01LI05); Hardware, Sensor and Technical Infrastructure Constraints (node_id:s002M01LI06); plus 3 additional retrieved nodes; conditions are Political, Regulatory & Jurisdictional Environment (node_id:s002M01ED01); Geographic & Physical Site Context (node_id:s002M01ED08); Governance, Standards & Formal Control (node_id:s002M01OD01); Financial, Technical & Information Resources (node_id:s002M01OD03); plus 2 additional retrieved nodes. Across assembly-training cases, MAR and AR overlays paired instructions with virtual components, Magic Leap prototypes used CAD-derived guidance, and VMAR supported trainer intervention. These relations connect immersive and sensing technologies to embodied and perceptual skills. These links bound the claim: the practice captures, transfers, or evaluates only the knowledge nodes explicitly retrieved. Where no non-ambiguous tacit-knowledge node appears, the graph does not directly establish tacit retention and evidence about explicit knowledge should not be relabelled as tacit. Retention Mechanism. Primary classification: Experience Amplification. The dominant function is situated rehearsal, interaction, feedback, and repeated application; durable records are supporting inputs. Technology makes expert action encounterable, but retention occurs only when learners internalize and competently reuse the pattern. This classification identifies an experiential mechanism, not proof of a lasting outcome. Tacit Knowledge Retained. The non-ambiguous candidate knowledge is Practised Motor and Tool-Operation Skill (node_id:s002M01TK05); Trained Sensory and Perceptual Recognition (node_id:s002M01TK06); Unrecognized or Unarticulated Personal Know-how (node_id:s002M01TK04); Embodied Posture, Balance, and Spatial Control (node_id:s002M01TK07). Its tacitness lies in skilled judgment, perception, coordination, or bodily performance that is difficult to detach from context and articulate completely. The focal practice mitigates Individual Knowledge and Memory Decay (node_id:s002M01LI01); Human Physiological, Cognitive-Capacity and Demographic Constraints (node_id:s002M01LI03); Instructional Design, Delivery, Assessment and Transfer Shortcomings (node_id:s002M01LI04); Hardware, Sensor and Technical Infrastructure Constraints (node_id:s002M01LI06); plus 1 additional retrieved nodes. The evidence supports a conditional pathway: technology preserves otherwise transient cues, traces, or feedback, but mitigation is not full resolution. Usable retention still depends on fidelity, engagement, and expert validation. Conditions and constraints. The focal practice depends on Political, Regulatory & Jurisdictional Environment (node_id:s002M01ED01); Geographic & Physical Site Context (node_id:s002M01ED08); Governance, Standards & Formal Control (node_id:s002M01OD01); Financial, Technical & Information Resources (node_id:s002M01OD03); plus 2 additional retrieved nodes. These dependencies are neutral enabling conditions: leadership, capable participants, resources, process integration, regulation, markets, or site context can enable deployment but can also become bottlenecks. It is constrained by Individual Ergonomic, Usability and Immediate Safety Risks (node_id:s002M01LI02); Instructional Design, Delivery, Assessment and Transfer Shortcomings (node_id:s002M01LI04); Software, Algorithmic, Data Quality and Interoperability Barriers (node_id:s002M01LI05); Hardware, Sensor and Technical Infrastructure Constraints (node_id:s002M01LI06); plus 3 additional retrieved nodes. These links create a weakest-link effect: technical operation does not ensure retention, and experts remain responsible for validation and contextual judgment. Integrative theoretical statement. Situated Experiential Learning through Extended Reality illustrates emerging-technology adoption for tacit knowledge retention as a socio-technical conversion process. Digital tools create a retention opportunity, the focal practice organizes that opportunity, and organizational and environmental complements determine whether it becomes durable, retrievable, and actionable know-how. The graph supports this bounded mechanism but does not warrant a causal claim beyond the cited relationships; missing, ambiguous, or indirect evidence should be treated as a limitation rather than filled by speculation. | D2: Experience Amplification | E2: Extended-reality technologies retain tacit knowledge by placing learners inside consequential work situations. AR, mixed reality, imaging, and sensing overlay expert instructions, components, and cues onto physical tasks, allowing users to observe, act, receive feedback, and repeat procedures. Assembly and machinery cases show improved positioning, procedural performance, perceptual recognition, and autonomous execution. The dominant mechanism is Experience Amplification because knowledge is stabilized through embodied rehearsal rather than preserved mainly as an external record. Retention nevertheless depends on instructional quality, usable interfaces, trainer intervention, realistic context, repeated practice, and delayed assessment; technical adoption alone does not demonstrate durable transfer to workplace performance. | F2: TK04 Unrecognized or Unarticulated Personal Know-how TK05 Practised Motor and Tool-Operation Skill TK06 Trained Sensory and Perceptual Recognition TK07 Embodied Posture, Balance, and Spatial Control | G2: TE02;TE05 -> TP03 -> TK04;TK05;TK06;TK07
A3: s002M01TP04 | B3: Technology-enable Retention Mechanism | C3: Focal technology-enabled tacit knowledge retention approach. Interactive Consequence Learning and Digital Feedback (node_id:s002M01TP04) is the single focal practice. It is defined in the graph as Uses responsive simulations, animations, indicators, interfaces, or multisensory feedback to make relationships between actions, system states, and consequences experientially perceptible. The node aggregates evidence across cases, so it represents a conceptual family rather than one event. The adopted technologies are Human–Computer Interaction and Immersive Technologies (node_id:s002M01TE02); Imaging, Sensing, and Perception Technologies (node_id:s002M01TE05); Mobile, Social and Communication Technologies (node_id:s002M01TE07). Adoption establishes technical availability and use, but it does not by itself establish retention. Evidence chain (directional and bounded). The supported main chain is Human–Computer Interaction and Immersive Technologies (node_id:s002M01TE02); Imaging, Sensing, and Perception Technologies (node_id:s002M01TE05); Mobile, Social and Communication Technologies (node_id:s002M01TE07) → Interactive Consequence Learning and Digital Feedback (node_id:s002M01TP04) → Practised Motor and Tool-Operation Skill (node_id:s002M01TK05). Retrieved constraints are Instructional Design, Delivery, Assessment and Transfer Shortcomings (node_id:s002M01LI04); Software, Algorithmic, Data Quality and Interoperability Barriers (node_id:s002M01LI05); Hardware, Sensor and Technical Infrastructure Constraints (node_id:s002M01LI06); Time, Staffing, Expertise, Scheduling and Workload Constraints (node_id:s002M01LI08); conditions are Geographic & Physical Site Context (node_id:s002M01ED08); Financial, Technical & Information Resources (node_id:s002M01OD03). Across interactive-training cases, responsive visualization, feedback, and mobile interfaces made action–consequence relationships perceptible and supported practised skill. These links bound the claim: the practice captures, transfers, or evaluates only the knowledge nodes explicitly retrieved. Where no non-ambiguous tacit-knowledge node appears, the graph does not directly establish tacit retention and evidence about explicit knowledge should not be relabelled as tacit. Retention Mechanism. Primary classification: Experience Amplification. The dominant function is situated rehearsal, interaction, feedback, and repeated application; durable records are supporting inputs. Technology makes expert action encounterable, but retention occurs only when learners internalize and competently reuse the pattern. This classification identifies an experiential mechanism, not proof of a lasting outcome. Tacit Knowledge Retained. The non-ambiguous candidate knowledge is Practised Motor and Tool-Operation Skill (node_id:s002M01TK05). Its tacitness lies in skilled judgment, perception, coordination, or bodily performance that is difficult to detach from context and articulate completely. The focal practice mitigates Instructional Design, Delivery, Assessment and Transfer Shortcomings (node_id:s002M01LI04). The evidence supports a conditional pathway: technology preserves otherwise transient cues, traces, or feedback, but mitigation is not full resolution. Usable retention still depends on fidelity, engagement, and expert validation. Conditions and constraints. The focal practice depends on Geographic & Physical Site Context (node_id:s002M01ED08); Financial, Technical & Information Resources (node_id:s002M01OD03). These dependencies are neutral enabling conditions: leadership, capable participants, resources, process integration, regulation, markets, or site context can enable deployment but can also become bottlenecks. It is constrained by Instructional Design, Delivery, Assessment and Transfer Shortcomings (node_id:s002M01LI04); Software, Algorithmic, Data Quality and Interoperability Barriers (node_id:s002M01LI05); Hardware, Sensor and Technical Infrastructure Constraints (node_id:s002M01LI06); Time, Staffing, Expertise, Scheduling and Workload Constraints (node_id:s002M01LI08). These links create a weakest-link effect: technical operation does not ensure retention, and experts remain responsible for validation and contextual judgment. Integrative theoretical statement. Interactive Consequence Learning and Digital Feedback illustrates emerging-technology adoption for tacit knowledge retention as a socio-technical conversion process. Digital tools create a retention opportunity, the focal practice organizes that opportunity, and organizational and environmental complements determine whether it becomes durable, retrievable, and actionable know-how. The graph supports this bounded mechanism but does not warrant a causal claim beyond the cited relationships; missing, ambiguous, or indirect evidence should be treated as a limitation rather than filled by speculation. | D3: Experience Amplification | E3: Interactive feedback technologies retain tacit knowledge by making the consequences of action immediately perceptible. Immersive interfaces, sensing tools, and mobile systems present animations, indicators, error messages, or multisensory responses while learners perform tasks. This closes the loop between choice, system state, and outcome, helping users adjust tool operation and consolidate procedural patterns through repetition. The dominant mechanism is Experience Amplification because the learning value resides in action and feedback, not in an archived representation. Retention depends on accurate feedback, suitable task difficulty, technical reliability, sufficient practice time, and transfer beyond the interface; engagement or improvement alone cannot establish lasting competence. | F3: TK05 Practised Motor and Tool-Operation Skill | G3: TE02;TE05;TE07 -> TP04 -> TK05
A4: s002M01TP11 | B4: Technology-enable Retention Mechanism | C4: Focal technology-enabled tacit knowledge retention approach. Collaborative Knowledge Co-creation through Digital Platforms (node_id:s002M01TP11) is the single focal practice. It is defined in the graph as Uses portals, messaging systems, shared virtual environments, and online collaboration platforms to support peer exchange, collective interpretation, user contribution, and shared knowledge construction. The node aggregates evidence across cases, so it represents a conceptual family rather than one event. The adopted technologies are Artificial Intelligence and Intelligent Computation (node_id:s002M01TE01); Human–Computer Interaction and Immersive Technologies (node_id:s002M01TE02); Cyber-Physical Systems, IoT, and Smart Environments (node_id:s002M01TE03); Data, Information, and Knowledge Systems (node_id:s002M01TE04); plus 1 additional retrieved nodes. Adoption establishes technical availability and use, but it does not by itself establish retention. Evidence chain (directional and bounded). The supported main chain is Artificial Intelligence and Intelligent Computation (node_id:s002M01TE01); Human–Computer Interaction and Immersive Technologies (node_id:s002M01TE02); Cyber-Physical Systems, IoT, and Smart Environments (node_id:s002M01TE03); Data, Information, and Knowledge Systems (node_id:s002M01TE04); plus 1 additional retrieved nodes → Collaborative Knowledge Co-creation through Digital Platforms (node_id:s002M01TP11) → Unrecognized or Unarticulated Personal Know-how (node_id:s002M01TK04); Shared Professional Language and Contextual Meaning (node_id:s002M01TK09); Organizational Culture and Unwritten Working Practices (node_id:s002M01TK12). Retrieved constraints are Software, Algorithmic, Data Quality and Interoperability Barriers (node_id:s002M01LI05); Knowledge Continuity, Documentation, Governance, Privacy and Security (node_id:s002M01LI10); conditions are Political, Regulatory & Jurisdictional Environment (node_id:s002M01ED01); Sociocultural & Societal Environment (node_id:s002M01ED03); Governance, Standards & Formal Control (node_id:s002M01OD01); Strategic Leadership & Sponsorship (node_id:s002M01OD02); plus 4 additional retrieved nodes. Across cases, AI, immersive, IoT, data, and mobile platforms supported contribution and collective interpretation, connecting peer exchange to unarticulated know-how, shared language, and unwritten practices. These links bound the claim: the practice captures, transfers, or evaluates only the knowledge nodes explicitly retrieved. Where no non-ambiguous tacit-knowledge node appears, the graph does not directly establish tacit retention and evidence about explicit knowledge should not be relabelled as tacit. Retention Mechanism. Primary classification: Experience Amplification. The dominant function is situated rehearsal, interaction, feedback, and repeated application; durable records are supporting inputs. Technology makes expert action encounterable, but retention occurs only when learners internalize and competently reuse the pattern. This classification identifies an experiential mechanism, not proof of a lasting outcome. Tacit Knowledge Retained. The non-ambiguous candidate knowledge is Unrecognized or Unarticulated Personal Know-how (node_id:s002M01TK04); Shared Professional Language and Contextual Meaning (node_id:s002M01TK09); Organizational Culture and Unwritten Working Practices (node_id:s002M01TK12). Its tacitness lies in skilled judgment, perception, coordination, or bodily performance that is difficult to detach from context and articulate completely. The focal practice mitigates Software, Algorithmic, Data Quality and Interoperability Barriers (node_id:s002M01LI05); Time, Staffing, Expertise, Scheduling and Workload Constraints (node_id:s002M01LI08); Knowledge Continuity, Documentation, Governance, Privacy and Security (node_id:s002M01LI10). The evidence supports a conditional pathway: technology preserves otherwise transient cues, traces, or feedback, but mitigation is not full resolution. Usable retention still depends on fidelity, engagement, and expert validation. Conditions and constraints. The focal practice depends on Political, Regulatory & Jurisdictional Environment (node_id:s002M01ED01); Sociocultural & Societal Environment (node_id:s002M01ED03); Governance, Standards & Formal Control (node_id:s002M01OD01); Strategic Leadership & Sponsorship (node_id:s002M01OD02); plus 4 additional retrieved nodes. These dependencies are neutral enabling conditions: leadership, capable participants, resources, process integration, regulation, markets, or site context can enable deployment but can also become bottlenecks. It is constrained by Software, Algorithmic, Data Quality and Interoperability Barriers (node_id:s002M01LI05); Knowledge Continuity, Documentation, Governance, Privacy and Security (node_id:s002M01LI10). These links create a weakest-link effect: technical operation does not ensure retention, and experts remain responsible for validation and contextual judgment. Integrative theoretical statement. Collaborative Knowledge Co-creation through Digital Platforms illustrates emerging-technology adoption for tacit knowledge retention as a socio-technical conversion process. Digital tools create a retention opportunity, the focal practice organizes that opportunity, and organizational and environmental complements determine whether it becomes durable, retrievable, and actionable know-how. The graph supports this bounded mechanism but does not warrant a causal claim beyond the cited relationships; missing, ambiguous, or indirect evidence should be treated as a limitation rather than filled by speculation. | D4: Experience Amplification | E4: Collaborative digital platforms retain tacit knowledge by enabling participants to contribute experience, interpret problems, negotiate meaning, and develop shared practices. Artificial intelligence, immersive interfaces, connected systems, and knowledge platforms create spaces where unarticulated know-how, professional language, and unwritten organizational norms become encounterable through interaction. The dominant mechanism is Experience Amplification because retention occurs principally through dialogue, participation, and collective sensemaking; stored messages or records play a supporting role. Effective retention depends on trust, psychological safety, inclusive participation, familiarity, governance, and workflow integration. Without sustained contribution and application, technical connectivity produces information exchange but not durable shared understanding or organizational capability. | F4: TK04 Unrecognized or Unarticulated Personal Know-how TK09 Shared Professional Language and Contextual Meaning TK12 Organizational Culture and Unwritten Working Practices | G4: TE01;TE02;TE03;TE04 -> TP11 -> TK04;TK09;TK12
A5: s002M01TP12 | B5: Technology-enable Retention Mechanism | C5: Focal technology-enabled tacit knowledge retention approach. Multimedia and Blended Knowledge Internalization (node_id:s002M01TP12) is the single focal practice. It is defined in the graph as Combines digital content, interactive media, online resources, and face-to-face or workplace activities to strengthen demonstration, participation, and knowledge internalization. The node aggregates evidence across cases, so it represents a conceptual family rather than one event. The adopted technologies are Cyber-Physical Systems, IoT, and Smart Environments (node_id:s002M01TE03). Adoption establishes technical availability and use, but it does not by itself establish retention. Evidence chain (directional and bounded). The supported main chain is Cyber-Physical Systems, IoT, and Smart Environments (node_id:s002M01TE03) → Multimedia and Blended Knowledge Internalization (node_id:s002M01TP12) → Practised Motor and Tool-Operation Skill (node_id:s002M01TK05); Shared Professional Norms and Standards of Judgment (node_id:s002M01TK10). Retrieved constraints are Human Physiological, Cognitive-Capacity and Demographic Constraints (node_id:s002M01LI03); Instructional Design, Delivery, Assessment and Transfer Shortcomings (node_id:s002M01LI04); Knowledge Continuity, Documentation, Governance, Privacy and Security (node_id:s002M01LI10); conditions are Political, Regulatory & Jurisdictional Environment (node_id:s002M01ED01); External Technological & Infrastructure Environment (node_id:s002M01ED05); Geographic & Physical Site Context (node_id:s002M01ED08); Strategic Leadership & Sponsorship (node_id:s002M01OD02); plus 4 additional retrieved nodes. The strongest direct evidence comes from the learning-factory workshop: IoT, collaborative robotics, and additive manufacturing were used in hands-on activities associated with skill acquisition and improved decision-making. These links bound the claim: the practice captures, transfers, or evaluates only the knowledge nodes explicitly retrieved. Where no non-ambiguous tacit-knowledge node appears, the graph does not directly establish tacit retention and evidence about explicit knowledge should not be relabelled as tacit. Retention Mechanism. Primary classification: Experience Amplification. The practice’s dominant function is to organize digital demonstrations, hands-on activity, discussion, and feedback so participants internalize situated skill and judgment, rather than preserve a representation independently of the knower. IoT, collaborative-robotics, and additive-manufacturing activities supply consequential tasks; learning factories, workshops, and blended media let learners encounter, practise, and interpret them. Digital content is therefore a supporting scaffold. Retention is established only when participants can perform and decide beyond the immediate session, so reported knowledge acquisition and decision improvement are promising but do not by themselves demonstrate long-term transfer. Tacit Knowledge Retained. The non-ambiguous candidate knowledge is Practised Motor and Tool-Operation Skill (node_id:s002M01TK05); Shared Professional Norms and Standards of Judgment (node_id:s002M01TK10). Its tacitness lies in skilled judgment, perception, coordination, or bodily performance that is difficult to detach from context and articulate completely. The focal practice mitigates Instructional Design, Delivery, Assessment and Transfer Shortcomings (node_id:s002M01LI04); Time, Staffing, Expertise, Scheduling and Workload Constraints (node_id:s002M01LI08). The evidence supports a conditional pathway: technology preserves otherwise transient cues, traces, or feedback, but mitigation is not full resolution. Usable retention still depends on fidelity, engagement, and expert validation. Conditions and constraints. The focal practice depends on Political, Regulatory & Jurisdictional Environment (node_id:s002M01ED01); External Technological & Infrastructure Environment (node_id:s002M01ED05); Geographic & Physical Site Context (node_id:s002M01ED08); Strategic Leadership & Sponsorship (node_id:s002M01OD02); plus 4 additional retrieved nodes. These dependencies are neutral enabling conditions: leadership, capable participants, resources, process integration, regulation, markets, or site context can enable deployment but can also become bottlenecks. It is constrained by Human Physiological, Cognitive-Capacity and Demographic Constraints (node_id:s002M01LI03); Instructional Design, Delivery, Assessment and Transfer Shortcomings (node_id:s002M01LI04); Knowledge Continuity, Documentation, Governance, Privacy and Security (node_id:s002M01LI10). These links create a weakest-link effect: technical operation does not ensure retention, and experts remain responsible for validation and contextual judgment. Integrative theoretical statement. Multimedia and Blended Knowledge Internalization illustrates emerging-technology adoption for tacit knowledge retention as a socio-technical conversion process. Digital tools create a retention opportunity, the focal practice organizes that opportunity, and organizational and environmental complements determine whether it becomes durable, retrievable, and actionable know-how. The graph supports this bounded mechanism but does not warrant a causal claim beyond the cited relationships; missing, ambiguous, or indirect evidence should be treated as a limitation rather than filled by speculation. | D5: Experience Amplification | E5: Blended technologies retain tacit knowledge by combining digital demonstrations with hands-on activity, discussion, reflection, and peer feedback. IoT and collaborative-robotics exercises, learning platforms, workshops, and media expose participants to manufacturing problems and allow them to practise solutions. The dominant mechanism is Experience Amplification because practical skill and professional judgment are stabilized through learning-by-doing rather than stored primarily as digital records. Reported knowledge acquisition and improved decision-making indicate enabling outcomes, but they do not establish long-term persistence. Effective retention depends on suitable facilities, accessible infrastructure, participant capability, tailored curriculum, sufficient hands-on time, organizational support, and assessment of competent performance after training. | F5: TK05 Practised Motor and Tool-Operation Skill TK10 Shared Professional Norms and Standards of Judgment | G5: TE03 -> TP12 -> TK05;TK10
A6: s002M01TP16 | B6: Technology-enable Retention Mechanism | C6: Focal technology-enabled tacit knowledge retention approach. Gamified Procedural and Scenario-based Learning (node_id:s002M01TP16) is the single focal practice. It is defined in the graph as Uses structured games, quizzes, cards, role-playing scenarios, and realistic problem cases to help learners reconstruct procedural sequences, apply operational criteria, recognize errors, and select appropriate responses. The node aggregates evidence across cases, so it represents a conceptual family rather than one event. The adopted technologies are Human–Computer Interaction and Immersive Technologies (node_id:s002M01TE02); Imaging, Sensing, and Perception Technologies (node_id:s002M01TE05); Mobile, Social and Communication Technologies (node_id:s002M01TE07). Adoption establishes technical availability and use, but it does not by itself establish retention. Evidence chain (directional and bounded). The supported main chain is Human–Computer Interaction and Immersive Technologies (node_id:s002M01TE02); Imaging, Sensing, and Perception Technologies (node_id:s002M01TE05); Mobile, Social and Communication Technologies (node_id:s002M01TE07) → Gamified Procedural and Scenario-based Learning (node_id:s002M01TP16) → Practised Motor and Tool-Operation Skill (node_id:s002M01TK05); Trained Sensory and Perceptual Recognition (node_id:s002M01TK06). Retrieved constraints are none directly retrieved; conditions are none directly retrieved. Across cases, immersive, sensing, and mobile tools supported games and scenarios that transferred motor skill and perceptual recognition, while outcome evidence remains bounded to the retrieved relations. These links bound the claim: the practice captures, transfers, or evaluates only the knowledge nodes explicitly retrieved. Where no non-ambiguous tacit-knowledge node appears, the graph does not directly establish tacit retention and evidence about explicit knowledge should not be relabelled as tacit. Retention Mechanism. Primary classification: Experience Amplification. The dominant function is situated rehearsal, interaction, feedback, and repeated application; durable records are supporting inputs. Technology makes expert action encounterable, but retention occurs only when learners internalize and competently reuse the pattern. This classification identifies an experiential mechanism, not proof of a lasting outcome. Tacit Knowledge Retained. The non-ambiguous candidate knowledge is Practised Motor and Tool-Operation Skill (node_id:s002M01TK05); Trained Sensory and Perceptual Recognition (node_id:s002M01TK06). Its tacitness lies in skilled judgment, perception, coordination, or bodily performance that is difficult to detach from context and articulate completely. The focal practice mitigates Instructional Design, Delivery, Assessment and Transfer Shortcomings (node_id:s002M01LI04); Hardware, Sensor and Technical Infrastructure Constraints (node_id:s002M01LI06); Financial and Capital Constraints (node_id:s002M01LI07). The evidence supports a conditional pathway: technology preserves otherwise transient cues, traces, or feedback, but mitigation is not full resolution. Usable retention still depends on fidelity, engagement, and expert validation. Conditions and constraints. The focal practice depends on none directly retrieved. These dependencies are neutral enabling conditions: leadership, capable participants, resources, process integration, regulation, markets, or site context can enable deployment but can also become bottlenecks. It is constrained by none directly retrieved. These links create a weakest-link effect: technical operation does not ensure retention, and experts remain responsible for validation and contextual judgment. Integrative theoretical statement. Gamified Procedural and Scenario-based Learning illustrates emerging-technology adoption for tacit knowledge retention as a socio-technical conversion process. Digital tools create a retention opportunity, the focal practice organizes that opportunity, and organizational and environmental complements determine whether it becomes durable, retrievable, and actionable know-how. The graph supports this bounded mechanism but does not warrant a causal claim beyond the cited relationships; missing, ambiguous, or indirect evidence should be treated as a limitation rather than filled by speculation. | D6: Experience Amplification | E6: Gamified and scenario-based technologies retain tacit knowledge by placing learners in problems that require procedural choices, error recognition, and response selection. Immersive interfaces, sensing tools, and mobile technologies support games, quizzes, simulations, and cases through which users practise motor operations and perceptual discrimination. The dominant mechanism is Experience Amplification because knowledge is stabilized through active participation, feedback, and scenario performance rather than primarily through external records. These formats can improve engagement and make practice more accessible, but retention requires credible scenarios, clear feedback, progressive difficulty, repeated use, and transfer assessment. Immediate game performance alone does not prove durable workplace competence. | F6: TK05 Practised Motor and Tool-Operation Skill TK06 Trained Sensory and Perceptual Recognition | G6: TE02;TE05;TE07 -> TP16 -> TK05;TK06
A7: s002M01TP06 | B7: Technology-enable Retention Mechanism | C7: Focal technology-enabled tacit knowledge retention approach. Worker Activity and State Capture through Wearable Sensors and Cameras (node_id:s002M01TP06) is the single focal practice. It is defined in the graph as Uses IMUs, wearable sensors, eye trackers, cameras, and video analysis to record workers’ movement, posture, gaze, workload, task sequences, and situated work activities. The node aggregates evidence across cases, so it represents a conceptual family rather than one event. The adopted technologies are Artificial Intelligence and Intelligent Computation (node_id:s002M01TE01); Human–Computer Interaction and Immersive Technologies (node_id:s002M01TE02); Imaging, Sensing, and Perception Technologies (node_id:s002M01TE05). Adoption establishes technical availability and use, but it does not by itself establish retention. Evidence chain (directional and bounded). The supported main chain is Artificial Intelligence and Intelligent Computation (node_id:s002M01TE01); Human–Computer Interaction and Immersive Technologies (node_id:s002M01TE02); Imaging, Sensing, and Perception Technologies (node_id:s002M01TE05) → Worker Activity and State Capture through Wearable Sensors and Cameras (node_id:s002M01TP06) → Unrecognized or Unarticulated Personal Know-how (node_id:s002M01TK04); Practised Motor and Tool-Operation Skill (node_id:s002M01TK05); Trained Sensory and Perceptual Recognition (node_id:s002M01TK06); Embodied Posture, Balance, and Spatial Control (node_id:s002M01TK07). Retrieved constraints are Software, Algorithmic, Data Quality and Interoperability Barriers (node_id:s002M01LI05); Hardware, Sensor and Technical Infrastructure Constraints (node_id:s002M01LI06); Knowledge Continuity, Documentation, Governance, Privacy and Security (node_id:s002M01LI10); Physical-Environmental and Operational Variability (node_id:s002M01LI11); conditions are Political, Regulatory & Jurisdictional Environment (node_id:s002M01ED01); Governance, Standards & Formal Control (node_id:s002M01OD01). Across activity-capture cases, AI, wearables, cameras, gaze sensing, and body-sound traces converted movement and posture into analyzable records linked to tacit motor, perceptual, and spatial skills. These links bound the claim: the practice captures, transfers, or evaluates only the knowledge nodes explicitly retrieved. Where no non-ambiguous tacit-knowledge node appears, the graph does not directly establish tacit retention and evidence about explicit knowledge should not be relabelled as tacit. Retention Mechanism. Primary classification: Digital Codification. The dominant function is to intercept, structure, model, or preserve situated activity and judgment as durable digital representations; experiential use is secondary. Capture creates traces or records, transfer makes them available to later users, and retention requires continued accessibility, expert interpretation, and application. This classification identifies a mechanism, not an automatic outcome. Tacit Knowledge Retained. The non-ambiguous candidate knowledge is Unrecognized or Unarticulated Personal Know-how (node_id:s002M01TK04); Practised Motor and Tool-Operation Skill (node_id:s002M01TK05); Trained Sensory and Perceptual Recognition (node_id:s002M01TK06); Embodied Posture, Balance, and Spatial Control (node_id:s002M01TK07). Its tacitness lies in skilled judgment, perception, coordination, or bodily performance that is difficult to detach from context and articulate completely. The focal practice mitigates Knowledge Continuity, Documentation, Governance, Privacy and Security (node_id:s002M01LI10); Physical-Environmental and Operational Variability (node_id:s002M01LI11). The evidence supports a conditional pathway: technology preserves otherwise transient cues, traces, or feedback, but mitigation is not full resolution. Usable retention still depends on fidelity, engagement, and expert validation. Conditions and constraints. The focal practice depends on Political, Regulatory & Jurisdictional Environment (node_id:s002M01ED01); Governance, Standards & Formal Control (node_id:s002M01OD01). These dependencies are neutral enabling conditions: leadership, capable participants, resources, process integration, regulation, markets, or site context can enable deployment but can also become bottlenecks. It is constrained by Software, Algorithmic, Data Quality and Interoperability Barriers (node_id:s002M01LI05); Hardware, Sensor and Technical Infrastructure Constraints (node_id:s002M01LI06); Knowledge Continuity, Documentation, Governance, Privacy and Security (node_id:s002M01LI10); Physical-Environmental and Operational Variability (node_id:s002M01LI11). These links create a weakest-link effect: technical operation does not ensure retention, and experts remain responsible for validation and contextual judgment. Integrative theoretical statement. Worker Activity and State Capture through Wearable Sensors and Cameras illustrates emerging-technology adoption for tacit knowledge retention as a socio-technical conversion process. Digital tools create a retention opportunity, the focal practice organizes that opportunity, and organizational and environmental complements determine whether it becomes durable, retrievable, and actionable know-how. The graph supports this bounded mechanism but does not warrant a causal claim beyond the cited relationships; missing, ambiguous, or indirect evidence should be treated as a limitation rather than filled by speculation. | D7: Digital Codification | E7: Wearable, imaging, and intelligent technologies retain tacit knowledge by converting bodily activity into durable records. Sensors, cameras, eye trackers, and AI analysis capture movement, posture, gaze, workload, hand action, and task sequence, making previously unarticulated performance available for comparison and review. The dominant mechanism is Digital Codification because the practice externalizes embodied traces as measurable data rather than primarily creating a rehearsal environment. These records can support coaching, risk detection, and later reuse, but they represent observable behavior incompletely. Effective retention requires reliable sensing, contextual annotation, privacy governance, expert interpretation, representative observations, and feedback into changed work or training practices. | F7: TK04 Unrecognized or Unarticulated Personal Know-how TK05 Practised Motor and Tool-Operation Skill TK06 Trained Sensory and Perceptual Recognition TK07 Embodied Posture, Balance, and Spatial Control | G7: TE01;TE02;TE05 -> TP06 -> TK04;TK05;TK06;TK07
A8: s002M01TP07 | B8: Technology-enable Retention Mechanism | C8: Focal technology-enabled tacit knowledge retention approach. Algorithmic Pattern Discovery and Prediction (node_id:s002M01TP07) is the single focal practice. It is defined in the graph as Uses AI, machine learning, NLP, statistical learning, or rule-based algorithms to derive classifications, forecasts, detected patterns, and predicted conditions from data. The node aggregates evidence across cases, so it represents a conceptual family rather than one event. The adopted technologies are Artificial Intelligence and Intelligent Computation (node_id:s002M01TE01); Data, Information, and Knowledge Systems (node_id:s002M01TE04); Imaging, Sensing, and Perception Technologies (node_id:s002M01TE05); Rule-Based, Decision and Expert Systems (node_id:s002M01TE08). Adoption establishes technical availability and use, but it does not by itself establish retention. Evidence chain (directional and bounded). The supported main chain is Artificial Intelligence and Intelligent Computation (node_id:s002M01TE01); Data, Information, and Knowledge Systems (node_id:s002M01TE04); Imaging, Sensing, and Perception Technologies (node_id:s002M01TE05); Rule-Based, Decision and Expert Systems (node_id:s002M01TE08) → Algorithmic Pattern Discovery and Prediction (node_id:s002M01TP07) → Knowledge Conveyed Through Examples or Demonstration (node_id:s002M01TK02); Unrecognized or Unarticulated Personal Know-how (node_id:s002M01TK04); Practised Motor and Tool-Operation Skill (node_id:s002M01TK05); Trained Sensory and Perceptual Recognition (node_id:s002M01TK06). Retrieved constraints are Software, Algorithmic, Data Quality and Interoperability Barriers (node_id:s002M01LI05); Hardware, Sensor and Technical Infrastructure Constraints (node_id:s002M01LI06); Time, Staffing, Expertise, Scheduling and Workload Constraints (node_id:s002M01LI08); Knowledge Continuity, Documentation, Governance, Privacy and Security (node_id:s002M01LI10); plus 3 additional retrieved nodes; conditions are Natural & Climatic Environment (node_id:s002M01ED04); Geographic & Physical Site Context (node_id:s002M01ED08); Governance, Standards & Formal Control (node_id:s002M01OD01); Strategic Leadership & Sponsorship (node_id:s002M01OD02); plus 5 additional retrieved nodes. Across cases, AI, data systems, imaging, and rules derived patterns from operational and learning traces, connecting classifications and evaluations to example-based, unarticulated, motor, and perceptual knowledge. These links bound the claim: the practice captures, transfers, or evaluates only the knowledge nodes explicitly retrieved. Where no non-ambiguous tacit-knowledge node appears, the graph does not directly establish tacit retention and evidence about explicit knowledge should not be relabelled as tacit. Retention Mechanism. Primary classification: Digital Codification. The dominant function is to intercept, structure, model, or preserve situated activity and judgment as durable digital representations; experiential use is secondary. Capture creates traces or records, transfer makes them available to later users, and retention requires continued accessibility, expert interpretation, and application. This classification identifies a mechanism, not an automatic outcome. Tacit Knowledge Retained. The non-ambiguous candidate knowledge is Knowledge Conveyed Through Examples or Demonstration (node_id:s002M01TK02); Unrecognized or Unarticulated Personal Know-how (node_id:s002M01TK04); Practised Motor and Tool-Operation Skill (node_id:s002M01TK05); Trained Sensory and Perceptual Recognition (node_id:s002M01TK06). Its tacitness lies in skilled judgment, perception, coordination, or bodily performance that is difficult to detach from context and articulate completely. The focal practice mitigates Software, Algorithmic, Data Quality and Interoperability Barriers (node_id:s002M01LI05); Hardware, Sensor and Technical Infrastructure Constraints (node_id:s002M01LI06); Knowledge Continuity, Documentation, Governance, Privacy and Security (node_id:s002M01LI10); Physical-Environmental and Operational Variability (node_id:s002M01LI11); plus 2 additional retrieved nodes. The evidence supports a conditional pathway: technology preserves otherwise transient cues, traces, or feedback, but mitigation is not full resolution. Usable retention still depends on fidelity, engagement, and expert validation. Conditions and constraints. The focal practice depends on Natural & Climatic Environment (node_id:s002M01ED04); Geographic & Physical Site Context (node_id:s002M01ED08); Governance, Standards & Formal Control (node_id:s002M01OD01); Strategic Leadership & Sponsorship (node_id:s002M01OD02); plus 5 additional retrieved nodes. These dependencies are neutral enabling conditions: leadership, capable participants, resources, process integration, regulation, markets, or site context can enable deployment but can also become bottlenecks. It is constrained by Software, Algorithmic, Data Quality and Interoperability Barriers (node_id:s002M01LI05); Hardware, Sensor and Technical Infrastructure Constraints (node_id:s002M01LI06); Time, Staffing, Expertise, Scheduling and Workload Constraints (node_id:s002M01LI08); Knowledge Continuity, Documentation, Governance, Privacy and Security (node_id:s002M01LI10); plus 3 additional retrieved nodes. These links create a weakest-link effect: technical operation does not ensure retention, and experts remain responsible for validation and contextual judgment. Integrative theoretical statement. Algorithmic Pattern Discovery and Prediction illustrates emerging-technology adoption for tacit knowledge retention as a socio-technical conversion process. Digital tools create a retention opportunity, the focal practice organizes that opportunity, and organizational and environmental complements determine whether it becomes durable, retrievable, and actionable know-how. The graph supports this bounded mechanism but does not warrant a causal claim beyond the cited relationships; missing, ambiguous, or indirect evidence should be treated as a limitation rather than filled by speculation. | D8: Digital Codification | E8: Algorithmic technologies retain tacit knowledge by discovering reusable patterns within behavioral and learning data. Artificial intelligence, knowledge systems, imaging, and rule-based tools transform examples, unarticulated routines, motor traces, and perceptual signals into classifications, predictions, and evaluation cues. The dominant mechanism is Digital Codification because experiential traces become explicit analytical representations that can be searched, compared, and reused beyond the original performer. Algorithms may reduce manual interpretation and reveal regularities, but pattern discovery is not automatically organizational memory. Retention depends on representative data, interoperable infrastructure, expert validation, transparent classifications, privacy safeguards, and incorporation of outputs into decisions, instruction, and corrective action. | F8: TK02 Knowledge Conveyed Through Examples or Demonstration TK04 Unrecognized or Unarticulated Personal Know-how TK05 Practised Motor and Tool-Operation Skill TK06 Trained Sensory and Perceptual Recognition | G8: TE01;TE04;TE05;TE08 -> TP07 -> TK02;TK04;TK05;TK06
A9: s002M01TP08 | B9: Technology-enable Retention Mechanism | C9: Focal technology-enabled tacit knowledge retention approach. Generative Knowledge Synthesis and Content Production (node_id:s002M01TP08) is the single focal practice. It is defined in the graph as Uses generative AI to combine requirements, contextual data, and retrieved knowledge into new drafts, reports, explanations, summaries, or recommendations. The node aggregates evidence across cases, so it represents a conceptual family rather than one event. The adopted technologies are Artificial Intelligence and Intelligent Computation (node_id:s002M01TE01); Human–Computer Interaction and Immersive Technologies (node_id:s002M01TE02). Adoption establishes technical availability and use, but it does not by itself establish retention. Evidence chain (directional and bounded). The supported main chain is Artificial Intelligence and Intelligent Computation (node_id:s002M01TE01); Human–Computer Interaction and Immersive Technologies (node_id:s002M01TE02) → Generative Knowledge Synthesis and Content Production (node_id:s002M01TP08) → Trained Sensory and Perceptual Recognition (node_id:s002M01TK06); Embodied Posture, Balance, and Spatial Control (node_id:s002M01TK07); Organizational Culture and Unwritten Working Practices (node_id:s002M01TK12). Retrieved constraints are Instructional Design, Delivery, Assessment and Transfer Shortcomings (node_id:s002M01LI04); Software, Algorithmic, Data Quality and Interoperability Barriers (node_id:s002M01LI05); Research Design, Measurement and Validation Flaws (node_id:s002M01LI13); conditions are Political, Regulatory & Jurisdictional Environment (node_id:s002M01ED01); Strategic Leadership & Sponsorship (node_id:s002M01OD02); Financial, Technical & Information Resources (node_id:s002M01OD03); Human Capacity, Roles & Participation (node_id:s002M01OD05); plus 1 additional retrieved nodes. Across cases, generative AI and interfaces produced context-sensitive content from retrieved material, with capture and evaluation links to perceptual, spatial, and organizational know-how; the evidence does not show complete substitution for expert judgment. These links bound the claim: the practice captures, transfers, or evaluates only the knowledge nodes explicitly retrieved. Where no non-ambiguous tacit-knowledge node appears, the graph does not directly establish tacit retention and evidence about explicit knowledge should not be relabelled as tacit. Retention Mechanism. Primary classification: Digital Codification. The dominant function is to intercept, structure, model, or preserve situated activity and judgment as durable digital representations; experiential use is secondary. Capture creates traces or records, transfer makes them available to later users, and retention requires continued accessibility, expert interpretation, and application. This classification identifies a mechanism, not an automatic outcome. Tacit Knowledge Retained. The non-ambiguous candidate knowledge is Trained Sensory and Perceptual Recognition (node_id:s002M01TK06); Embodied Posture, Balance, and Spatial Control (node_id:s002M01TK07); Organizational Culture and Unwritten Working Practices (node_id:s002M01TK12). Its tacitness lies in skilled judgment, perception, coordination, or bodily performance that is difficult to detach from context and articulate completely. The focal practice mitigates Instructional Design, Delivery, Assessment and Transfer Shortcomings (node_id:s002M01LI04); Software, Algorithmic, Data Quality and Interoperability Barriers (node_id:s002M01LI05); Time, Staffing, Expertise, Scheduling and Workload Constraints (node_id:s002M01LI08); Knowledge Continuity, Documentation, Governance, Privacy and Security (node_id:s002M01LI10); plus 1 additional retrieved nodes. The evidence supports a conditional pathway: technology preserves otherwise transient cues, traces, or feedback, but mitigation is not full resolution. Usable retention still depends on fidelity, engagement, and expert validation. Conditions and constraints. The focal practice depends on Political, Regulatory & Jurisdictional Environment (node_id:s002M01ED01); Strategic Leadership & Sponsorship (node_id:s002M01OD02); Financial, Technical & Information Resources (node_id:s002M01OD03); Human Capacity, Roles & Participation (node_id:s002M01OD05); plus 1 additional retrieved nodes. These dependencies are neutral enabling conditions: leadership, capable participants, resources, process integration, regulation, markets, or site context can enable deployment but can also become bottlenecks. It is constrained by Instructional Design, Delivery, Assessment and Transfer Shortcomings (node_id:s002M01LI04); Software, Algorithmic, Data Quality and Interoperability Barriers (node_id:s002M01LI05); Research Design, Measurement and Validation Flaws (node_id:s002M01LI13). These links create a weakest-link effect: technical operation does not ensure retention, and experts remain responsible for validation and contextual judgment. Integrative theoretical statement. Generative Knowledge Synthesis and Content Production illustrates emerging-technology adoption for tacit knowledge retention as a socio-technical conversion process. Digital tools create a retention opportunity, the focal practice organizes that opportunity, and organizational and environmental complements determine whether it becomes durable, retrievable, and actionable know-how. The graph supports this bounded mechanism but does not warrant a causal claim beyond the cited relationships; missing, ambiguous, or indirect evidence should be treated as a limitation rather than filled by speculation. | D9: Digital Codification | E9: Generative and interactive technologies retain tacit knowledge by transforming inputs and retrieved experience into explanations, recommendations, or content. Artificial intelligence and human–computer interfaces synthesize perceptual cues, spatial judgments, and unwritten organizational practices, allowing knowledge to be reactivated for new situations. The dominant mechanism is Digital Codification because the system produces persistent, reviewable representations rather than principally teaching through embodied rehearsal. Generated material can widen access and support reflection, but it does not contain every exception or situated reason. Effective retention therefore requires grounded source material, provenance, expert review, user participation, governance, and application; plausible output alone is not verified knowledge. | F9: TK06 Trained Sensory and Perceptual Recognition TK07 Embodied Posture, Balance, and Spatial Control TK12 Organizational Culture and Unwritten Working Practices | G9: TE01;TE02 -> TP08 -> TK06;TK07;TK12
A10: s002M01TP09 | B10: Technology-enable Retention Mechanism | C10: Focal technology-enabled tacit knowledge retention approach. Semantic Knowledge Structuring and Retrieval (node_id:s002M01TP09) is the single focal practice. It is defined in the graph as Uses knowledge graphs, semantic metadata, embeddings, vector databases, and meaning-based search to represent knowledge relationships and retrieve contextually relevant information. The node aggregates evidence across cases, so it represents a conceptual family rather than one event. The adopted technologies are Data, Information, and Knowledge Systems (node_id:s002M01TE04); Rule-Based, Decision and Expert Systems (node_id:s002M01TE08). Adoption establishes technical availability and use, but it does not by itself establish retention. Evidence chain (directional and bounded). The supported main chain is Data, Information, and Knowledge Systems (node_id:s002M01TE04); Rule-Based, Decision and Expert Systems (node_id:s002M01TE08) → Semantic Knowledge Structuring and Retrieval (node_id:s002M01TP09) → Organizational Culture and Unwritten Working Practices (node_id:s002M01TK12). Retrieved constraints are Software, Algorithmic, Data Quality and Interoperability Barriers (node_id:s002M01LI05); Organizational Culture, Leadership and Adoption Barriers (node_id:s002M01LI09); Knowledge Continuity, Documentation, Governance, Privacy and Security (node_id:s002M01LI10); conditions are none directly retrieved. Across cases, databases and rule-based systems organized semantic relations and evaluated whether unwritten organizational practices became searchable; evaluation is weaker evidence than direct capture or transfer. These links bound the claim: the practice captures, transfers, or evaluates only the knowledge nodes explicitly retrieved. Where no non-ambiguous tacit-knowledge node appears, the graph does not directly establish tacit retention and evidence about explicit knowledge should not be relabelled as tacit. Retention Mechanism. Primary classification: Digital Codification. The dominant function is to intercept, structure, model, or preserve situated activity and judgment as durable digital representations; experiential use is secondary. Capture creates traces or records, transfer makes them available to later users, and retention requires continued accessibility, expert interpretation, and application. This classification identifies a mechanism, not an automatic outcome. Tacit Knowledge Retained. The non-ambiguous candidate knowledge is Organizational Culture and Unwritten Working Practices (node_id:s002M01TK12). Its tacitness lies in skilled judgment, perception, coordination, or bodily performance that is difficult to detach from context and articulate completely. The focal practice mitigates Software, Algorithmic, Data Quality and Interoperability Barriers (node_id:s002M01LI05); Time, Staffing, Expertise, Scheduling and Workload Constraints (node_id:s002M01LI08); Organizational Culture, Leadership and Adoption Barriers (node_id:s002M01LI09); Knowledge Continuity, Documentation, Governance, Privacy and Security (node_id:s002M01LI10); plus 1 additional retrieved nodes. The evidence supports a conditional pathway: technology preserves otherwise transient cues, traces, or feedback, but mitigation is not full resolution. Usable retention still depends on fidelity, engagement, and expert validation. Conditions and constraints. The focal practice depends on none directly retrieved. These dependencies are neutral enabling conditions: leadership, capable participants, resources, process integration, regulation, markets, or site context can enable deployment but can also become bottlenecks. It is constrained by Software, Algorithmic, Data Quality and Interoperability Barriers (node_id:s002M01LI05); Organizational Culture, Leadership and Adoption Barriers (node_id:s002M01LI09); Knowledge Continuity, Documentation, Governance, Privacy and Security (node_id:s002M01LI10). These links create a weakest-link effect: technical operation does not ensure retention, and experts remain responsible for validation and contextual judgment. Integrative theoretical statement. Semantic Knowledge Structuring and Retrieval illustrates emerging-technology adoption for tacit knowledge retention as a socio-technical conversion process. Digital tools create a retention opportunity, the focal practice organizes that opportunity, and organizational and environmental complements determine whether it becomes durable, retrievable, and actionable know-how. The graph supports this bounded mechanism but does not warrant a causal claim beyond the cited relationships; missing, ambiguous, or indirect evidence should be treated as a limitation rather than filled by speculation. | D10: Digital Codification | E10: Semantic technologies retain tacit knowledge by organizing material into searchable relationships, categories, and retrieval paths. Data and knowledge systems, together with rule-based tools, structure unwritten organizational practices so later users can locate relevant information and compare it across situations. The dominant mechanism is Digital Codification because retention depends on a semantic representation outside the original knower. However, the link evaluates organizational culture and working practices rather than directly demonstrating their capture or transfer, so the evidence is conditional. Effective retention requires metadata, interoperable formats, curated vocabularies, corpus coverage, access governance, expert interpretation, and evidence that retrieved material informs competent action. | F10: TK12 Organizational Culture and Unwritten Working Practices | G10: TE04;TE08 -> TP09 -> TK12
A11: s002M01TP10 | B11: Technology-enable Retention Mechanism | C11: Focal technology-enabled tacit knowledge retention approach. Database-supported Project Knowledge Archiving (node_id:s002M01TP10) is the single focal practice. It is defined in the graph as Preserves and retrieves codified project records, narratives, lessons learned, safety information, and operational knowledge through databases, data warehouses, or conventional KMS repositories. The node aggregates evidence across cases, so it represents a conceptual family rather than one event. The adopted technologies are Artificial Intelligence and Intelligent Computation (node_id:s002M01TE01). Adoption establishes technical availability and use, but it does not by itself establish retention. Evidence chain (directional and bounded). The supported main chain is Artificial Intelligence and Intelligent Computation (node_id:s002M01TE01) → Database-supported Project Knowledge Archiving (node_id:s002M01TP10) → Unrecognized or Unarticulated Personal Know-how (node_id:s002M01TK04); Practised Motor and Tool-Operation Skill (node_id:s002M01TK05). Retrieved constraints are none directly retrieved; conditions are Political, Regulatory & Jurisdictional Environment (node_id:s002M01ED01); Sociocultural & Societal Environment (node_id:s002M01ED03); Strategic Leadership & Sponsorship (node_id:s002M01OD02); Financial, Technical & Information Resources (node_id:s002M01OD03); plus 1 additional retrieved nodes. Across cases, AI-assisted archiving converted project experience into repositories, with capture and transfer links to unarticulated know-how and practised skill. These links bound the claim: the practice captures, transfers, or evaluates only the knowledge nodes explicitly retrieved. Where no non-ambiguous tacit-knowledge node appears, the graph does not directly establish tacit retention and evidence about explicit knowledge should not be relabelled as tacit. Retention Mechanism. Primary classification: Digital Codification. The dominant function is to intercept, structure, model, or preserve situated activity and judgment as durable digital representations; experiential use is secondary. Capture creates traces or records, transfer makes them available to later users, and retention requires continued accessibility, expert interpretation, and application. This classification identifies a mechanism, not an automatic outcome. Tacit Knowledge Retained. The non-ambiguous candidate knowledge is Unrecognized or Unarticulated Personal Know-how (node_id:s002M01TK04); Practised Motor and Tool-Operation Skill (node_id:s002M01TK05). Its tacitness lies in skilled judgment, perception, coordination, or bodily performance that is difficult to detach from context and articulate completely. The focal practice mitigates Organizational Culture, Leadership and Adoption Barriers (node_id:s002M01LI09); Knowledge Continuity, Documentation, Governance, Privacy and Security (node_id:s002M01LI10). The evidence supports a conditional pathway: technology preserves otherwise transient cues, traces, or feedback, but mitigation is not full resolution. Usable retention still depends on fidelity, engagement, and expert validation. Conditions and constraints. The focal practice depends on Political, Regulatory & Jurisdictional Environment (node_id:s002M01ED01); Sociocultural & Societal Environment (node_id:s002M01ED03); Strategic Leadership & Sponsorship (node_id:s002M01OD02); Financial, Technical & Information Resources (node_id:s002M01OD03); plus 1 additional retrieved nodes. These dependencies are neutral enabling conditions: leadership, capable participants, resources, process integration, regulation, markets, or site context can enable deployment but can also become bottlenecks. It is constrained by none directly retrieved. These links create a weakest-link effect: technical operation does not ensure retention, and experts remain responsible for validation and contextual judgment. Integrative theoretical statement. Database-supported Project Knowledge Archiving illustrates emerging-technology adoption for tacit knowledge retention as a socio-technical conversion process. Digital tools create a retention opportunity, the focal practice organizes that opportunity, and organizational and environmental complements determine whether it becomes durable, retrievable, and actionable know-how. The graph supports this bounded mechanism but does not warrant a causal claim beyond the cited relationships; missing, ambiguous, or indirect evidence should be treated as a limitation rather than filled by speculation. | D11: Digital Codification | E11: AI-supported archiving technologies retain tacit knowledge by converting project experience into organizational records. Tools help elicit, classify, summarize, and store unarticulated know-how and practised motor or operational skills within repositories. The dominant mechanism is Digital Codification because experience is externalized as structured content that can remain available after the original holder leaves. Archives can improve continuity and provide examples for work, but storage alone does not preserve contextual meaning or guarantee reuse. Effective retention depends on trustworthy elicitation, expert validation, appropriate metadata, privacy controls, stewardship, accessible retrieval, and organizational routines that translate archived material back into situated judgment and performance. | F11: TK04 Unrecognized or Unarticulated Personal Know-how TK05 Practised Motor and Tool-Operation Skill | G11: TE01 -> TP10 -> TK04;TK05
A12: s002M01TP13 | B12: Technology-enable Retention Mechanism | C12: Focal technology-enabled tacit knowledge retention approach. Criteria-based Performance Evaluation and Ranking (node_id:s002M01TP13) is the single focal practice. It is defined in the graph as Measures, compares, scores, or ranks learners, models, interventions, and alternatives using predefined criteria, indicators, benchmarks, or performance metrics. The node aggregates evidence across cases, so it represents a conceptual family rather than one event. The adopted technologies are Artificial Intelligence and Intelligent Computation (node_id:s002M01TE01); Data, Information, and Knowledge Systems (node_id:s002M01TE04). Adoption establishes technical availability and use, but it does not by itself establish retention. Evidence chain (directional and bounded). The supported main chain is Artificial Intelligence and Intelligent Computation (node_id:s002M01TE01); Data, Information, and Knowledge Systems (node_id:s002M01TE04) → Criteria-based Performance Evaluation and Ranking (node_id:s002M01TP13) → Practised Motor and Tool-Operation Skill (node_id:s002M01TK05); Shared Professional Norms and Standards of Judgment (node_id:s002M01TK10). Retrieved constraints are Instructional Design, Delivery, Assessment and Transfer Shortcomings (node_id:s002M01LI04); Organizational Culture, Leadership and Adoption Barriers (node_id:s002M01LI09); Empirical Sample and Generalizability Limitations (node_id:s002M01LI14); conditions are Governance, Standards & Formal Control (node_id:s002M01OD01); Strategic Leadership & Sponsorship (node_id:s002M01OD02); Financial, Technical & Information Resources (node_id:s002M01OD03); Time, Workload & Operational Scheduling (node_id:s002M01OD04); plus 1 additional retrieved nodes. Across cases, AI and data systems converted performance into scores and benchmarks that evaluated motor skill and shared professional judgment; assessment evidences retention only when constructs and timing are valid. These links bound the claim: the practice captures, transfers, or evaluates only the knowledge nodes explicitly retrieved. Where no non-ambiguous tacit-knowledge node appears, the graph does not directly establish tacit retention and evidence about explicit knowledge should not be relabelled as tacit. Retention Mechanism. Primary classification: Digital Codification. The dominant function is to intercept, structure, model, or preserve situated activity and judgment as durable digital representations; experiential use is secondary. Capture creates traces or records, transfer makes them available to later users, and retention requires continued accessibility, expert interpretation, and application. This classification identifies a mechanism, not an automatic outcome. Tacit Knowledge Retained. The non-ambiguous candidate knowledge is Practised Motor and Tool-Operation Skill (node_id:s002M01TK05); Shared Professional Norms and Standards of Judgment (node_id:s002M01TK10). Its tacitness lies in skilled judgment, perception, coordination, or bodily performance that is difficult to detach from context and articulate completely. The focal practice mitigates Software, Algorithmic, Data Quality and Interoperability Barriers (node_id:s002M01LI05); Knowledge Continuity, Documentation, Governance, Privacy and Security (node_id:s002M01LI10). The evidence supports a conditional pathway: technology preserves otherwise transient cues, traces, or feedback, but mitigation is not full resolution. Usable retention still depends on fidelity, engagement, and expert validation. Conditions and constraints. The focal practice depends on Governance, Standards & Formal Control (node_id:s002M01OD01); Strategic Leadership & Sponsorship (node_id:s002M01OD02); Financial, Technical & Information Resources (node_id:s002M01OD03); Time, Workload & Operational Scheduling (node_id:s002M01OD04); plus 1 additional retrieved nodes. These dependencies are neutral enabling conditions: leadership, capable participants, resources, process integration, regulation, markets, or site context can enable deployment but can also become bottlenecks. It is constrained by Instructional Design, Delivery, Assessment and Transfer Shortcomings (node_id:s002M01LI04); Organizational Culture, Leadership and Adoption Barriers (node_id:s002M01LI09); Empirical Sample and Generalizability Limitations (node_id:s002M01LI14). These links create a weakest-link effect: technical operation does not ensure retention, and experts remain responsible for validation and contextual judgment. Integrative theoretical statement. Criteria-based Performance Evaluation and Ranking illustrates emerging-technology adoption for tacit knowledge retention as a socio-technical conversion process. Digital tools create a retention opportunity, the focal practice organizes that opportunity, and organizational and environmental complements determine whether it becomes durable, retrievable, and actionable know-how. The graph supports this bounded mechanism but does not warrant a causal claim beyond the cited relationships; missing, ambiguous, or indirect evidence should be treated as a limitation rather than filled by speculation. | D12: Digital Codification | E12: Digital evaluation technologies assist tacit knowledge retention by converting performance into comparable evidence. Artificial intelligence and information systems score, rank, or benchmark practical motor skill and shared professional judgment using criteria and indicators. The dominant mechanism is Digital Codification because the practice produces durable measurement records that reveal performance differences, learning decay, or corrective needs. Evaluation is a verification layer rather than the learning mechanism, and a score cannot represent embodied competence. Its contribution to retention depends on valid constructs, timing, representative tasks, transparent metrics, expert interpretation, corrective feedback, and organizational use of results to guide refresher learning and practice. | F12: TK05 Practised Motor and Tool-Operation Skill TK10 Shared Professional Norms and Standards of Judgment | G12: TE01;TE04 -> TP13 -> TK05;TK10

Sheet s003_insights
A1: node_id | B1: category | C1: insight | D1: primary_retention_category | E1: retention_mechanism | F1: tacit_knowledge_retained | G1: evidence_chain
A2: s003M01TP03 | B2: Technology-enable Retention Mechanism | C2: Focal technology-enabled tacit knowledge retention approach. Situated Experiential Learning through Extended Reality (node_id:s003M01TP03) is the single focal practice. Its definition describes uses vr, ar, mr, cave, or hybrid xr environments to support embodied rehearsal, contextual guidance, historical interpretation, hazard recognition, and situated knowledge transfer. The relationship evidence combines material from 4 case sources (c216, c214, c212, c225), so the node represents a cross-case conceptual aggregation, not one event. Technology availability is not treated as adoption, and adoption is not treated as retention; the claim is bounded to relationships that explicitly connect this practice to technology and non-ambiguous tacit knowledge. Evidence chain (directional and bounded). Main chain: Artificial Intelligence and Intelligent Computation (node_id:s003M01TE01); Human–Computer Interaction and Immersive Technologies (node_id:s003M01TE02); Cyber-Physical Systems, IoT, and Smart Environments (node_id:s003M01TE03); Data, Information, and Knowledge Systems (node_id:s003M01TE04); Imaging, Sensing, and Perception Technologies (node_id:s003M01TE05) → Situated Experiential Learning through Extended Reality (node_id:s003M01TP03) → Practised Motor and Tool-Operation Skill (node_id:s003M01TK05); Trained Sensory and Perceptual Recognition (node_id:s003M01TK06); Immediate Embodied Response to Changing Conditions (node_id:s003M01TK08); Informal Coordination, Communication, and Escalation Know-how (node_id:s003M01TK11); Shared Professional Norms and Standards of Judgment (node_id:s003M01TK10). The adoption links identify deployed digital technology families, while the capture/transfer links identify the knowledge object; they do not by themselves establish long-term retention. Secondary chain: Situated Experiential Learning through Extended Reality (node_id:s003M01TP03) → Geographic & Physical Site Context (node_id:s003M01ED08); User Characteristics, Eligibility & Participation Conditions (node_id:s003M01ED11); Governance, Standards & Formal Control (node_id:s003M01OD01); Financial, Technical & Information Resources (node_id:s003M01OD03); Time, Workload & Operational Scheduling (node_id:s003M01OD04); Human Capacity, Roles & Participation (node_id:s003M01OD05). The evidence therefore supports a configured socio-technical practice, not an autonomous tool. Where evaluation links exist, they indicate measurement of knowledge or outcomes, but measurement remains distinct from durable organizational memory. Retention Mechanism — Experience Amplification. Its dominant function is situated rehearsal, interaction, feedback, demonstration, or internalization; the technology lets learners experience and refine judgment without fully converting that judgment into a durable symbolic representation. Any recorded actions or content are secondary supports. This is the primary classification only. The alternative perspective may appear as a secondary capability—for example, experiential systems can record actions, and codifying systems can support learning—but it does not define the dominant retention function evidenced here. Tacit Knowledge Retained. The bounded target comprises Practised Motor and Tool-Operation Skill (node_id:s003M01TK05); Trained Sensory and Perceptual Recognition (node_id:s003M01TK06); Immediate Embodied Response to Changing Conditions (node_id:s003M01TK08); Informal Coordination, Communication, and Escalation Know-how (node_id:s003M01TK11); Shared Professional Norms and Standards of Judgment (node_id:s003M01TK10). These forms of knowing are difficult to preserve because skilled action, perceptual discrimination, contextual meaning, and professional judgment are enacted in practice and are only partly verbalizable. The focal approach makes them more retainable by repeatedly exposing learners to their cues or by stabilizing traces that others can retrieve and interpret. Its explicitly linked mitigation/resolution targets are Individual Knowledge and Memory Decay (node_id:s003M01LI01); Individual Ergonomic, Usability and Immediate Safety Risks (node_id:s003M01LI02); Instructional Design, Delivery, Assessment and Transfer Shortcomings (node_id:s003M01LI04); Knowledge Continuity, Documentation, Governance, Privacy and Security (node_id:s003M01LI10). This supports a mechanism claim, but not a guarantee: capture can omit context, transfer can fail to produce competent performance, and evaluation can measure short-term response rather than longitudinal retention. Conditions and constraints. The practice depends on Geographic & Physical Site Context (node_id:s003M01ED08); User Characteristics, Eligibility & Participation Conditions (node_id:s003M01ED11); Governance, Standards & Formal Control (node_id:s003M01OD01); Financial, Technical & Information Resources (node_id:s003M01OD03); Time, Workload & Operational Scheduling (node_id:s003M01OD04); Human Capacity, Roles & Participation (node_id:s003M01OD05). These resources are complementary: technical infrastructure without expert participation and governance yields an available system rather than actionable memory, while expertise without time, access, and process integration cannot populate or validate it. The directly linked constraints are Individual Ergonomic, Usability and Immediate Safety Risks (node_id:s003M01LI02); Human Physiological, Cognitive-Capacity and Demographic Constraints (node_id:s003M01LI03); Instructional Design, Delivery, Assessment and Transfer Shortcomings (node_id:s003M01LI04); Software, Algorithmic, Data Quality and Interoperability Barriers (node_id:s003M01LI05); Hardware, Sensor and Technical Infrastructure Constraints (node_id:s003M01LI06); Financial and Capital Constraints (node_id:s003M01LI07). They create weakest-link effects involving data quality, usability, infrastructure, cost, workload, privacy, adoption, or validation. Any limitation not linked to this focal practice is excluded from the claim. Integrative theoretical statement. This practice illustrates emerging-technology adoption as a conversion process: digital affordances must be configured into a governed practice, connected to a specific tacit-knowledge object, interpreted by capable participants, and reinforced through use or evaluation. Retention emerges only when those elements jointly preserve knowledge in a form that later actors can enact; the graph supports the pathway, while incomplete longitudinal evidence prevents a stronger causal claim. | D2: Experience Amplification | E2: Extended-reality technologies retain tacit knowledge by reconstructing consequential clinical and technical situations in which learners perceive cues, perform actions, coordinate responses, and receive feedback. AI, immersive interfaces, connected systems, data platforms, and sensing technologies create repeatable environments for practising motor control, perceptual recognition, rapid response, informal coordination, and professional judgment. The dominant mechanism is Experience Amplification because retention occurs through embodied rehearsal and internalization rather than through a standalone record. Simulations can support safe failure and repeated exposure, but durable transfer depends on realistic scenarios, accessible equipment, capable facilitation, manageable cognitive load, repeated practice, and assessment beyond immediate clinical performance. | F2: TK05 Practised Motor and Tool-Operation Skill TK06 Trained Sensory and Perceptual Recognition TK08 Immediate Embodied Response to Changing Conditions TK11 Informal Coordination, Communication, and Escalation Know-how TK10 Shared Professional Norms and Standards of Judgment | G2: TE01;TE02;TE03;TE04;TE05 -> TP03 -> TK05;TK06;TK08;TK11;TK10
A3: s003M01TP04 | B3: Technology-enable Retention Mechanism | C3: Focal technology-enabled tacit knowledge retention approach. Interactive Consequence Learning and Digital Feedback (node_id:s003M01TP04) is the single focal practice. Its definition describes uses responsive simulations, animations, indicators, interfaces, or multisensory feedback to make relationships between actions, system states, and consequences experientially perceptible. The retrieved relationship evidence is concentrated in one case source, limiting cross-case generalization. Technology availability is not treated as adoption, and adoption is not treated as retention; the claim is bounded to relationships that explicitly connect this practice to technology and non-ambiguous tacit knowledge. Evidence chain (directional and bounded). Main chain: Artificial Intelligence and Intelligent Computation (node_id:s003M01TE01); Human–Computer Interaction and Immersive Technologies (node_id:s003M01TE02) → Interactive Consequence Learning and Digital Feedback (node_id:s003M01TP04) → Shared Professional Norms and Standards of Judgment (node_id:s003M01TK10). The adoption links identify deployed digital technology families, while the capture/transfer links identify the knowledge object; they do not by themselves establish long-term retention. Secondary chain: Interactive Consequence Learning and Digital Feedback (node_id:s003M01TP04) → Financial, Technical & Information Resources (node_id:s003M01OD03); Human Capacity, Roles & Participation (node_id:s003M01OD05). The evidence therefore supports a configured socio-technical practice, not an autonomous tool. Where evaluation links exist, they indicate measurement of knowledge or outcomes, but measurement remains distinct from durable organizational memory. Retention Mechanism — Experience Amplification. Its dominant function is situated rehearsal, interaction, feedback, demonstration, or internalization; the technology lets learners experience and refine judgment without fully converting that judgment into a durable symbolic representation. Any recorded actions or content are secondary supports. This is the primary classification only. The alternative perspective may appear as a secondary capability—for example, experiential systems can record actions, and codifying systems can support learning—but it does not define the dominant retention function evidenced here. Tacit Knowledge Retained. The bounded target comprises Shared Professional Norms and Standards of Judgment (node_id:s003M01TK10). These forms of knowing are difficult to preserve because skilled action, perceptual discrimination, contextual meaning, and professional judgment are enacted in practice and are only partly verbalizable. The focal approach makes them more retainable by repeatedly exposing learners to their cues or by stabilizing traces that others can retrieve and interpret. Its explicitly linked mitigation/resolution targets are Instructional Design, Delivery, Assessment and Transfer Shortcomings (node_id:s003M01LI04). This supports a mechanism claim, but not a guarantee: capture can omit context, transfer can fail to produce competent performance, and evaluation can measure short-term response rather than longitudinal retention. Conditions and constraints. The practice depends on Financial, Technical & Information Resources (node_id:s003M01OD03); Human Capacity, Roles & Participation (node_id:s003M01OD05). These resources are complementary: technical infrastructure without expert participation and governance yields an available system rather than actionable memory, while expertise without time, access, and process integration cannot populate or validate it. The directly linked constraints are Software, Algorithmic, Data Quality and Interoperability Barriers (node_id:s003M01LI05); Hardware, Sensor and Technical Infrastructure Constraints (node_id:s003M01LI06); Knowledge Continuity, Documentation, Governance, Privacy and Security (node_id:s003M01LI10); Research Design, Measurement and Validation Flaws (node_id:s003M01LI13). They create weakest-link effects involving data quality, usability, infrastructure, cost, workload, privacy, adoption, or validation. Any limitation not linked to this focal practice is excluded from the claim. Integrative theoretical statement. This practice illustrates emerging-technology adoption as a conversion process: digital affordances must be configured into a governed practice, connected to a specific tacit-knowledge object, interpreted by capable participants, and reinforced through use or evaluation. Retention emerges only when those elements jointly preserve knowledge in a form that later actors can enact; the graph supports the pathway, while incomplete longitudinal evidence prevents a stronger causal claim. | D3: Experience Amplification | E3: Interactive feedback technologies retain tacit knowledge by making the consequences of professional decisions visible during action. Artificial intelligence and immersive interfaces present scenarios, indicators, explanations, and multisensory feedback that help learners compare choices with accepted standards and adjust their judgment. The dominant mechanism is Experience Amplification because the learning value lies in experience, correction, and repeated decision-making, not primarily in preserving intuition as a document or dataset. This approach can reinforce shared professional norms, but retention depends on valid feedback, realistic cases, technical reliability, expert oversight, learner participation, and application. Short-term scores or engagement alone cannot demonstrate durable professional judgment. | F3: TK10 Shared Professional Norms and Standards of Judgment | G3: TE01;TE02 -> TP04 -> TK10
A4: s003M01TP11 | B4: Technology-enable Retention Mechanism | C4: Focal technology-enabled tacit knowledge retention approach. Collaborative Knowledge Co-creation through Digital Platforms (node_id:s003M01TP11) is the single focal practice. Its definition describes uses portals, messaging systems, shared virtual environments, and online collaboration platforms to support peer exchange, collective interpretation, user contribution, and shared knowledge construction. The relationship evidence combines material from 3 case sources (c211, c217, c218), so the node represents a cross-case conceptual aggregation, not one event. Technology availability is not treated as adoption, and adoption is not treated as retention; the claim is bounded to relationships that explicitly connect this practice to technology and non-ambiguous tacit knowledge. Evidence chain (directional and bounded). Main chain: Artificial Intelligence and Intelligent Computation (node_id:s003M01TE01); Mobile, Social and Communication Technologies (node_id:s003M01TE07) → Collaborative Knowledge Co-creation through Digital Platforms (node_id:s003M01TP11) → Knowledge Conveyed Through Examples or Demonstration (node_id:s003M01TK02); Unrecognized or Unarticulated Personal Know-how (node_id:s003M01TK04); Shared Professional Norms and Standards of Judgment (node_id:s003M01TK10). The adoption links identify deployed digital technology families, while the capture/transfer links identify the knowledge object; they do not by themselves establish long-term retention. Secondary chain: Collaborative Knowledge Co-creation through Digital Platforms (node_id:s003M01TP11) → External Technological & Infrastructure Environment (node_id:s003M01ED05); Governance, Standards & Formal Control (node_id:s003M01OD01); Financial, Technical & Information Resources (node_id:s003M01OD03); Culture, Trust & Relational Climate (node_id:s003M01OD06). The evidence therefore supports a configured socio-technical practice, not an autonomous tool. Where evaluation links exist, they indicate measurement of knowledge or outcomes, but measurement remains distinct from durable organizational memory. Retention Mechanism — Experience Amplification. Its dominant function is situated rehearsal, interaction, feedback, demonstration, or internalization; the technology lets learners experience and refine judgment without fully converting that judgment into a durable symbolic representation. Any recorded actions or content are secondary supports. This is the primary classification only. The alternative perspective may appear as a secondary capability—for example, experiential systems can record actions, and codifying systems can support learning—but it does not define the dominant retention function evidenced here. Tacit Knowledge Retained. The bounded target comprises Knowledge Conveyed Through Examples or Demonstration (node_id:s003M01TK02); Unrecognized or Unarticulated Personal Know-how (node_id:s003M01TK04); Shared Professional Norms and Standards of Judgment (node_id:s003M01TK10). These forms of knowing are difficult to preserve because skilled action, perceptual discrimination, contextual meaning, and professional judgment are enacted in practice and are only partly verbalizable. The focal approach makes them more retainable by repeatedly exposing learners to their cues or by stabilizing traces that others can retrieve and interpret. Its explicitly linked mitigation/resolution targets are Knowledge Continuity, Documentation, Governance, Privacy and Security (node_id:s003M01LI10). This supports a mechanism claim, but not a guarantee: capture can omit context, transfer can fail to produce competent performance, and evaluation can measure short-term response rather than longitudinal retention. Conditions and constraints. The practice depends on External Technological & Infrastructure Environment (node_id:s003M01ED05); Governance, Standards & Formal Control (node_id:s003M01OD01); Financial, Technical & Information Resources (node_id:s003M01OD03); Culture, Trust & Relational Climate (node_id:s003M01OD06). These resources are complementary: technical infrastructure without expert participation and governance yields an available system rather than actionable memory, while expertise without time, access, and process integration cannot populate or validate it. The directly linked constraints are Individual Ergonomic, Usability and Immediate Safety Risks (node_id:s003M01LI02); Human Physiological, Cognitive-Capacity and Demographic Constraints (node_id:s003M01LI03); Instructional Design, Delivery, Assessment and Transfer Shortcomings (node_id:s003M01LI04); Software, Algorithmic, Data Quality and Interoperability Barriers (node_id:s003M01LI05); Time, Staffing, Expertise, Scheduling and Workload Constraints (node_id:s003M01LI08); Organizational Culture, Leadership and Adoption Barriers (node_id:s003M01LI09). They create weakest-link effects involving data quality, usability, infrastructure, cost, workload, privacy, adoption, or validation. Any limitation not linked to this focal practice is excluded from the claim. Integrative theoretical statement. This practice illustrates emerging-technology adoption as a conversion process: digital affordances must be configured into a governed practice, connected to a specific tacit-knowledge object, interpreted by capable participants, and reinforced through use or evaluation. Retention emerges only when those elements jointly preserve knowledge in a form that later actors can enact; the graph supports the pathway, while incomplete longitudinal evidence prevents a stronger causal claim. | D4: Experience Amplification | E4: Collaborative digital platforms retain tacit knowledge by enabling experts and learners to exchange examples, narrate experience, discuss cases, correct interpretations, and negotiate standards. Artificial intelligence and mobile or social communication technologies expand participation and make unarticulated know-how encounterable through interaction and demonstration. The dominant mechanism is Experience Amplification because knowledge is retained through social learning, collective sensemaking, and repeated contribution rather than through an external record alone. Platforms can preserve supporting traces, but durable retention depends on trust, psychological safety, inclusive participation, governance, accessible infrastructure, and reuse. Without engagement and workflow integration, connectivity produces information exchange rather than shared capability. | F4: TK02 Knowledge Conveyed Through Examples or Demonstration TK04 Unrecognized or Unarticulated Personal Know-how TK10 Shared Professional Norms and Standards of Judgment | G4: TE01;TE07 -> TP11 -> TK02;TK04;TK10
A5: s003M01TP12 | B5: Technology-enable Retention Mechanism | C5: Focal technology-enabled tacit knowledge retention approach. Multimedia and Blended Knowledge Internalization (node_id:s003M01TP12) is the single focal practice. Its definition describes combines digital content, interactive media, online resources, and face-to-face or workplace activities to strengthen demonstration, participation, and knowledge internalization. The relationship evidence combines material from 5 case sources (c210, c224, c218, c217, c219), so the node represents a cross-case conceptual aggregation, not one event. Technology availability is not treated as adoption, and adoption is not treated as retention; the claim is bounded to relationships that explicitly connect this practice to technology and non-ambiguous tacit knowledge. Evidence chain (directional and bounded). Main chain: Human–Computer Interaction and Immersive Technologies (node_id:s003M01TE02); Data, Information, and Knowledge Systems (node_id:s003M01TE04); Mobile, Social and Communication Technologies (node_id:s003M01TE07) → Multimedia and Blended Knowledge Internalization (node_id:s003M01TP12) → Practised Motor and Tool-Operation Skill (node_id:s003M01TK05). The adoption links identify deployed digital technology families, while the capture/transfer links identify the knowledge object; they do not by themselves establish long-term retention. Secondary chain: Multimedia and Blended Knowledge Internalization (node_id:s003M01TP12) → Political, Regulatory & Jurisdictional Environment (node_id:s003M01ED01); External Technological & Infrastructure Environment (node_id:s003M01ED05); Local Utility & Connectivity Conditions (node_id:s003M01ED09); Financial, Technical & Information Resources (node_id:s003M01OD03); Time, Workload & Operational Scheduling (node_id:s003M01OD04); Human Capacity, Roles & Participation (node_id:s003M01OD05). The evidence therefore supports a configured socio-technical practice, not an autonomous tool. Where evaluation links exist, they indicate measurement of knowledge or outcomes, but measurement remains distinct from durable organizational memory. Retention Mechanism — Experience Amplification. Its dominant function is situated rehearsal, interaction, feedback, demonstration, or internalization; the technology lets learners experience and refine judgment without fully converting that judgment into a durable symbolic representation. Any recorded actions or content are secondary supports. This is the primary classification only. The alternative perspective may appear as a secondary capability—for example, experiential systems can record actions, and codifying systems can support learning—but it does not define the dominant retention function evidenced here. Tacit Knowledge Retained. The bounded target comprises Practised Motor and Tool-Operation Skill (node_id:s003M01TK05). These forms of knowing are difficult to preserve because skilled action, perceptual discrimination, contextual meaning, and professional judgment are enacted in practice and are only partly verbalizable. The focal approach makes them more retainable by repeatedly exposing learners to their cues or by stabilizing traces that others can retrieve and interpret. Its explicitly linked mitigation/resolution targets are Instructional Design, Delivery, Assessment and Transfer Shortcomings (node_id:s003M01LI04); Hardware, Sensor and Technical Infrastructure Constraints (node_id:s003M01LI06); Financial and Capital Constraints (node_id:s003M01LI07); Time, Staffing, Expertise, Scheduling and Workload Constraints (node_id:s003M01LI08); Organizational Culture, Leadership and Adoption Barriers (node_id:s003M01LI09). This supports a mechanism claim, but not a guarantee: capture can omit context, transfer can fail to produce competent performance, and evaluation can measure short-term response rather than longitudinal retention. Conditions and constraints. The practice depends on Political, Regulatory & Jurisdictional Environment (node_id:s003M01ED01); External Technological & Infrastructure Environment (node_id:s003M01ED05); Local Utility & Connectivity Conditions (node_id:s003M01ED09); Financial, Technical & Information Resources (node_id:s003M01OD03); Time, Workload & Operational Scheduling (node_id:s003M01OD04); Human Capacity, Roles & Participation (node_id:s003M01OD05). These resources are complementary: technical infrastructure without expert participation and governance yields an available system rather than actionable memory, while expertise without time, access, and process integration cannot populate or validate it. The directly linked constraints are Individual Knowledge and Memory Decay (node_id:s003M01LI01); Instructional Design, Delivery, Assessment and Transfer Shortcomings (node_id:s003M01LI04); Hardware, Sensor and Technical Infrastructure Constraints (node_id:s003M01LI06); Time, Staffing, Expertise, Scheduling and Workload Constraints (node_id:s003M01LI08); Organizational Culture, Leadership and Adoption Barriers (node_id:s003M01LI09); Research Design, Measurement and Validation Flaws (node_id:s003M01LI13). They create weakest-link effects involving data quality, usability, infrastructure, cost, workload, privacy, adoption, or validation. Any limitation not linked to this focal practice is excluded from the claim. Integrative theoretical statement. This practice illustrates emerging-technology adoption as a conversion process: digital affordances must be configured into a governed practice, connected to a specific tacit-knowledge object, interpreted by capable participants, and reinforced through use or evaluation. Retention emerges only when those elements jointly preserve knowledge in a form that later actors can enact; the graph supports the pathway, while incomplete longitudinal evidence prevents a stronger causal claim. | D5: Experience Amplification | E5: Blended technologies retain tacit knowledge by combining digital content with discussion, demonstration, workplace activity, and practice. Immersive interfaces, data platforms, and mobile tools provide videos, examples, prompts, and access, while face-to-face or workplace participation lets learners rehearse motor and tool-operation skills and receive feedback. The dominant mechanism is Experience Amplification because the technology scaffolds internalization through situated action rather than preserving competence as a record. Retention depends on reliable infrastructure, connectivity, sufficient practice time, capable facilitators, organizational support, and alignment between digital material and real tasks. Passive consumption or immediate assessment results do not establish durable transfer into competent performance. | F5: TK05 Practised Motor and Tool-Operation Skill | G5: TE02;TE04;TE07 -> TP12 -> TK05
A6: s003M01TP01 | B6: Technology-enable Retention Mechanism | C6: Focal technology-enabled tacit knowledge retention approach. Model-based Knowledge Representation and Simulation (node_id:s003M01TP01) is the single focal practice. Its dominant activity is the construction of persistent, patient-specific anatomical representations: CT images in DICOM format are reconstructed in Mimics, post-processed in 3-matic or Voxel Dance, and converted into digital or 3D-printed models. Although learners subsequently interact with these artifacts, interaction does not transform a desktop visualization or physical print into an extended-reality practice. The virtual-clinical-scenario evidence (c224M01N15) is conceptually inconsistent with the otherwise model-centered evidence and should be reviewed for reassignment to TP03 rather than used to recode the complete aggregate. Evidence chain (directional and bounded). Main chain: Human–Computer Interaction and Immersive Technologies (node_id:s003M01TE02), Cyber-Physical Systems, IoT, and Smart Environments (node_id:s003M01TE03), Data, Information, and Knowledge Systems (node_id:s003M01TE04), and Imaging, Sensing, and Perception Technologies (node_id:s003M01TE05) → Model-based Knowledge Representation and Simulation (node_id:s003M01TP01) → Practised Motor and Tool-Operation Skill (node_id:s003M01TK05), Trained Sensory and Perceptual Recognition (node_id:s003M01TK06), and Shared Professional Norms and Standards of Judgment (node_id:s003M01TK10). Secondary chain: the focal practice depends on Governance, Standards & Formal Control (node_id:s003M01OD01), Financial, Technical & Information Resources (node_id:s003M01OD03), and Human Capacity, Roles & Participation (node_id:s003M01OD05). Adoption supports the pathway but does not itself establish retention. Retention Mechanism — Digital Coding. The practice principally translates imaging data, anatomical boundaries, vascular pathways, tumour margins, and surgical resection areas into durable, inspectable representations. The decisive counterfactual is representational: without reconstruction and modelling, the patient-specific spatial relationships would not persist in a form that can be revisited, replicated, compared, or used independently of the original clinical encounter. Visual–tactile inspection, demonstration, and surgical rehearsal are downstream uses of the codified model, not evidence that the focal practice is TP03. Experience amplification is therefore not assigned as a second classification. Tacit Knowledge Retained. The representations partially externalize perceptual and procedural judgment by making otherwise difficult spatial relationships visible and manipulable. Evidence links the models to vascular-spatial recognition, localization and resection techniques, surgical application, and standards for safe margins. This does not mean motor skill or judgment is fully codified: competent performance still requires interpretation and practice. The model preserves cues and relationships from which such knowing can be reconstructed; it does not store embodied competence itself. Conditions and constraints. Model fidelity depends on accurate imaging, boundary delineation, preprocessing, printing infrastructure, funding, and medically prepared learners. The practice is constrained by incomplete safe-margin information, unclear sublobar boundaries, glare or refraction, obstructed structures, limited interactivity, production time, technical complexity, and cost (node_id:s003M01LI05; node_id:s003M01LI06; node_id:s003M01LI07; node_id:s003M01LI08). Model redesign can mitigate some visibility and boundary problems, but not eliminate the need for expert validation. Integrative theoretical statement. s003M01TP01 illustrates tacit-knowledge retention through Digital Coding: emerging technologies stabilize clinically meaningful spatial and procedural cues in durable models, while human teaching and rehearsal convert those representations into enacted skill. The evidence supports TP01 as the exclusive practice category; the isolated virtual-scenario item should be separated rather than allowed to blur TP01 with TP03. | D6: Digital Codification | E6: Model-based technologies retain tacit knowledge by converting patient imaging and anatomical relationships into persistent digital or printed representations. Interactive 3D models allow learners to inspect spatial structures, rehearse surgical decisions, compare safe margins, and recover perceptual or procedural cues beyond the original clinical encounter. The dominant mechanism is Digital Codification because imaging, modelling, and data systems externalize anatomy and decision-relevant relationships into revisitable artifacts. These models support motor learning, perceptual recognition, and professional judgment, but they do not store embodied competence itself. Retention requires accurate segmentation, expert validation, appropriate model design, usable interfaces, printing resources, and practice in clinical contexts. | F6: TK05 Practised Motor and Tool-Operation Skill TK06 Trained Sensory and Perceptual Recognition TK10 Shared Professional Norms and Standards of Judgment | G6: TE02;TE03;TE04;TE05 -> TP01 -> TK05;TK06;TK10
A7: s003M01TP07 | B7: Technology-enable Retention Mechanism | C7: Focal technology-enabled tacit knowledge retention approach. Algorithmic Pattern Discovery and Prediction (node_id:s003M01TP07) is the single focal practice. Its definition describes uses ai, machine learning, nlp, statistical learning, or rule-based algorithms to derive classifications, forecasts, detected patterns, and predicted conditions from data. The relationship evidence combines material from 8 case sources (c222, c215, c221, c212, c209, c213…), so the node represents a cross-case conceptual aggregation, not one event. Technology availability is not treated as adoption, and adoption is not treated as retention; the claim is bounded to relationships that explicitly connect this practice to technology and non-ambiguous tacit knowledge. Evidence chain (directional and bounded). Main chain: Artificial Intelligence and Intelligent Computation (node_id:s003M01TE01); Data, Information, and Knowledge Systems (node_id:s003M01TE04); Imaging, Sensing, and Perception Technologies (node_id:s003M01TE05); Security, Privacy, and Trustworthy Technologies (node_id:s003M01TE06) → Algorithmic Pattern Discovery and Prediction (node_id:s003M01TP07) → Trained Sensory and Perceptual Recognition (node_id:s003M01TK06); Shared Professional Norms and Standards of Judgment (node_id:s003M01TK10). The adoption links identify deployed digital technology families, while the capture/transfer links identify the knowledge object; they do not by themselves establish long-term retention. Secondary chain: Algorithmic Pattern Discovery and Prediction (node_id:s003M01TP07) → Political, Regulatory & Jurisdictional Environment (node_id:s003M01ED01); External Technological & Infrastructure Environment (node_id:s003M01ED05); Client, Procurement & Institutional Environment (node_id:s003M01ED06); Supply-Chain & Logistical Environment (node_id:s003M01ED07); Governance, Standards & Formal Control (node_id:s003M01OD01). The evidence therefore supports a configured socio-technical practice, not an autonomous tool. Where evaluation links exist, they indicate measurement of knowledge or outcomes, but measurement remains distinct from durable organizational memory. Retention Mechanism — Digital Coding. Its dominant function is to intercept, structure, model, archive, predict, or translate situated activity and judgment into durable data or representations. Human interpretation remains necessary, but persistence and retrievability—not rehearsal alone—provide the principal retention pathway. This is the primary classification only. The alternative perspective may appear as a secondary capability—for example, experiential systems can record actions, and codifying systems can support learning—but it does not define the dominant retention function evidenced here. Tacit Knowledge Retained. The bounded target comprises Trained Sensory and Perceptual Recognition (node_id:s003M01TK06); Shared Professional Norms and Standards of Judgment (node_id:s003M01TK10). These forms of knowing are difficult to preserve because skilled action, perceptual discrimination, contextual meaning, and professional judgment are enacted in practice and are only partly verbalizable. The focal approach makes them more retainable by repeatedly exposing learners to their cues or by stabilizing traces that others can retrieve and interpret. Its explicitly linked mitigation/resolution targets are Software, Algorithmic, Data Quality and Interoperability Barriers (node_id:s003M01LI05); Hardware, Sensor and Technical Infrastructure Constraints (node_id:s003M01LI06); Time, Staffing, Expertise, Scheduling and Workload Constraints (node_id:s003M01LI08); Knowledge Continuity, Documentation, Governance, Privacy and Security (node_id:s003M01LI10). This supports a mechanism claim, but not a guarantee: capture can omit context, transfer can fail to produce competent performance, and evaluation can measure short-term response rather than longitudinal retention. Conditions and constraints. The practice depends on Political, Regulatory & Jurisdictional Environment (node_id:s003M01ED01); External Technological & Infrastructure Environment (node_id:s003M01ED05); Client, Procurement & Institutional Environment (node_id:s003M01ED06); Supply-Chain & Logistical Environment (node_id:s003M01ED07); Governance, Standards & Formal Control (node_id:s003M01OD01). These resources are complementary: technical infrastructure without expert participation and governance yields an available system rather than actionable memory, while expertise without time, access, and process integration cannot populate or validate it. The directly linked constraints are Software, Algorithmic, Data Quality and Interoperability Barriers (node_id:s003M01LI05); Hardware, Sensor and Technical Infrastructure Constraints (node_id:s003M01LI06); Time, Staffing, Expertise, Scheduling and Workload Constraints (node_id:s003M01LI08); Knowledge Continuity, Documentation, Governance, Privacy and Security (node_id:s003M01LI10). They create weakest-link effects involving data quality, usability, infrastructure, cost, workload, privacy, adoption, or validation. Any limitation not linked to this focal practice is excluded from the claim. Integrative theoretical statement. This practice illustrates emerging-technology adoption as a conversion process: digital affordances must be configured into a governed practice, connected to a specific tacit-knowledge object, interpreted by capable participants, and reinforced through use or evaluation. Retention emerges only when those elements jointly preserve knowledge in a form that later actors can enact; the graph supports the pathway, while incomplete longitudinal evidence prevents a stronger causal claim. | D7: Digital Codification | E7: Algorithmic technologies retain tacit knowledge by translating observations, sensor signals, and expert judgments into classifications, predictions, and decision cues. Artificial intelligence, knowledge systems, sensing technologies, and privacy-supporting tools make perceptual patterns and professional standards explicit enough for comparison, monitoring, and interpretation. The dominant mechanism is Digital Codification because experiential traces become durable analytical representations rather than remaining solely within individual cognition. These outputs can support diagnosis, forecasting, and evaluation, but retention requires representative data, interoperable infrastructure, transparent models, expert validation, privacy safeguards, and workflow integration. Bias, sensor error, context loss, or uncritical automation can preserve misleading patterns instead of knowledge. | F7: TK06 Trained Sensory and Perceptual Recognition TK10 Shared Professional Norms and Standards of Judgment | G7: TE01;TE04;TE05;TE06 -> TP07 -> TK06;TK10
A8: s003M01TP09 | B8: Technology-enable Retention Mechanism | C8: Focal technology-enabled tacit knowledge retention approach. Semantic Knowledge Structuring and Retrieval (node_id:s003M01TP09) is the single focal practice. Its definition describes uses knowledge graphs, semantic metadata, embeddings, vector databases, and meaning-based search to represent knowledge relationships and retrieve contextually relevant information. The relationship evidence combines material from 3 case sources (c219, c222, c214), so the node represents a cross-case conceptual aggregation, not one event. Technology availability is not treated as adoption, and adoption is not treated as retention; the claim is bounded to relationships that explicitly connect this practice to technology and non-ambiguous tacit knowledge. Evidence chain (directional and bounded). Main chain: Artificial Intelligence and Intelligent Computation (node_id:s003M01TE01); Data, Information, and Knowledge Systems (node_id:s003M01TE04); Rule-Based, Decision and Expert Systems (node_id:s003M01TE08) → Semantic Knowledge Structuring and Retrieval (node_id:s003M01TP09) → Knowledge Conveyed Through Examples or Demonstration (node_id:s003M01TK02); Practised Motor and Tool-Operation Skill (node_id:s003M01TK05); Shared Professional Norms and Standards of Judgment (node_id:s003M01TK10); TK09 Shared Professional Language and Contextual Meaning (node_id:s003M01TK09). The adoption links identify deployed digital technology families, while the capture/transfer links identify the knowledge object; they do not by themselves establish long-term retention. Secondary chain: Semantic Knowledge Structuring and Retrieval (node_id:s003M01TP09) → External Technological & Infrastructure Environment (node_id:s003M01ED05); Local Utility & Connectivity Conditions (node_id:s003M01ED09); Governance, Standards & Formal Control (node_id:s003M01OD01); Human Capacity, Roles & Participation (node_id:s003M01OD05); Organizational Structure & Process Design (node_id:s003M01OD08). The evidence therefore supports a configured socio-technical practice, not an autonomous tool. Where evaluation links exist, they indicate measurement of knowledge or outcomes, but measurement remains distinct from durable organizational memory. Retention Mechanism — Digital Coding. Its dominant function is to intercept, structure, model, archive, predict, or translate situated activity and judgment into durable data or representations. Human interpretation remains necessary, but persistence and retrievability—not rehearsal alone—provide the principal retention pathway. This is the primary classification only. The alternative perspective may appear as a secondary capability—for example, experiential systems can record actions, and codifying systems can support learning—but it does not define the dominant retention function evidenced here. Tacit Knowledge Retained. The bounded target comprises Knowledge Conveyed Through Examples or Demonstration (node_id:s003M01TK02); Practised Motor and Tool-Operation Skill (node_id:s003M01TK05); Shared Professional Norms and Standards of Judgment (node_id:s003M01TK10); TK09 Shared Professional Language and Contextual Meaning (node_id:s003M01TK09). These forms of knowing are difficult to preserve because skilled action, perceptual discrimination, contextual meaning, and professional judgment are enacted in practice and are only partly verbalizable. The focal approach makes them more retainable by repeatedly exposing learners to their cues or by stabilizing traces that others can retrieve and interpret. Its explicitly linked mitigation/resolution targets are Instructional Design, Delivery, Assessment and Transfer Shortcomings (node_id:s003M01LI04); Software, Algorithmic, Data Quality and Interoperability Barriers (node_id:s003M01LI05). This supports a mechanism claim, but not a guarantee: capture can omit context, transfer can fail to produce competent performance, and evaluation can measure short-term response rather than longitudinal retention. Conditions and constraints. The practice depends on External Technological & Infrastructure Environment (node_id:s003M01ED05); Local Utility & Connectivity Conditions (node_id:s003M01ED09); Governance, Standards & Formal Control (node_id:s003M01OD01); Human Capacity, Roles & Participation (node_id:s003M01OD05); Organizational Structure & Process Design (node_id:s003M01OD08). These resources are complementary: technical infrastructure without expert participation and governance yields an available system rather than actionable memory, while expertise without time, access, and process integration cannot populate or validate it. The directly linked constraints are Instructional Design, Delivery, Assessment and Transfer Shortcomings (node_id:s003M01LI04); Software, Algorithmic, Data Quality and Interoperability Barriers (node_id:s003M01LI05); Time, Staffing, Expertise, Scheduling and Workload Constraints (node_id:s003M01LI08). They create weakest-link effects involving data quality, usability, infrastructure, cost, workload, privacy, adoption, or validation. Any limitation not linked to this focal practice is excluded from the claim. Integrative theoretical statement. This practice illustrates emerging-technology adoption as a conversion process: digital affordances must be configured into a governed practice, connected to a specific tacit-knowledge object, interpreted by capable participants, and reinforced through use or evaluation. Retention emerges only when those elements jointly preserve knowledge in a form that later actors can enact; the graph supports the pathway, while incomplete longitudinal evidence prevents a stronger causal claim. | D8: Digital Codification | E8: Semantic technologies retain tacit knowledge by organizing cases, demonstrations, procedures, professional language, and judgment into searchable relationships and retrieval structures. Artificial intelligence, data systems, and rule-based tools transform experiential material into knowledge graphs, semantic metadata, embeddings, or expert-system links that later users can navigate and reinterpret. The dominant mechanism is Digital Codification because situated knowledge is preserved as an explicit, durable structure outside the original knower. The approach supports examples, motor procedures, contextual meaning, and professional standards, but retention depends on curated vocabularies, reliable metadata, interoperable systems, expert validation, adequate connectivity, and opportunities to translate retrieved representations into competent practice. | F8: TK02 Knowledge Conveyed Through Examples or Demonstration TK05 Practised Motor and Tool-Operation Skill TK10 Shared Professional Norms and Standards of Judgment TK09 Shared Professional Language and Contextual Meaning | G8: TE01;TE04;TE08 -> TP09 -> TK02;TK05;TK10;TK09
A9: s003M01TP10 | B9: Technology-enable Retention Mechanism | C9: Focal technology-enabled tacit knowledge retention approach. Database-supported Project Knowledge Archiving (node_id:s003M01TP10) is the single focal practice. Its definition describes preserves and retrieves codified project records, narratives, lessons learned, safety information, and operational knowledge through databases, data warehouses, or conventional kms repositories. The relationship evidence combines material from 2 case sources (c221, c227), so the node represents a cross-case conceptual aggregation, not one event. Technology availability is not treated as adoption, and adoption is not treated as retention; the claim is bounded to relationships that explicitly connect this practice to technology and non-ambiguous tacit knowledge. Evidence chain (directional and bounded). Main chain: Human–Computer Interaction and Immersive Technologies (node_id:s003M01TE02); Data, Information, and Knowledge Systems (node_id:s003M01TE04) → Database-supported Project Knowledge Archiving (node_id:s003M01TP10) → TK09 Shared Professional Language and Contextual Meaning (node_id:s003M01TK09). The adoption links identify deployed digital technology families, while the capture/transfer links identify the knowledge object; they do not by themselves establish long-term retention. Secondary chain: Database-supported Project Knowledge Archiving (node_id:s003M01TP10) → Supply-Chain & Logistical Environment (node_id:s003M01ED07). The evidence therefore supports a configured socio-technical practice, not an autonomous tool. Where evaluation links exist, they indicate measurement of knowledge or outcomes, but measurement remains distinct from durable organizational memory. Retention Mechanism — Digital Coding. Its dominant function is to intercept, structure, model, archive, predict, or translate situated activity and judgment into durable data or representations. Human interpretation remains necessary, but persistence and retrievability—not rehearsal alone—provide the principal retention pathway. This is the primary classification only. The alternative perspective may appear as a secondary capability—for example, experiential systems can record actions, and codifying systems can support learning—but it does not define the dominant retention function evidenced here. Tacit Knowledge Retained. The bounded target comprises TK09 Shared Professional Language and Contextual Meaning (node_id:s003M01TK09). These forms of knowing are difficult to preserve because skilled action, perceptual discrimination, contextual meaning, and professional judgment are enacted in practice and are only partly verbalizable. The focal approach makes them more retainable by repeatedly exposing learners to their cues or by stabilizing traces that others can retrieve and interpret. Its explicitly linked mitigation/resolution targets are Knowledge Continuity, Documentation, Governance, Privacy and Security (node_id:s003M01LI10). This supports a mechanism claim, but not a guarantee: capture can omit context, transfer can fail to produce competent performance, and evaluation can measure short-term response rather than longitudinal retention. Conditions and constraints. The practice depends on Supply-Chain & Logistical Environment (node_id:s003M01ED07). These resources are complementary: technical infrastructure without expert participation and governance yields an available system rather than actionable memory, while expertise without time, access, and process integration cannot populate or validate it. The directly linked constraints are no qualifying node. They create weakest-link effects involving data quality, usability, infrastructure, cost, workload, privacy, adoption, or validation. Any limitation not linked to this focal practice is excluded from the claim. Integrative theoretical statement. This practice illustrates emerging-technology adoption as a conversion process: digital affordances must be configured into a governed practice, connected to a specific tacit-knowledge object, interpreted by capable participants, and reinforced through use or evaluation. Retention emerges only when those elements jointly preserve knowledge in a form that later actors can enact; the graph supports the pathway, while incomplete longitudinal evidence prevents a stronger causal claim. | D9: Digital Codification | E9: Database-supported archiving retains tacit knowledge by converting project narratives, records, safety information, and contextual language into durable repositories. Interactive interfaces and knowledge systems enable contributors to record, organize, retrieve, and reuse explanations that would otherwise remain dispersed across individuals or work arrangements. The dominant mechanism is Digital Codification because the practice preserves experience as searchable material independent of the original holder. It supports TK09 Shared Professional Language and Contextual Meaning, yet storage alone cannot guarantee understanding or application. Effective retention requires trustworthy elicitation, metadata, accessible search, privacy governance, stewardship, supply-chain continuity, expert interpretation, and routines that reconnect archived content with action. | F9: TK09 Shared Professional Language and Contextual Meaning | G9: TE02;TE04 -> TP10 -> TK09
