Workbook

Sheet s001_insights
A1: node_id | B1: category | C1: insight | D1: primary_retention_category | E1: retention_mechanism | F1: tacit_knowledge_retained | G1: evidence_chain
A2: s001M01TP03 | B2: Technology-enable Retention Mechanism | C2: Focal technology-enabled tacit knowledge retention approach. Situated Experiential Learning through Extended Reality is classified as Experience Amplification. The aggregated practice uses VR, AR, MR, CAVE, and hybrid environments to reconstruct consequential cues, let learners navigate or act, and return immediate sensory or instructional feedback (node_id:s001M01TP03). Its dominant function is rehearsal and situated perception; 3D assets and logs are supporting representations rather than the principal retained object. Evidence chain (directional and bounded). The practice adopts Artificial Intelligence and Intelligent Computation (node_id:s001M01TE01); Human–Computer Interaction and Immersive Technologies such as Unity, HoloLens, Oculus, HTC VIVE, and CAVE (node_id:s001M01TE02); cyber-physical, modelling, sensing, mobile, and supporting tools (node_id:s001M01TE03; node_id:s001M01TE04; node_id:s001M01TE05; node_id:s001M01TE07; node_id:s001M01TE09). It transfers Trained Sensory and Perceptual Recognition (node_id:s001M01TK06) through clearer and interactive hazard visualization and transfers Shared Professional Norms and Standards of Judgment (node_id:s001M01TK10) through risk assessment, equipment choice, and consequence feedback. It also captures Practised Motor and Tool-Operation Skill, Embodied Posture and Spatial Control, and Immediate Embodied Response (node_id:s001M01TK05; node_id:s001M01TK07; node_id:s001M01TK08) through recorded craft sequences, VR behaviour, and practical performance assessment. Retention mechanism. Experience Amplification follows the mechanism reconstructed cues → learner action → feedback or consequence → stabilized experiential pattern. Cross-case evidence supports this pattern: AR and VR made hazards perceptible and improved identification; virtual excavation enabled practical performance before and after training; problem-first VR required selection under uncertainty and then displayed accident consequences. Long-term evidence is mixed. One VR cohort showed no significant knowledge decline after four weeks and problem-first VR outperformed direct instruction, yet another comparison found significant forgetting after four to five weeks, and long-term practical performance was not tested. Thus the graph supports stronger experiential learning and some retention, not uniform causal persistence. Tacit knowledge retained. The core retained knowledge is embodied hazard recognition and judgment: perceiving hazards, assessing severity and likelihood, choosing protective equipment, navigating space, and responding rapidly. Such knowledge is difficult to retain because passive instruction lacks interaction, learners forget, expertise levels differ, and context-dependent judgment resists full articulation (node_id:s001M01LI01; node_id:s001M01LI03; node_id:s001M01LI04; node_id:s001M01LI10). XR mitigates these limits by permitting safe failure, reproducing otherwise inaccessible or unethical disaster conditions, making consequences visible, and linking knowing to doing. It does not eliminate motivation or expertise-reversal effects. Conditions and constraints. The practice depends on regulatory and ethics controls, external connectivity, physical site conditions, retention-test timing, governance, technical resources, protected training time, participant availability, and task-aligned interface design (node_id:s001M01ED01; node_id:s001M01ED05; node_id:s001M01ED08; node_id:s001M01ED10; node_id:s001M01OD01; node_id:s001M01OD03; node_id:s001M01OD04; node_id:s001M01OD05; node_id:s001M01OD08). Constraints include cybersickness and withdrawal, age and working-memory differences, limited content coverage, interoperability and loading delays, scarce haptics and physical space, development workload, commercialization pressure, and narrow retention measures (node_id:s001M01LI02; node_id:s001M01LI03; node_id:s001M01LI04; node_id:s001M01LI05; node_id:s001M01LI06; node_id:s001M01LI08; node_id:s001M01LI12; node_id:s001M01LI13). Cross-case synthesis and theoretical statement. Heritage interpretation, construction hazard training, energy-use learning, and confined-space exercises are not separate focal practices here; together they reveal a common experiential mechanism. Their complementarity also explains the limits: fidelity without accessible hardware excludes users, immersion without sound instructional design can overload them, and short-term performance without delayed workplace assessment leaves retention uncertain. Emerging XR retains tacit knowledge by amplifying situated experience and allowing safe, consequential practice, but only when governance, design, access, adaptation time, and repeated use convert immersive exposure into durable workplace judgment. | D2: Experience Amplification | E2: Extended-reality technologies retain tacit knowledge by reconstructing consequential workplace cues, enabling learners to act within simulated situations, and returning immediate sensory or instructional feedback. VR, AR, MR, and CAVE environments make hazards perceptible, support equipment selection and spatial navigation, permit safe failure, and reveal consequences that cannot be ethically recreated onsite. Repeated action stabilizes perceptual, motor, postural, response, and professional-judgment patterns. Across cases, hazard identification and practical performance improved, and some four-week persistence appeared, although forgetting was also observed. Durable retention therefore depends on sound instructional design, accessible hardware, adaptation time, governance, and repeated, task-aligned practice with delayed workplace assessment. | F2: Practised Motor and Tool-Operation Skill; Trained Sensory and Perceptual Recognition; Embodied Posture, Balance, and Spatial Control; Immediate Embodied Response to Changing Conditions; Shared Professional Norms and Standards of Judgment | G2: TE01;TE02;TE03;TE04;TE05;TE07;TE09 -> TP03 -> TK05;TK06;TK07;TK08;TK10
A3: s001M01TP12 | B3: Technology-enable Retention Mechanism | C3: Focal technology-enabled tacit knowledge retention approach. Multimedia and Blended Knowledge Internalization is classified as Experience Amplification. It combines digital content, interactive media, online resources, and face-to-face or workplace activity so learners observe demonstrations, contribute, discuss, and apply knowledge (node_id:s001M01TP12). Its dominant function is strengthened experience and social participation, not merely the storage of content. Evidence chain (directional and bounded). Interactive classroom technologies such as Vevox and Mentimeter (node_id:s001M01TE02), Moodle (node_id:s001M01TE04), Padlet and YouTube (node_id:s001M01TE07), and eBooks within the ambiguous technology class (node_id:s001M01TE09) are adopted by Multimedia and Blended Internalization (node_id:s001M01TP12). The practice transfers Practised Motor and Tool-Operation Skill (node_id:s001M01TK05) through technology-supported practical learning and demonstration, and transfers Informal Coordination, Communication, and Escalation Know-how (node_id:s001M01TK11) through group learning. The latter relationship is directly expressed as learning from groupmates. Retention mechanism. Experience Amplification follows digital demonstration and content → active discussion or problem solving → application and peer feedback → internalization. YouTube scaffolding visualization and interactive platforms supply examples; face-to-face participation and small-group exchange allow learners to interpret and rehearse them. The graph reports that 82 percent of respondents felt more involved and that flipped and block structures can reduce cognitive overload. These are plausible enabling outcomes, but no delayed retention test is linked to this practice, so long-term persistence remains unproven. Tacit knowledge retained. The target knowledge is practical digital and construction skill plus the unwritten coordination habits learned through peer collaboration. These are hard to retain where craft inheritance is interrupted, formats fragment, and formal documentation misses interpersonal nuance (node_id:s001M01LI05; node_id:s001M01LI10). Blended learning mitigates passive listening and the theory–practice gap (node_id:s001M01LI04) by making learners active contributors, but it does not automatically resolve absenteeism, unequal participation, or differences in prior education. Conditions and constraints. The practice depends on institutional sponsorship (node_id:s001M01OD02), protected schedules and manageable class sizes (node_id:s001M01OD04), student engagement and co-creation (node_id:s001M01OD05), industry-aligned curriculum design (node_id:s001M01OD08), and the sociocultural diversity of learners (node_id:s001M01ED03). Student absence is an incompletely specified external dependency (node_id:s001M01ED10). Diverse backgrounds, scheduling pressure, and group dynamics constrain results (node_id:s001M01LI03; node_id:s001M01LI08; node_id:s001M01LI09). Cross-case synthesis. Heritage craft display and higher-education blended learning contribute different components to the aggregate. The former suggests that lightweight digital presentation can extend access to craft processes, while the latter shows how interactive platforms, peer collaboration, and block teaching support internalization. The strongest tacit link is not the medium itself but participation around the medium: students interpret demonstrations, compare perspectives, and learn coordination from groupmates. Content availability without these interactions would be codified access rather than experiential retention. Integrative theoretical statement. Blended technologies retain tacit knowledge primarily by amplifying socially situated practice. Digital content becomes durable know-how only when learners participate, receive contextual guidance, obtain feedback, and repeatedly translate representations into coordinated action. Evidence of later performance across different projects would strengthen the retention claim beyond reported engagement and immediate understanding. Institutional support and curriculum alignment are therefore not background variables but constitutive parts of the mechanism; they determine whether multimedia is consumed passively or becomes a scaffold for practice. | D3: Experience Amplification | E3: Blended technologies retain tacit knowledge by combining demonstrations with active discussion, problem solving, workplace application, and peer feedback. Videos, eBooks, Moodle, Padlet, and interactive classroom tools supply examples and reference points; face-to-face and small-group activity lets learners interpret, rehearse, and adapt them. The mechanism amplifies socially situated experience, supporting practical skill and informal coordination rather than merely distributing content. Reported involvement and reduced cognitive overload indicate enabling conditions, but delayed retention remains untested. Persistence therefore depends on institutional sponsorship, protected schedules, manageable groups, inclusive participation, industry-aligned curriculum, and repeated application across projects; passive consumption would amount only to codified access. | F3: Practised Motor and Tool-Operation Skill; Informal Coordination, Communication, and Escalation Know-how | G3: TE02;TE04;TE07;TE09 -> TP12 -> TK05;TK11
A4: s001M01TP01 | B4: Technology-enable Retention Mechanism | C4: Focal technology-enabled tacit knowledge retention approach. Model-based Knowledge Representation and Simulation is classified as Digital Codification. Across the aggregated cases, BIM, 3D/4D models, computational scenarios, and virtual models translate spatial arrangements, construction sequences, hazards, and performance relationships into inspectable representations (node_id:s001M01TP01). The dominant retention function is therefore the preservation and reuse of a model, not repeated embodied rehearsal. Immersive presentation is a secondary delivery capability. Evidence chain (directional and bounded). Human–Computer Interaction and Immersive Technologies, including Unity, CAVE, Navisworks, and SketchUp (node_id:s001M01TE02), together with Data, Information, and Knowledge Systems such as BIM, AutoCAD, Rhinoceros, Revit, and a centralized database (node_id:s001M01TE04), and the specifically evidenced EnergyPlus tool within the ambiguous technology class (node_id:s001M01TE09), are adopted by Model-based Knowledge Representation and Simulation (node_id:s001M01TP01). The only non-ambiguous retention edge is Technology-enabled Practice → captures → Trained Sensory and Perceptual Recognition (node_id:s001M01TK06): 4D BIM simulation made activity-based hazards identifiable at design stage. The linked tacit knowledge is difficult to retain where passive instruction fails to stimulate skill transfer (node_id:s001M01LI04) and where manual rules or sparse data omit complex safety cues (node_id:s001M01LI05). The secondary chain is Technology-enabled Practice → depends on → Culture, Trust and Relational Climate (node_id:s001M01OD06), evidenced by the need for a consciously maintained safety and continuous-improvement culture. Retention mechanism. Digital Codification is justified because the practice externalizes expert hazard recognition into persistent geometry, schedules, risk records, and simulated sequences that can be inspected before work and revisited across projects. The graph distinguishes adoption from retention: the presence of modelling software establishes technical availability; the capture edge to hazard-recognition knowledge establishes codification; effective retention is strongest only where the centralized OHS database preserves and shares information for later projects. Tacit knowledge retained. The retained capability is trained perceptual recognition: noticing activity-based hazards in spatial and temporal context (node_id:s001M01TK06). This know-how is hard to verbalize exhaustively and conventional instruction leaves a knowledge-to-practice gap. The model mitigates that gap by making otherwise latent relationships among design, sequence, and hazard visible, while the database component counters loss of OHS information as personnel change (node_id:s001M01LI10). BIM also reduced stakeholder document-approval time in one case, mitigating part of the workload constraint (node_id:s001M01LI08), but that efficiency is not itself evidence of knowledge retention. Conditions and constraints. Implementation is constrained by capital and maintenance cost (node_id:s001M01LI07), limited BIM and OHS-model expertise (node_id:s001M01LI08), and the quality limits attached to formal rules and data (node_id:s001M01LI05). The dependence on safety and learning culture means that a technically available model may remain unused or fail to become organizational memory. Cross-case synthesis and theoretical statement. The cases contribute different components rather than different practices: heritage and apartment models establish representation, BIM cases establish design communication and sequence simulation, and the OHS cases connect modelling to hazard recognition and future-project reuse. The strongest retention evidence comes from the OHS chain because it joins simulation to a named tacit capability and then to centralized continuity. The energy and presentation examples demonstrate adoption and representation but do not independently prove retention. Emerging modelling technologies therefore retain tacit know-how when organizations convert situated expert recognition into a governed, revisitable representation, preserve the related decisions and lessons, and embed the artefact in continuous-improvement routines; adoption without capture, database continuity, and cultural use remains only technological deployment. | D4: Digital Codification | E4: Modeling technologies retain tacit hazard-recognition knowledge by translating experts’ spatial, sequencing, and performance judgments into BIM, 3D/4D models, simulations, and linked risk records. These representations make latent relationships visible before construction, allow teams to inspect activity-based hazards, and preserve decisions for later projects. Centralized OHS databases strengthen continuity by storing and sharing the modeled information beyond individual staff tenure. Retention depends on expert validation, adequate modeling competence, governed data, and a safety-oriented continuous-improvement culture. Software adoption alone is insufficient: the mechanism becomes retention only when captured cues remain revisitable, interpretable, and routinely reused in design reviews, training, and project learning. | F4: Trained Sensory and Perceptual Recognition | G4: TE02;TE04;TE09 -> TP01 -> TK06
A5: s001M01TP06 | B5: Technology-enable Retention Mechanism | C5: Focal technology-enabled tacit knowledge retention approach. Worker Activity and State Capture through Wearable Sensors and Cameras is classified as Digital Codification. IMUs, wearable cameras, eye tracking, and video analysis intercept embodied work and convert posture, movement, gaze, external load, and task context into measurable records (node_id:s001M01TP06). The durable data representation is the dominant function; feedback or rehearsal is not the primary mechanism. Evidence chain (directional and bounded). Human–Computer Interaction and Immersive Technologies, specifically HoloLens eye and head gaze capture (node_id:s001M01TE02), and Imaging, Sensing, and Perception Technologies, including multiple IMUs and wearable cameras (node_id:s001M01TE05), are adopted by Worker Activity and State Capture (node_id:s001M01TP06). The practice captures Trained Sensory and Perceptual Recognition (node_id:s001M01TK06) by detecting abnormal or hazardous postures, and it captures and evaluates Embodied Posture, Balance, and Spatial Control (node_id:s001M01TK07) by combining sensor posture with video-observed hand weight to estimate lumbar load. The associated knowledge is hard to capture uniformly because individual bodies differ and motivation affects workplace transfer (node_id:s001M01LI03; node_id:s001M01LI04). Retention mechanism. Digital Codification operates as activity → sensor/video trace → calculated posture or workload representation → comparison and later assessment. This preserves aspects of embodied know-how that workers may not verbalize, including how they position themselves and handle loads. It remains a partial codification: the data represent observable posture and state, not the full situated reasons behind a worker's action. The graph supports capture and evaluation more strongly than transfer or long-term reuse. Tacit knowledge retained. The focal content is perceptual hazard recognition and embodied posture control. Video and IMU measurements make otherwise fleeting bodily performance inspectable, enabling organizations to identify risky patterns and potentially design assistive technology. The practice mitigates a measurement weakness only conditionally: collecting more observations may improve workload estimates, but one study found no clear correlation between workload and assistive technologies and an unclear target population (node_id:s001M01LI13). Thus the graph does not demonstrate that recorded data became retained operational know-how. Conditions and constraints. Regulatory evaluation frameworks such as OWAS, RULA, REBA, and HOHSRAM provide an external interpretation standard (node_id:s001M01ED01); access to actual job sites supplies the physical context needed to relate sensors to work (node_id:s001M01ED08); and individual–technology compatibility shapes implementation (node_id:s001M01OD08). Mixed learner characteristics, narrow samples, and uncertain construct validity constrain generalization (node_id:s001M01LI03; node_id:s001M01LI13; node_id:s001M01LI14). Cross-case synthesis and theoretical statement. The workload and mixed-reality cases identify complementary forms of capture: body-worn devices record the worker, while eye and head tracking record attention inside an instructional environment. Both depend on interpretation standards and representative populations. A measured posture may indicate risk without explaining the practical trade-off that produced it, and gaze may indicate attention without establishing comprehension. Retention therefore requires expert annotation, comparison over time, and feedback into redesigned tasks or training. Longitudinal evidence showing safer later performance would be needed to close the chain from measurement to retained capability. Wearables support tacit-knowledge retention when ephemeral embodied action is converted into interpretable, governed records and then fed back into practice; sensing alone records performance without proving organizational learning. | D5: Digital Codification | E5: Wearable sensors and cameras retain tacit knowledge by converting fleeting embodied activity into durable, interpretable records. IMUs, wearable video, eye tracking, and workload analysis capture posture, movement, gaze, load handling, and task context that workers may struggle to verbalize. Analysts can compare traces over time, identify hazardous patterns, and use the findings to redesign work, assistive technology, or training. The codification remains partial because measurements represent observable action, not every situated reason behind it. Retention therefore requires expert annotation, regulatory interpretation, representative samples, privacy safeguards, and feedback into practice; sensing alone documents performance without demonstrating transfer or safer long-term behavior. | F5: Trained Sensory and Perceptual Recognition; Embodied Posture, Balance, and Spatial Control | G5: TE02;TE05 -> TP06 -> TK06;TK07
A6: s001M01TP07 | B6: Technology-enable Retention Mechanism | C6: Focal technology-enabled tacit knowledge retention approach. Algorithmic Pattern Discovery and Prediction is classified as Digital Codification. AI, machine learning, NLP, statistical learning, and rules transform unstructured reports, gaze data, and operating measurements into features, classifications, forecasts, and detected patterns (node_id:s001M01TP07). The dominant function is the extraction and durable representation of latent regularities, not situated rehearsal. Evidence chain (directional and bounded). Artificial Intelligence and Intelligent Computation—NLP, deep learning, CNNs, Word2Vec, GPT-4o extraction, ensemble classifiers, and predictive analytics—is the principal adopted technology (node_id:s001M01TE01), with Python grouped as a supporting ambiguous technology (node_id:s001M01TE09). The practice captures and transfers Trained Sensory and Perceptual Recognition (node_id:s001M01TK06) by extracting accident precursors and non-explicit semantic associations, and captures Shared Professional Norms and Standards of Judgment (node_id:s001M01TK10) by identifying the importance of risk factors, scenario-specific hazards, temporary support, soil stability, and material fatigue. These knowledge types are difficult to retain because manual rules omit complex texts, classification is subjective, and contextual judgment resists full automation (node_id:s001M01LI05; node_id:s001M01LI08; node_id:s001M01LI10). Retention mechanism. Digital Codification proceeds from historical data → preprocessing and representation → learned pattern or prediction → retrievable classification and decision cue. Cross-case evidence supports automatic feature extraction from accident narratives, requirement extraction from bids, learner-pattern classification, and predictive monitoring. Algorithms reduce dependence on manually designed features and large-scale human classification, mitigating software/data barriers and workload (node_id:s001M01LI05; node_id:s001M01LI08). They also surface information for archiving and immediate sharing. Yet discovery is not automatically retention: the graph provides limited evidence that predictions were repeatedly used, validated, or embedded in routines. Tacit knowledge retained. The strongest retained content is latent safety recognition and professional risk judgment. Narrative phrases and CNN representations make antecedents that experts perceive implicitly available for comparison across reports. This can broaden organizational memory beyond individual recall. However, overlapping vocabulary produced misclassification, language specificity reduced portability, object-strike performance remained weak, and the theoretical framework had not become a practical tool. The data therefore support codification of candidate tacit patterns, not a complete replacement for expert interpretation. Conditions and constraints. The practice depends on representative corpora and integrated infrastructure (node_id:s001M01OD03), leadership sponsorship and safety-management commitment (node_id:s001M01OD02), a knowledge-sharing and safety culture (node_id:s001M01OD06), and, for heating prediction, climatic context (node_id:s001M01ED04). Constraints include data imbalance, OCR and format limits, infrastructure gaps, underutilization under authoritarian leadership, privacy risks, operational variability, and limited validation (node_id:s001M01LI05; node_id:s001M01LI06; node_id:s001M01LI09; node_id:s001M01LI10; node_id:s001M01LI11; node_id:s001M01LI13; node_id:s001M01LI14). Cross-case synthesis and theoretical statement. Accident classification offers the clearest codification chain because latent phrases are linked to named safety knowledge; bid extraction, learner classification, project monitoring, and heating prediction show the broader analytical capability but not the same strength of retention evidence. The cases also expose a recurrent trade-off between scale and meaning: algorithms can process more traces than experts, yet their categories inherit corpus imbalance, language boundaries, labels, and infrastructure conditions. Algorithmic technologies retain tacit knowledge by converting dispersed experiential traces into reusable pattern representations, but those representations become actionable organizational memory only through expert validation, adequate data, leadership support, contestable classifications, and incorporation into real decisions. | D6: Digital Codification | E6: Algorithmic technologies retain tacit knowledge by transforming experience traces into reusable classifications, patterns, forecasts, and decision cues. AI, machine learning, and NLP preprocess accident narratives, gaze data, bid material, and operating measurements, then surface hidden precursors, semantic associations, and risk factors that manual rules may miss. These codified patterns can support search, monitoring, and professional judgment while reducing classification workload. However, discovery becomes organizational memory only when outputs are validated by experts, supported by representative data and infrastructure, and embedded in real decisions. Bias, privacy, context loss, weak leadership, or limited validation can otherwise preserve misleading patterns rather than knowledge. | F6: Trained Sensory and Perceptual Recognition; Shared Professional Norms and Standards of Judgment | G6: TE01;TE09 -> TP07 -> TK06;TK10
A7: s001M01TP08 | B7: Technology-enable Retention Mechanism | C7: Focal technology-enabled tacit knowledge retention approach. Generative Knowledge Synthesis and Content Production is classified as Digital Codification. The practice combines requirements, embeddings, retrieved organizational examples, and generative models to produce new drafts and reports (node_id:s001M01TP08). Its dominant retention function is to reactivate preserved organizational material through a durable semantic representation and generated artefact; conversational interaction is secondary. Evidence chain (directional and bounded). Artificial Intelligence and Intelligent Computation—GPT-4o, embeddings, cosine similarity, few-shot prompting, NLP, and LangChain orchestration (node_id:s001M01TE01)—is combined with a Streamlit interface (node_id:s001M01TE02), Pinecone vector storage (node_id:s001M01TE04), and API access (node_id:s001M01TE09). These technologies are adopted by Generative Knowledge Synthesis (node_id:s001M01TP08), which transfers Organizational Culture and Unwritten Working Practices (node_id:s001M01TK12) through an AI system drawing on historical bids. This tacit knowledge is difficult to capture where incentives and trust are weak (node_id:s001M01LI09) and is vulnerable to staff turnover, fragmented records, and context loss (node_id:s001M01LI10). Retention mechanism. Digital Codification operates through historical documents → chunking and embeddings → semantic retrieval → contextual prompting → generated methodology → expert review. Retrieval grounds the output in firm-specific history, allowing prior ways of working to be surfaced when a new request arrives. This is stronger than simple model availability because the graph documents an integrated proof of concept and transfer relation. Effective retention nevertheless remains conditional: the system generates only methodology text, and organizational judgment is not fully contained in the corpus or model. Tacit knowledge retained. The focal content is historically developed organizational practice embodied in earlier bids—how the firm frames methods, responds to requirements, and structures persuasive technical content. Semantic retrieval and generation mitigate fragmented storage, inconsistent documentation, manual drafting effort, limited knowledge transfer, and turnover-related loss. They do not eliminate expert contextual judgment: each bid requires customization, nuanced risks make full automation impractical, and hallucination or confidentiality risk may weaken trust in the resulting memory. Conditions and constraints. The practice depends on client and procurement rules (node_id:s001M01ED06), document standards and stewardship (node_id:s001M01OD01), leadership sponsorship (node_id:s001M01OD02), high-quality centralized data and information-system readiness (node_id:s001M01OD03), openness to digital transformation (node_id:s001M01OD06), and organizational maturity and workflow fit (node_id:s001M01OD08). PDF-only processing, absent OCR, small historical corpora, third-party APIs, fragmented data, limited training, and underuse constrain scaling (node_id:s001M01LI05; node_id:s001M01LI08; node_id:s001M01LI09; node_id:s001M01LI10; node_id:s001M01LI14). Cross-case synthesis and theoretical statement. The bid system supplies the most direct mechanism evidence: retrieved examples shape a new methodology draft and human reviewers remain responsible for project-specific meaning. Net Zero Cloud broadens the category to automated reporting, but the graph does not connect that reporting to the same tacit-knowledge node; it should therefore be treated as adoption evidence, not an additional retention practice. Retention quality should be assessed through provenance, reviewer correction, later reuse, and whether outputs improve decisions without flattening exceptions. Generative AI retains tacit organizational knowledge when it is coupled to a governed retrieval layer, standardized historical corpus, auditable provenance, and expert review. Without data readiness, trust, confidentiality controls, and contextual validation, generation recombines text but does not secure actionable memory. | D7: Digital Codification | E7: Generative technologies retain tacit organizational knowledge by reactivating prior work practices when new tasks arise. Historical bids are segmented, embedded, stored, and semantically retrieved; relevant examples then ground prompts that generate a methodology draft for expert review. This chain converts fragmented experience into a reusable artifact while preserving links to firm-specific precedent. Retention quality depends on governed documents, adequate corpus breadth, provenance, reviewer correction, infrastructure, and workflow fit. The model cannot contain every contextual judgment, and generated text is not automatically valid knowledge. Its value lies in helping experts recover, adapt, and transmit unwritten practices despite turnover and documentation gaps. | F7: Organizational Culture and Unwritten Working Practices | G7: TE01;TE02;TE04;TE09 -> TP08 -> TK12
A8: s001M01TP09 | B8: Technology-enable Retention Mechanism | C8: Focal technology-enabled tacit knowledge retention approach. Semantic Knowledge Structuring and Retrieval is classified as Digital Codification. Knowledge graphs, metadata, embeddings, vector databases, and meaning-based search organize relationships and create durable retrieval paths (node_id:s001M01TP09). The dominant function is representational persistence and recall rather than rehearsal. Evidence chain (directional and bounded). Artificial Intelligence and Intelligent Computation, including text embeddings and cosine similarity (node_id:s001M01TE01), and Data, Information, and Knowledge Systems, specifically Pinecone vector storage (node_id:s001M01TE04), are adopted by Semantic Knowledge Structuring and Retrieval (node_id:s001M01TP09). The non-ambiguous retention chain is Technology-enabled Practice → transfers → Practised Motor and Tool-Operation Skill (node_id:s001M01TK05): an interactive knowledge graph digitizes the sequence of wooden construction, rammed-earth work, and associated intangible-cultural-heritage skills. The skill is difficult to retain because inheritance is interrupted (node_id:s001M01LI10), while fragmented formats restrict cross-platform reuse (node_id:s001M01LI05). No organizational or environmental dependency and no mitigation or resolve edge is returned for the focal practice. Retention mechanism. Digital Codification converts a craft sequence or historical document into structured entities, semantic metadata, embeddings, and indexed relationships, then retrieves a contextually relevant representation. For craftsmanship, the knowledge graph makes process order available beyond the original practitioner; for bids, vector search ranks similar proposals. Only the craftsmanship relation is explicitly tied to tacit knowledge, so bid retrieval should not be counted as a second retention practice. Tacit knowledge retained. The retained content is practised motor and tool-operation skill represented through ordered craft processes. The representation can preserve sequence and access, but the graph does not show that users can reproduce the embodied quality of the skill from the digital structure alone. Accordingly, the evidence supports partial externalization and transfer, not complete substitution for demonstration, practice, or expert correction. Conditions and constraints. More than 70 percent of referenced projects encounter data-format or interoperability problems, and the bid knowledge base contains only 13 documents from two firms. These limitations narrow retrieval coverage and portability. Cross-case synthesis. The heritage graph and bid-retrieval cases demonstrate the same technical logic but different evidentiary strength. Both structure dispersed material and make it searchable by relation or meaning. Only the heritage case links that function to a named tacit skill, while the bid case establishes retrieval of similar documents without a corresponding tacit-knowledge edge in this focal subgraph. This distinction prevents corpus size, search quality, or semantic similarity from being mistaken for retention. Theoretical implication. Semantic structure can preserve the order, provenance, and relationships surrounding practice, which are often lost in isolated files. It can also support boundary crossing by letting later users approach knowledge through task meaning rather than exact keywords. Yet retrieval remains representational: a returned craft sequence must still be interpreted, demonstrated, and embodied by a learner. Evaluation should therefore test whether users can find the right episode and perform competently in a changed context. Semantic technologies support tacit-knowledge retention by creating durable relational pathways to examples and procedures, but actionable retention depends on interoperable standards, adequate metadata, sufficient corpus breadth, expert curation, and complementary human enactment. | D8: Digital Codification | E8: Semantic technologies retain tacit knowledge by converting craft sequences into structured entities, metadata, embeddings, relationships, and meaning-based retrieval paths. In the heritage case, a knowledge graph preserves the order and relationships of wooden construction and rammed-earth practices so later users can approach skills beyond the original practitioner. Vector search similarly retrieves related bid examples, although that case lacks an explicit tacit-knowledge link. Codification is therefore partial: structured representations provide durable access but cannot replace demonstration, enactment, or expert correction. Effective retention requires interoperable formats, adequate metadata, sufficient corpus breadth, curation, and opportunities to translate retrieved representations back into competent action. | F8: Practised Motor and Tool-Operation Skill | G8: TE01;TE04 -> TP09 -> TK05
A9: s001M01TP10 | B9: Technology-enable Retention Mechanism | C9: Focal technology-enabled tacit knowledge retention approach. Database-supported Project Knowledge Archiving is classified as Digital Codification. It preserves project narratives, lessons learned, safety information, and operational records in data warehouses, conventional KMS repositories, SQL databases, and applications (node_id:s001M01TP10). The dominant function is explicitly durable storage and retrieval. Evidence chain (directional and bounded). PowerApps interfaces (node_id:s001M01TE02), data warehouses, databases, digital KMS, Excel, Azure, and SQL (node_id:s001M01TE04), audio/video recording (node_id:s001M01TE05), and rule-based macros (node_id:s001M01TE08) are adopted by the archive practice. It captures or transfers Knowledge Conveyed Through Examples, Unrecognized Personal Know-how, Practised Motor Skill, Shared Professional Judgment, Informal Coordination Know-how, and Organizational Culture and Unwritten Practices (node_id:s001M01TK02; node_id:s001M01TK04; node_id:s001M01TK05; node_id:s001M01TK10; node_id:s001M01TK11; node_id:s001M01TK12). Stories preserve intuitive geotechnical responses, risk judgments, failure lessons, coordination norms, and organizational identity; databases preserve craft sequences, OHS lessons, and prior-phase information. Retention mechanism. Digital Codification proceeds from elicited story or project activity → recording and transcription → curation, tagging, and structured asset → database integration → retrieval, monitoring, and reuse. Multiple cases show a common mechanism despite different media: data warehousing stores lessons learned; storytelling converts nuanced experience into reusable narrative artefacts; centralized OHS databases carry prior-project risk information into later monitoring. The archive therefore externalizes aspects of intuition without claiming that every nuance becomes explicit. Tacit knowledge retained. The practice targets knowledge that is intuitive, example-dependent, socially embedded, or hard to articulate. These forms are threatened by retirement, turnover, temporary teams, formal documents that omit context, knowledge hoarding, and weak trust (node_id:s001M01LI09; node_id:s001M01LI10). Storytelling improves capture of contextual, emotional, and situational detail; centralized storage reduces dependence on individual memory and makes information available to future projects. Privacy safeguards, restricted access, and anonymization are necessary because sensitive stories can otherwise make retention unethical or unusable. Conditions and constraints. The practice depends on regulatory standards for OHS records (node_id:s001M01ED01), workforce demographic pressure (node_id:s001M01ED02), stewardship and review cycles (node_id:s001M01OD01), leadership and cultural reinforcement (node_id:s001M01OD02), technical and financial resources (node_id:s001M01OD03), protected time (node_id:s001M01OD04), psychological safety (node_id:s001M01OD06), and incentives (node_id:s001M01OD07). Cost and slow benefits (node_id:s001M01LI07), facilitation and curation workload (node_id:s001M01LI08), and cultural resistance (node_id:s001M01LI09) create weakest-link effects: failure at elicitation, trust, curation, governance, or retrieval can prevent a stored artefact from becoming organizational memory. Cross-case synthesis. The archive combines two different input pathways: direct digital recording of processes and deliberate human elicitation through stories. Their convergence is theoretically important. Process records improve continuity and traceability, while narratives recover motives, emotions, contingencies, and interpersonal knowledge omitted by formal documents. A repository that receives only one pathway risks either context-poor data or unstructured stories that cannot be found. Integrative theoretical statement. Emerging databases enable tacit-knowledge retention when human elicitation and governance convert situated experience into a findable, trusted, and repeatedly used asset. Technology redistributes expert work toward narration, validation, stewardship, and contextual interpretation; it does not eliminate that work. The evidence supports continuity and reuse, but effective retention still depends on whether later users can translate codified narratives and records back into competent action and whether reuse metrics reveal that the archive is functioning as organizational memory. | D9: Digital Codification | E9: Database technologies retain tacit knowledge by moving experience through elicitation, recording, transcription, curation, tagging, integration, retrieval, and reuse. Data warehouses preserve lessons learned; digital storytelling captures motives, emotions, examples, and interpersonal nuance; OHS databases carry risk information across projects. Together, these systems counter turnover, retirement, temporary teams, fragmented records, and formal documents that omit context. Organizational memory still depends on psychological safety, incentives, privacy safeguards, stewardship, leadership, protected time, and search. Technology shifts expert work toward narration, validation, and interpretation: a stored asset contributes to retention only when later users trust it, retrieve it, and translate it into competent action. | F9: Knowledge Conveyed Through Examples or Demonstration; Unrecognized or Unarticulated Personal Know-how; Practised Motor and Tool-Operation Skill; Shared Professional Norms and Standards of Judgment; Informal Coordination, Communication, and Escalation Know-how; Organizational Culture and Unwritten Working Practices | G9: TE02;TE04;TE05;TE08 -> TP10 -> TK02;TK04;TK05;TK10;TK11;TK12
A10: s001M01TP13 | B10: Technology-enable Retention Mechanism | C10: Focal technology-enabled tacit knowledge retention approach. Criteria-based Performance Evaluation and Ranking is classified as Digital Codification because questionnaires, tests, indicators, and benchmarked scores convert otherwise situated performance and judgment into comparable records (node_id:s001M01TP13). This is an assessment-centred codification, not a training or capture mechanism in itself. Evidence chain (directional and bounded). Human–Computer Interaction technologies such as Google Forms, a web application, and Qualtrics (node_id:s001M01TE02), together with Microsoft Excel as a data system (node_id:s001M01TE04), are adopted by Criteria-based Evaluation (node_id:s001M01TP13). The practice evaluates Shared Professional Norms and Standards of Judgment (node_id:s001M01TK10): retained safety knowledge is connected to safe work practices, and VR practical assessment asks participants to identify, evaluate, and respond to excavation hazards. The query provides no direct capture or transfer edge, no tacit-knowledge limitation edge specific to this evaluated node, and no mitigation or resolve relationship. Retention mechanism. Digital Codification is justified because the practice makes performance legible through pre/post/retention questionnaires, practical hazard assessments, model metrics, rankings, and OHS indicators. These records can diagnose change and support comparison. Yet evaluation is evidence about retention only when measurement timing and construct validity match the tacit capability. A questionnaire score cannot be assumed to represent embodied workplace action. Tacit knowledge retained. The evaluated content is professional safety judgment—recognizing hazards, appraising severity, and selecting an appropriate response. The graph supports evaluation of this judgment but not the mechanism by which it was retained. The practice should therefore be treated as a verification layer around other learning practices, rather than as proof that the assessment technology preserved knowledge. Conditions and constraints. OHS indicators depend on external regulatory standards (node_id:s001M01ED01). Learner preferences are heterogeneous and not fixed (node_id:s001M01LI03), while questioned learning-style validity and null physical-performance differences expose construct and validation problems (node_id:s001M01LI13). Cross-case synthesis. The aggregate combines fuzzy multi-criteria comparison of training media, practical VR hazard assessment, repeated knowledge tests, workload questionnaires, classifier benchmarks, and OHS monitoring. These are measurement components, not separate retention practices. Together they show that evaluation can examine both declarative recall and situated response, but the measures are not interchangeable. Delayed tests assess persistence, practical scenarios assess enactment, and algorithmic metrics assess model performance rather than human knowledge. Analytical boundary and theoretical statement. A valid retention claim requires temporal evidence and a measure close to the tacit capability of interest. Pre/post gains show acquisition; a four-week score shows persistence; safe action in a changed setting provides stronger transfer evidence. Regulatory benchmarks add legitimacy but may not capture local judgment. Scores also require interpretation by instructors, safety professionals, or managers; otherwise the record remains detached from intervention. Digital evaluation can stabilize evidence of tacit performance as organizational data, reveal decay or mismatch, and direct refresher learning, but it contributes to retention only when valid measures are linked to repeated learning, corrective feedback, later competent action, and organizational decisions about how practice should change. | D10: Digital Codification | E10: Assessments assist retention by converting situated judgment and performance into comparable evidence. Forms, web applications, spreadsheets, tests, hazard scenarios, rankings, and OHS indicators record what learners identify, evaluate, remember, and enact. Repeated or delayed measures can reveal knowledge decay, diagnose mismatches, trigger refresher learning, and guide organizational decisions. Yet assessment is a verification layer, not the learning mechanism, and scores cannot represent embodied workplace competence. Its contribution depends on valid constructs, appropriate timing, regulatory alignment, corrective feedback, and later performance in changed settings. When these conditions hold, evaluation stabilizes evidence of professional judgment and helps organizations maintain it over time. | F10: Shared Professional Norms and Standards of Judgment | G10: TE02;TE04 -> TP13 -> TK10

Sheet Sheet1
A1: node id | B1: retention mechanism | C1: tacit knowledge retained | D1: evidence chain
A2: primary category: Experience Amplification
A3: =s001_insights!A2 -> s001M01TP03 | B3: =s001_insights!E2 -> Extended-reality technologies retain tacit knowledge by reconstructing consequential workplace cues, enabling learners to act within simulated situations, and returning immediate sensory or instructional feedback. VR, AR, MR, and CAVE environments make hazards perceptible, support equipment selection and spatial navigation, permit safe failure, and reveal consequences that cannot be ethically recreated onsite. Repeated action stabilizes perceptual, motor, postural, response, and professional-judgment patterns. Across cases, hazard identification and practical performance improved, and some four-week persistence appeared, although forgetting was also observed. Durable retention therefore depends on sound instructional design, accessible hardware, adaptation time, governance, and repeated, task-aligned practice with delayed workplace assessment. | C3: =s001_insights!F2 -> Practised Motor and Tool-Operation Skill; Trained Sensory and Perceptual Recognition; Embodied Posture, Balance, and Spatial Control; Immediate Embodied Response to Changing Conditions; Shared Professional Norms and Standards of Judgment | D3: =s001_insights!G2 -> TE01;TE02;TE03;TE04;TE05;TE07;TE09 -> TP03 -> TK05;TK06;TK07;TK08;TK10
A4: =s001_insights!A3 -> s001M01TP12 | B4: =s001_insights!E3 -> Blended technologies retain tacit knowledge by combining demonstrations with active discussion, problem solving, workplace application, and peer feedback. Videos, eBooks, Moodle, Padlet, and interactive classroom tools supply examples and reference points; face-to-face and small-group activity lets learners interpret, rehearse, and adapt them. The mechanism amplifies socially situated experience, supporting practical skill and informal coordination rather than merely distributing content. Reported involvement and reduced cognitive overload indicate enabling conditions, but delayed retention remains untested. Persistence therefore depends on institutional sponsorship, protected schedules, manageable groups, inclusive participation, industry-aligned curriculum, and repeated application across projects; passive consumption would amount only to codified access. | C4: =s001_insights!F3 -> Practised Motor and Tool-Operation Skill; Informal Coordination, Communication, and Escalation Know-how | D4: =s001_insights!G3 -> TE02;TE04;TE07;TE09 -> TP12 -> TK05;TK11
A5: primary category: Digital Codification
A6: =s001_insights!A4 -> s001M01TP01 | B6: =s001_insights!E4 -> Modeling technologies retain tacit hazard-recognition knowledge by translating experts’ spatial, sequencing, and performance judgments into BIM, 3D/4D models, simulations, and linked risk records. These representations make latent relationships visible before construction, allow teams to inspect activity-based hazards, and preserve decisions for later projects. Centralized OHS databases strengthen continuity by storing and sharing the modeled information beyond individual staff tenure. Retention depends on expert validation, adequate modeling competence, governed data, and a safety-oriented continuous-improvement culture. Software adoption alone is insufficient: the mechanism becomes retention only when captured cues remain revisitable, interpretable, and routinely reused in design reviews, training, and project learning. | C6: =s001_insights!F4 -> Trained Sensory and Perceptual Recognition | D6: =s001_insights!G4 -> TE02;TE04;TE09 -> TP01 -> TK06
A7: =s001_insights!A5 -> s001M01TP06 | B7: =s001_insights!E5 -> Wearable sensors and cameras retain tacit knowledge by converting fleeting embodied activity into durable, interpretable records. IMUs, wearable video, eye tracking, and workload analysis capture posture, movement, gaze, load handling, and task context that workers may struggle to verbalize. Analysts can compare traces over time, identify hazardous patterns, and use the findings to redesign work, assistive technology, or training. The codification remains partial because measurements represent observable action, not every situated reason behind it. Retention therefore requires expert annotation, regulatory interpretation, representative samples, privacy safeguards, and feedback into practice; sensing alone documents performance without demonstrating transfer or safer long-term behavior. | C7: =s001_insights!F5 -> Trained Sensory and Perceptual Recognition; Embodied Posture, Balance, and Spatial Control | D7: =s001_insights!G5 -> TE02;TE05 -> TP06 -> TK06;TK07
A8: =s001_insights!A6 -> s001M01TP07 | B8: =s001_insights!E6 -> Algorithmic technologies retain tacit knowledge by transforming experience traces into reusable classifications, patterns, forecasts, and decision cues. AI, machine learning, and NLP preprocess accident narratives, gaze data, bid material, and operating measurements, then surface hidden precursors, semantic associations, and risk factors that manual rules may miss. These codified patterns can support search, monitoring, and professional judgment while reducing classification workload. However, discovery becomes organizational memory only when outputs are validated by experts, supported by representative data and infrastructure, and embedded in real decisions. Bias, privacy, context loss, weak leadership, or limited validation can otherwise preserve misleading patterns rather than knowledge. | C8: =s001_insights!F6 -> Trained Sensory and Perceptual Recognition; Shared Professional Norms and Standards of Judgment | D8: =s001_insights!G6 -> TE01;TE09 -> TP07 -> TK06;TK10
A9: =s001_insights!A7 -> s001M01TP08 | B9: =s001_insights!E7 -> Generative technologies retain tacit organizational knowledge by reactivating prior work practices when new tasks arise. Historical bids are segmented, embedded, stored, and semantically retrieved; relevant examples then ground prompts that generate a methodology draft for expert review. This chain converts fragmented experience into a reusable artifact while preserving links to firm-specific precedent. Retention quality depends on governed documents, adequate corpus breadth, provenance, reviewer correction, infrastructure, and workflow fit. The model cannot contain every contextual judgment, and generated text is not automatically valid knowledge. Its value lies in helping experts recover, adapt, and transmit unwritten practices despite turnover and documentation gaps. | C9: =s001_insights!F7 -> Organizational Culture and Unwritten Working Practices | D9: =s001_insights!G7 -> TE01;TE02;TE04;TE09 -> TP08 -> TK12
A10: =s001_insights!A8 -> s001M01TP09 | B10: =s001_insights!E8 -> Semantic technologies retain tacit knowledge by converting craft sequences into structured entities, metadata, embeddings, relationships, and meaning-based retrieval paths. In the heritage case, a knowledge graph preserves the order and relationships of wooden construction and rammed-earth practices so later users can approach skills beyond the original practitioner. Vector search similarly retrieves related bid examples, although that case lacks an explicit tacit-knowledge link. Codification is therefore partial: structured representations provide durable access but cannot replace demonstration, enactment, or expert correction. Effective retention requires interoperable formats, adequate metadata, sufficient corpus breadth, curation, and opportunities to translate retrieved representations back into competent action. | C10: =s001_insights!F8 -> Practised Motor and Tool-Operation Skill | D10: =s001_insights!G8 -> TE01;TE04 -> TP09 -> TK05
A11: =s001_insights!A9 -> s001M01TP10 | B11: =s001_insights!E9 -> Database technologies retain tacit knowledge by moving experience through elicitation, recording, transcription, curation, tagging, integration, retrieval, and reuse. Data warehouses preserve lessons learned; digital storytelling captures motives, emotions, examples, and interpersonal nuance; OHS databases carry risk information across projects. Together, these systems counter turnover, retirement, temporary teams, fragmented records, and formal documents that omit context. Organizational memory still depends on psychological safety, incentives, privacy safeguards, stewardship, leadership, protected time, and search. Technology shifts expert work toward narration, validation, and interpretation: a stored asset contributes to retention only when later users trust it, retrieve it, and translate it into competent action. | C11: =s001_insights!F9 -> Knowledge Conveyed Through Examples or Demonstration; Unrecognized or Unarticulated Personal Know-how; Practised Motor and Tool-Operation Skill; Shared Professional Norms and Standards of Judgment; Informal Coordination, Communication, and Escalation Know-how; Organizational Culture and Unwritten Working Practices | D11: =s001_insights!G9 -> TE02;TE04;TE05;TE08 -> TP10 -> TK02;TK04;TK05;TK10;TK11;TK12
A12: =s001_insights!A10 -> s001M01TP13 | B12: =s001_insights!E10 -> Assessments assist retention by converting situated judgment and performance into comparable evidence. Forms, web applications, spreadsheets, tests, hazard scenarios, rankings, and OHS indicators record what learners identify, evaluate, remember, and enact. Repeated or delayed measures can reveal knowledge decay, diagnose mismatches, trigger refresher learning, and guide organizational decisions. Yet assessment is a verification layer, not the learning mechanism, and scores cannot represent embodied workplace competence. Its contribution depends on valid constructs, appropriate timing, regulatory alignment, corrective feedback, and later performance in changed settings. When these conditions hold, evaluation stabilizes evidence of professional judgment and helps organizations maintain it over time. | C12: =s001_insights!F10 -> Shared Professional Norms and Standards of Judgment | D12: =s001_insights!G10 -> TE02;TE04 -> TP13 -> TK10
A13: =s001_insights!A11 -> 0 | B13: =s001_insights!E11 -> 0 | C13: =s001_insights!F11 -> 0 | D13: =s001_insights!G11 -> 0
A14: =s001_insights!A12 -> 0 | B14: =s001_insights!E12 -> 0 | C14: =s001_insights!F12 -> 0 | D14: =s001_insights!G12 -> 0
A15: =s001_insights!A13 -> 0 | B15: =s001_insights!E13 -> 0 | C15: =s001_insights!F13 -> 0 | D15: =s001_insights!G13 -> 0
A16: =s001_insights!A14 -> 0 | B16: =s001_insights!E14 -> 0 | C16: =s001_insights!F14 -> 0 | D16: =s001_insights!G14 -> 0
A17: =s001_insights!A15 -> 0 | B17: =s001_insights!E15 -> 0 | C17: =s001_insights!F15 -> 0 | D17: =s001_insights!G15 -> 0
... A21: =s001_insights!A19 -> 0 | B21: =s001_insights!E19 -> 0 | C21: =s001_insights!F19 -> 0 | D21: =s001_insights!G19 -> 0
A22: =s001_insights!A20 -> 0
